Workbook

Sheet Example of Residential SS
A1: OWNER'S SWORN STATEMENT - Example of categories for the Construction of a Residential Home
K2: Title Company File #
B3: Owner: | F3: General Contractor Name: | K3: Phone #
B4: Address of | F4: Person Submitting: | K4: Email address
B5: Improvements: | G5: (authorized person signing sworn statement) | K5: Cell phone #
B7: State of Michigan | D7: ) | G7: (2) The following is a statement of each subcontractor and supplier, and laborer for whom payment of wages or fringe benefits and withholdings is due but unpaid, with whom the (contractor) (subcontractor) has (contracted) (subcontracted) for performance under the contract with the owner or lessee of the property, and the amounts due to the persons as of the date of this statement are correctly and fully set forth opposite their names. (3) The contractor has not procured material from, or subcontracted with, any person other than those set forth and owes no money for the improvement other than the sums set forth. (4) I make this statement as the (contractor) (subcontractor) or as ____________________ of the (contractor) (subcontractor) to represent to the owner or lessee of the property and his or her agents that the property is free from claims of construction liens, or the possibility of construction liens, except as specifically set forth in this statement except for claims of construction liens by laborers that may be provided under Section 109 of the Construction Lien Act, 1980 PA 497, MCL 570.1109.
D8: ) ss.
B9: County of : | D9: )
B11: =IF(G4=0,"",G4) | D11: (deponent), being sworn, states the following:
A12: (1) | B12: =+G3 -> 0 | D12: is the (contractor) (subcontractor) for an improvement to the following real
B13: property in | C13: =+C9 -> 0 | D13: County, Michigan described as follows:
B16: Name of Subcontractor, Supplier or Laborer | D16: Address of Subcontractor, Supplier or Laborer | E16: Telephone # | F16: Type of Improvement Furnished | G16: Total Contract Price | H16: Adjustment to Contract Amount ( +/ -) | I16: Adjusted Contract Price | J16: Amount Already Paid | K16: Current Request | L16: Balance to Complete
A17: 1 | F17: ARCHITECTURAL SERVICES | G17: 0 | H17: 0 | I17: =+G17+H17 -> 0 | L17: =+I17-J17-K17 -> 0
A18: 2 | F18: ENGINEERING SERVICES | G18: 0 | H18: 0 | I18: =+G18+H18 -> 0 | L18: =+I18-J18-K18 -> 0
A19: 3 | F19: EXCAVATING | G19: 0 | H19: 0 | I19: =+G19+H19 -> 0 | L19: =+I19-J19-K19 -> 0
A20: 4 | F20: SAND/GRAVEL/BACKFILL | G20: 0 | H20: 0 | I20: =+G20+H20 -> 0 | L20: =+I20-J20-K20 -> 0
A21: 5 | F21: BASEMENT WALLS | G21: 0 | H21: 0 | I21: =+G21+H21 -> 0 | L21: =+I21-J21-K21 -> 0
A22: 6 | F22: STRUCTURAL STEEL | G22: 0 | H22: 0 | I22: =+G22+H22 -> 0 | L22: =+I22-J22-K22 -> 0
A23: 7 | F23: ROUGH LUMBER/TRUSSES | G23: 0 | H23: 0 | I23: =+G23+H23 -> 0 | L23: =+I23-J23-K23 -> 0
A24: 8 | F24: FINISH LUMBER | G24: 0 | H24: 0 | I24: =+G24+H24 -> 0 | L24: =+I24-J24-K24 -> 0
A25: 9 | F25: ROUGH CARPENTRY | G25: 0 | H25: 0 | I25: =+G25+H25 -> 0 | L25: =+I25-J25-K25 -> 0
A26: 10 | F26: FINISH CARPENTRY | G26: 0 | H26: 0 | I26: =+G26+H26 -> 0 | L26: =+I26-J26-K26 -> 0
A27: 11 | F27: WINDOWS & DOORS | G27: 0 | H27: 0 | I27: =+G27+H27 -> 0 | L27: =+I27-J27-K27 -> 0
A28: 12 | F28: ROOFING LABOR / MATERIALS | G28: 0 | H28: 0 | I28: =+G28+H28 -> 0 | L28: =+I28-J28-K28 -> 0
... A46: 30 | F46: COUNTERTOPS | G46: 0 | H46: 0 | I46: =+G46+H46 -> 0 | L46: =+I46-J46-K46 -> 0
F47: SUBTOTALS | G47: =SUM(G17:G46) -> 0 | H47: =SUM(H17:H46) -> 0 | I47: =SUM(I17:I46) -> 0 | J47: =SUM(J17:J46) -> 0 | K47: =SUM(K17:K46) -> 0 | L47: =SUM(L17:L46) -> 0
B48: WARNING TO OWNER OR LESSEE: An owner or lessee of the property may not rely on this sworn statement to avoid the claim of a subcontractor, supplier, or laborer who has provided a Notice of Furnishing or a laborer who may provide a Notice of Furnishing under Section 109 of the Construction Lien Act, 1980 PA 497, MCL 570.1109, to the designee or to the owner or lessee if the designee is not named or has died.
B52: Name of Subcontractor, Supplier or Laborer | D52: Address of Subcontractor, Supplier or Laborer | E52: Telephone # | F52: Type of Improvement Furnished | G52: Total Contract Price | H52: Adjustment to Contract Amount ( +/ -) | I52: Adjusted Contract Price | J52: Amount Already Paid | K52: Current Request | L52: Balance to Complete
A53: 31 | F53: GARAGE DOOR | G53: 0 | H53: 0 | I53: =+G53+H53 -> 0 | L53: =+I53-J53-K53 -> 0
A54: 32 | F54: FINAL GRADING | G54: 0 | H54: 0 | I54: =+G54+H54 -> 0 | L54: =+I54-J54-K54 -> 0
A55: 33 | F55: ELECTRICAL FIXTURES | G55: 0 | H55: 0 | I55: =+G55+H55 -> 0 | L55: =+I55-J55-K55 -> 0
A56: 34 | F56: CARPETING | G56: 0 | H56: 0 | I56: =+G56+H56 -> 0 | L56: =+I56-J56-K56 -> 0
A57: 35 | F57: FLOOR COVERING | G57: 0 | H57: 0 | I57: =+G57+H57 -> 0 | L57: =+I57-J57-K57 -> 0
A58: 36 | F58: BUILT IN APPLIANCES | G58: 0 | H58: 0 | I58: =+G58+H58 -> 0 | L58: =+I58-J58-K58 -> 0
A59: 37 | F59: WELL | G59: 0 | H59: 0 | I59: =+G59+H59 -> 0 | L59: =+I59-J59-K59 -> 0
A60: 38 | F60: SEPTIC | G60: 0 | H60: 0 | I60: =+G60+H60 -> 0 | L60: =+I60-J60-K60 -> 0
A61: 39 | F61: FIREPLACE | G61: 0 | H61: 0 | I61: =+G61+H61 -> 0 | L61: =+I61-J61-K61 -> 0
A62: 40 | F62: DRIVEWAY PAVING | G62: 0 | H62: 0 | I62: =+G62+H62 -> 0 | L62: =+I62-J62-K62 -> 0
A63: 41 | F63: PERMITS | G63: 0 | H63: 0 | I63: =+G63+H63 -> 0 | L63: =+I63-J63-K63 -> 0
A64: 42 | F64: PAYOFFS | G64: 0 | H64: 0 | I64: =+G64+H64 -> 0 | L64: =+I64-J64-K64 -> 0
... A67: 45 | F67: SIGNAGE | G67: 0 | H67: 0 | I67: =+G67+H67 -> 0 | L67: =+I67-J67-K67 -> 0
A68: 46 | G68: 0 | H68: 0 | I68: =+G68+H68 -> 0 | L68: =+I68-J68-K68 -> 0
A69: 47 | G69: 0 | H69: 0 | I69: =+G69+H69 -> 0 | L69: =+I69-J69-K69 -> 0
A70: 48 | G70: 0 | H70: 0 | I70: =+G70+H70 -> 0 | L70: =+I70-J70-K70 -> 0
A71: 49 | G71: 0 | H71: 0 | I71: =+G71+H71 -> 0 | L71: =+I71-J71-K71 -> 0
A72: 50 | G72: 0 | H72: 0 | I72: =+G72+H72 -> 0 | L72: =+I72-J72-K72 -> 0
A73: 51 | G73: 0 | H73: 0 | I73: =+G73+H73 -> 0 | L73: =+I73-J73-K73 -> 0
A74: 52 | G74: 0 | H74: 0 | I74: =+G74+H74 -> 0 | L74: =+I74-J74-K74 -> 0
A75: 53 | G75: 0 | H75: 0 | I75: =+G75+H75 -> 0 | L75: =+I75-J75-K75 -> 0
A76: 54 | G76: 0 | H76: 0 | I76: =+G76+H76 -> 0 | L76: =+I76-J76-K76 -> 0
A77: 55 | G77: 0 | H77: 0 | I77: =+G77+H77 -> 0 | L77: =+I77-J77-K77 -> 0
A78: 56 | G78: 0 | H78: 0 | I78: =+G78+H78 -> 0 | L78: =+I78-J78-K78 -> 0
A79: 57 | G79: 0 | H79: 0 | I79: =+G79+H79 -> 0 | L79: =+I79-J79-K79 -> 0
... A82: 60 | G82: 0 | H82: 0 | I82: =+G82+H82 -> 0 | L82: =+I82-J82-K82 -> 0
F83: Total | G83: =SUM(G53:G82)+G47 -> 0 | H83: =SUM(H53:H82)+H47 -> 0 | I83: =SUM(I53:I82)+I47 -> 0 | J83: =SUM(J53:J82)+J47 -> 0 | K83: =SUM(K53:K82)+K47 -> 0 | L83: =SUM(L53:L82)+L47 -> 0
B84: If this sworn statement is in regard to a residential structure (defined as "an individual residential condominium unit or a residential building containing not more than 2 residential units,
B85: the land on which it is or will be located, and all appurtenances, in which the owner or lessee contracting for the improvement is residing or will reside upon completion of the improvement"), on
B86: receipt of this sworn statement, the owner or lessee, or the owner's or lessee's designee must give notice of its receipt, either in writing, or by telephone, or personally, to each subcontractor,
B87: supplier, and laborer who has provided a Notice of Furnishing under Section 109 or, if a Notice of Furnishing is excused under Section 108 or 108A, to each subcontractor, supplier, and
B88: laborer named in the sworn statement. If a subcontractor, supplier, or laborer who has provided a Notice of Furnishing or who is named in the sworn statement makes a request, the
B89: owner, lessee, or designee shall provide the requester a copy of the sworn statement within 10 business days after receiving the request.
D92: =IF(B11=0,"",B11)
D93: (DEPONENT) | F93: DATE
B95: WARNING TO DEPONENT: A person gives a false sworn statement with intent to defraud is
B96: subject to criminal penalties as provided in Section 110 of the Construction Lien Act, 1980 PA 497, MCL570.1110.
C99: Subscribed and sworn to before me on | E99: (date) by
G100: Notary Signature
C101: Notary Public | E101: County, Michigan
C103: My Commission expires: | L103: =IF(D4=0,"",D4)

Sheet How to Use Sworn Stmt
A1: How to use this Sworn Statement Template
A3: NOTE: Microsoft Excel is required to use this Sworn Statement.
A5: Entering Information:
A6: 1. Many tabs (worksheets) are located on the bottom of the file:
A7: - Example of Residential Sworn Statement
A8: - How to Use Sworn Statement template
A9: - Master Sworn Statement
A10: - Draw 1
A11: - Draw 2
A13: - Draw 16
A14: - Partial Waiver
A15: - Full Waiver
... A19: Key to navigate through the document. Enter the following:
A20: a. | B20: Owner Name
A21: b. | B21: Contractor Information
A22: i. Company Name
A23: ii. Name of Person submitting sworn statement
A24: iii. Phone #
A25: iv. Email address
A26: v. Cell phone #
A27: c. | B27: Address of the property where construction will take place
A28: d. | B28: County where sworn statement will be Notarized
A29: e. | B29: County Property located in
A30: f. | B30: Names of all Subcontractor, Supplier, or Laborer
A31: g. | B31: Addresses of all Subcontractor, Supplier, or Laborer
A32: h. | B32: Telephone numbers of all Subcontractor, Supplier, or Laborer
A33: i. Company Name | B33: Total Contract Price – should not be changed once initial statement has been submitted
A34: j. | B34: Adjustments – the amount of any change to the initial contract price should be entered in this
B35: column. For increases to the contract price, enter the additional amount. For decreases,
B36: enter (-) and the amount (i.e. -200 to subtract $200 from initial contract amount)
A37: k. | B37: Amount Already Paid – Enter the amounts already paid by the owner prior to first draw
A38: l. | B38: Current Request Column is not available on the Initial Sworn Statement – Amounts requested
B39: must be entered on the specific draw tabs
A41: 3. For each draw requested, Click on the corresponding Draw tab based on the Draw #:
A42: a. | B42: Total Contract Price – is not to be changed once initial statement has been submitted
A43: b. | B43: Adjustments – the amount of any change to the initial contract price is added or subtracted
A44: on the Draw tab. The Adjusted Contract Price column will increase or decrease by the Additional line items (added after initial statement has been submitted) must be | B44: on the Draw tab. The Adjusted Contract Price column will increase or decrease by the
B45: amount input in the Adjustments column. Please offset any adjustment amount with an
B46: adjustment to the Contingency line item in order to keep the net sum of the Adjustments
B47: column at $0.
B48: If you need to add additional line items on subsequent draws (added after initial statement
A49: added in the adjustments column (not the contract price column). | B49: has been submitted) please add the names on the Master tab. THEN return to the draw tab #
B50: corresponding to the current draw and add the dollar amount for the contract in the
B51: "Adjustments" column.
A52: c. | B52: Amount Already Paid is calculated based on amounts of previous draws.
A53: d. | B53: Current Request – enter amounts owed for each Improvement Furnished.
A54: e. | B54: Balance to Complete – this column will calculate automatically.
A57: Using Additional Tabs
A58: 1. Partial Waivers are usually completed by contractor. Subcontractor will sign this form if they received
A59: a partial payment for work completed/supplies furnished. If the subcontractor information is entered
A60: on the sworn statement, then their information can be pulled onto the form. (Auto form currently
A61: not available.)
A62: 2. Full Waivers are usually completed by contractor. Subcontractor will sign this form if they received
A63: full payment for work completed/supplies furnished. If the subcontractor information is entered
A64: on the sworn statement, then their information can be pulled onto the form. (Auto form currently
A65: not available.)
A102: Please note, the information provided herein does not constitute legal advice. For legal advice, please consult
A103: your attorney.

Sheet Master
A1: OWNER'S SWORN STATEMENT
K2: Title Company File #
B3: Owner: | C3: Wolven Investments LLC | F3: General Contractor Name: | G3: Wolven Investments LLC | K3: Phone #
B4: Address of | F4: Person Submitting: | G4: Jeff Klaasen | K4: Email address
B5: Improvements: | C5: 43 North Phase 2 | G5: (authorized person signing sworn statement) | K5: Cell phone #
B7: State of Michigan | D7: ) | G7: (2) The following is a statement of each subcontractor and supplier, and laborer for whom payment of wages or fringe benefits and withholdings is due but unpaid, with whom the (contractor) (subcontractor) has (contracted) (subcontracted) for performance under the contract with the owner or lessee of the property, and the amounts due to the persons as of the date of this statement are correctly and fully set forth opposite their names. (3) The contractor has not procured material from, or subcontracted with, any person other than those set forth and owes no money for the improvement other than the sums set forth. (4) I make this statement as the (contractor) (subcontractor) or as ____________________ of the (contractor) (subcontractor) to represent to the owner or lessee of the property and his or her agents that the property is free from claims of construction liens, or the possibility of construction liens, except as specifically set forth in this statement except for claims of construction liens by laborers that may be provided under Section 109 of the Construction Lien Act, 1980 PA 497, MCL 570.1109.
D8: ) ss.
B9: County of: | C9: Kent | D9: )
B11: =+G4 -> Jeff Klaasen | D11: (deponent), being sworn, states the following:
A12: (1) | B12: Wolven Investmens LLC | D12: is the (contractor) (subcontractor) for an improvement to the following real
B13: property in | C13: =+C9 -> Kent | D13: County, Michigan described as follows:
B16: Name of Subcontractor, Supplier or Laborer | D16: Address of Subcontractor, Supplier or Laborer | E16: Telephone # | F16: Type of Improvement Furnished | G16: Total Contract Price | H16: Adjustment to Contract Amount ( +/ -) | I16: Adjusted Contract Price | J16: Amount Already Paid | K16: Current Request | L16: Balance to Complete
A17: 1 | B17: Jack Dykstra Excavating | D17: 3677 3 Mile Rd., Grand Rapids, MI 49534 | E17: 616-453-4827 | F17: GC Contract Amount | G17: 623097.95 | H17: 0 | I17: =+G17+H17 -> 623097.95 | J17: 138897.29 | L17: =+I17-J17-K17 -> 484200.66
A18: 2 | G18: 0 | H18: 0 | I18: =+G18+H18 -> 0 | J18: 0 | L18: =+I18-J18-K18 -> 0
A19: 3 | B19: Roosien & Associaties | D19: 5055 Plainfield Ave., Grand Rapids, MI 49525 | E19: 616-361-7220 | F19: Engineering Services | G19: 62376 | H19: 0 | I19: =+G19+H19 -> 62376 | J19: 62376 | L19: =+I19-J19-K19 -> 0
A20: 4 | B20: Soils and Structures | D20: 6480 Grand Haven Rd Muskegon MI 49441 | E20: 1-800-933-3959 | F20: Engineering Services | G20: 15930 | H20: 0 | I20: =+G20+H20 -> 15930 | J20: 0 | L20: =+I20-J20-K20 -> 15930
A21: 5 | F21: Engineering Services | G21: =84118.22-62376 -> 21742.22 | H21: 0 | I21: =+G21+H21 -> 21742.22 | L21: =+I21-J21-K21 -> 21742.22
A22: 6 | H22: 0 | I22: =+G22+H22 -> 0 | L22: =+I22-J22-K22 -> 0
A23: 7 | B23: Handicap Sign | D23: 1142 Wealthy St., Grand Rapids, MI 49506 | E23: 616-454-9416 | F23: Common Area Improvements | G23: 424.4 | H23: 0 | I23: =+G23+H23 -> 424.4 | J23: 424.4 | L23: =+I23-J23-K23 -> 0
A24: 8 | B24: Rosendall Well Drilling | D24: 4181 Knapp, Grand Rapids, MI 49525 | E24: 616-363-2683 | F24: Common Area Improvements | G24: 47734 | H24: 0 | I24: =+G24+H24 -> 47734 | J24: 47734 | L24: =+I24-J24-K24 -> 0
A25: 9 | F25: Common Area Improvements | G25: =56373-424.4-47734 -> 8214.6 | H25: 0 | I25: =+G25+H25 -> 8214.6 | L25: =+I25-J25-K25 -> 8214.6
A26: 10 | H26: 0 | I26: =+G26+H26 -> 0 | L26: =+I26-J26-K26 -> 0
A27: 11 | H27: 0 | I27: =+G27+H27 -> 0 | L27: =+I27-J27-K27 -> 0
A28: 12 | H28: 0 | I28: =+G28+H28 -> 0 | L28: =+I28-J28-K28 -> 0
A29: 13 | B29: State of Michigan | D29: Lansing, MI 48909 | F29: Permits and Fees | G29: 800 | H29: 0 | I29: =+G29+H29 -> 800 | J29: 800 | L29: =+I29-J29-K29 -> 0
A30: 14 | B30: Kent County Health Department | D30: 700 Fuller Ave., Grand Rapids, MI 49503 | E30: 616-632-7100 | F30: Permits and Fees | G30: 2635 | H30: 0 | I30: =+G30+H30 -> 2635 | J30: 2635 | L30: =+I30-J30-K30 -> 0
A31: 15 | B31: Kent County Road Commission | D31: 1500 Scribner, Grand Rapids, MI 49504 | E31: 616-242-6900 | F31: Permits and Fees | G31: 13445 | H31: 0 | I31: =+G31+H31 -> 13445 | J31: 13445 | L31: =+I31-J31-K31 -> 0
A32: 16 | B32: Kent County Drain Commission | D32: 1500 Scribner, Grand Rapids, MI 49504 | E32: 616-632-7910 | F32: Permits and Fees | H32: 0 | I32: =+G32+H32 -> 0 | L32: =+I32-J32-K32 -> 0
A33: 17 | B33: Algoma Township | D33: 10531 Algoma Ave., Rockford, MI 49341 | E33: 616-866-1583 | F33: Permits and Fees | G33: =6939+11856 -> 18795 | H33: 0 | I33: =+G33+H33 -> 18795 | J33: =11856+6939 -> 18795 | L33: =+I33-J33-K33 -> 0
A34: 18 | F34: Permits and Fees | G34: =68540.77-15930+1650-800-2635-13445-18795 -> 18585.77 | H34: 0 | I34: =+G34+H34 -> 18585.77 | J34: 0 | L34: =+I34-J34-K34 -> 18585.77
A35: 19 | F35: Electric, Gas, Street Lights | G35: =85320-68518 -> 16802 | H35: 0 | I35: =+G35+H35 -> 16802 | J35: 0 | L35: =+I35-J35-K35 -> 16802
A36: 20 | B36: Consumers Energy | D36: 530 W Willow St. Lansing MI 48909 | E36: 616-530-4210 | F36: Electric, Gas, Street Lights | G36: 68518 | H36: 0 | I36: =+G36+H36 -> 68518 | J36: 0 | L36: =+I36-J36-K36 -> 68518
A37: 21 | B37: DTE Energy | D37: 4420 44th St., Grand Rapids, MI 49512 | E37: 616-278-4720 | F37: Electric, Gas, Street Lights | G37: 0 | H37: 0 | I37: =+G37+H37 -> 0 | J37: 0 | L37: =+I37-J37-K37 -> 0
A38: 22 | F38: Professional Services | G38: =20000-14832.5 -> 5167.5 | H38: 0 | I38: =+G38+H38 -> 5167.5 | L38: =+I38-J38-K38 -> 5167.5
A39: 23 | B39: Rhodes Mckee | D39: 55 Campau Ave. Grand Rapids MI 49503 | E39: 616-235-3500 | F39: Professional Services | G39: 14832.5 | H39: 0 | I39: =+G39+H39 -> 14832.5 | J39: 14832.5 | L39: =+I39-J39-K39 -> 0
A40: 24 | H40: 0 | I40: =+G40+H40 -> 0 | L40: =+I40-J40-K40 -> 0
A41: 25 | I41: =+G41+H41 -> 0 | J41: 0 | L41: =+I41-J41-K41 -> 0
A42: 26 | I42: =+G42+H42 -> 0 | J42: 0 | L42: =+I42-J42-K42 -> 0
A43: 27 | I43: =+G43+H43 -> 0 | L43: =+I43-J43-K43 -> 0
A44: 28 | F44: Contingency | G44: 48532.35 | H44: 0 | I44: =+G44+H44 -> 48532.35 | L44: =+I44-J44-K44 -> 48532.35
A45: 29 | F45: Interest Carry | G45: 46433.43 | H45: 0 | I45: =+G45+H45 -> 46433.43 | L45: =+I45-J45-K45 -> 46433.43
A46: 30 | F46: Land | G46: 234300 | H46: 0 | I46: =+G46+H46 -> 234300 | J46: 234300 | L46: =+I46-J46-K46 -> 0
F47: SUBTOTALS | G47: =SUM(G17:G46) -> 1268365.7 | H47: =SUM(H17:H46) -> 0 | I47: =SUM(I17:I46) -> 1268365.7 | J47: =SUM(J17:J46) -> 534239.19 | K47: =SUM(K17:K46) -> 0 | L47: =SUM(L17:L46) -> 734126.53
B48: WARNING TO OWNER OR LESSEE: An owner or lessee of the property may not rely on this sworn statement to avoid the claim of a subcontractor, supplier, or laborer who has provided a Notice of Furnishing or a laborer who may provide a Notice of Furnishing under Section 109 of the Construction Lien Act, 1980 PA 497, MCL 570.1109, to the designee or to the owner or lessee if the designee is not named or has died.
B52: Name of Subcontractor, Supplier or Laborer | D52: Address of Subcontractor, Supplier or Laborer | E52: Telephone # | F52: Type of Improvement Furnished | G52: Total Contract Price | H52: Adjustment to Contract Amount ( +/ -) | I52: Adjusted Contract Price | J52: Amount Already Paid | K52: Current Request | L52: Balance to Complete
A53: 31 | G53: 0 | H53: 0 | I53: =+G53+H53 -> 0 | J53: 0 | L53: =+I53-J53-K53 -> 0
A54: 32 | G54: 0 | H54: 0 | I54: =+G54+H54 -> 0 | L54: =+I54-J54-K54 -> 0
A55: 33 | G55: 0 | H55: 0 | I55: =+G55+H55 -> 0 | L55: =+I55-J55-K55 -> 0
A56: 34 | G56: 0 | H56: 0 | I56: =+G56+H56 -> 0 | L56: =+I56-J56-K56 -> 0
A57: 35 | G57: 0 | H57: 0 | I57: =+G57+H57 -> 0 | L57: =+I57-J57-K57 -> 0
A58: 36 | G58: 0 | H58: 0 | I58: =+G58+H58 -> 0 | L58: =+I58-J58-K58 -> 0
A59: 37 | G59: 0 | H59: 0 | I59: =+G59+H59 -> 0 | L59: =+I59-J59-K59 -> 0
A60: 38 | G60: 0 | H60: 0 | I60: =+G60+H60 -> 0 | L60: =+I60-J60-K60 -> 0
A61: 39 | G61: 0 | H61: 0 | I61: =+G61+H61 -> 0 | L61: =+I61-J61-K61 -> 0
A62: 40 | G62: 0 | H62: 0 | I62: =+G62+H62 -> 0 | L62: =+I62-J62-K62 -> 0
A63: 41 | G63: 0 | H63: 0 | I63: =+G63+H63 -> 0 | L63: =+I63-J63-K63 -> 0
A64: 42 | G64: 0 | H64: 0 | I64: =+G64+H64 -> 0 | L64: =+I64-J64-K64 -> 0
A65: 43 | G65: 0 | H65: 0 | I65: =+G65+H65 -> 0 | L65: =+I65-J65-K65 -> 0
... A82: 60 | G82: 0 | H82: 0 | I82: =+G82+H82 -> 0 | L82: =+I82-J82-K82 -> 0
F83: Total | G83: =SUM(G53:G82)+G47 -> 1268365.7 | H83: =SUM(H53:H82)+H47 -> 0 | I83: =SUM(I53:I82)+I47 -> 1268365.7 | J83: =SUM(J53:J82)+J47 -> 534239.19 | K83: =SUM(K53:K82)+K47 -> 0 | L83: =SUM(L53:L82)+L47 -> 734126.53
B84: If this sworn statement is in regard to a residential structure (defined as "an individual residential condominium unit or a residential building containing not more than 2 residential units,
B85: the land on which it is or will be located, and all appurtenances, in which the owner or lessee contracting for the improvement is residing or will reside upon completion of the improvement"), on
B86: receipt of this sworn statement, the owner or lessee, or the owner's or lessee's designee must give notice of its receipt, either in writing, or by telephone, or personally, to each subcontractor,
B87: supplier, and laborer who has provided a Notice of Furnishing under Section 109 or, if a Notice of Furnishing is excused under Section 108 or 108A, to each subcontractor, supplier, and
B88: laborer named in the sworn statement. If a subcontractor, supplier, or laborer who has provided a Notice of Furnishing or who is named in the sworn statement makes a request, the
B89: owner, lessee, or designee shall provide the requester a copy of the sworn statement within 10 business days after receiving the request.
D92: =IF(B11=0,"",B11) -> Jeff Klaasen
D93: (DEPONENT) | F93: DATE
B95: WARNING TO DEPONENT: A person gives a false sworn statement with intent to defraud is
B96: subject to criminal penalties as provided in Section 110 of the Construction Lien Act, 1980 PA 497, MCL570.1110.
C99: Subscribed and sworn to before me on | E99: (date) by
G100: Notary Signature
C101: Notary Public | E101: County, Michigan
C103: My Commission expires: | L103: =IF(D4=0,"",D4)

Sheet Draw 1
A1: OWNER'S SWORN STATEMENT - Draw #1
K2: Title Company File # | L2: =+Master!L2 -> 0
B3: Owner: | C3: =+Master!C3 -> Wolven Investments LLC | F3: General Contractor Name: | G3: =+Master!G3 -> Wolven Investments LLC | K3: Phone # | L3: =+Master!L3 -> 0
B4: Address of | F4: Person Submitting: | G4: =+Master!G4 -> Jeff Klaasen | K4: Email address | L4: =+Master!L4 -> 0
B5: Improvements: | C5: =+Master!C5 -> 43 North Phase 2 | G5: (authorized person signing sworn statement) | K5: Cell phone # | L5: =+Master!L5 -> 0
B7: State of Michigan | D7: ) | G7: (2) The following is a statement of each subcontractor and supplier, and laborer for whom payment of wages or fringe benefits and withholdings is due but unpaid, with whom the (contractor) (subcontractor) has (contracted) (subcontracted) for performance under the contract with the owner or lessee of the property, and the amounts due to the persons as of the date of this statement are correctly and fully set forth opposite their names. (3) The contractor has not procured material from, or subcontracted with, any person other than those set forth and owes no money for the improvement other than the sums set forth. (4) I make this statement as the (contractor) (subcontractor) or as ____________________ of the (contractor) (subcontractor) to represent to the owner or lessee of the property and his or her agents that the property is free from claims of construction liens, or the possibility of construction liens, except as specifically set forth in this statement except for claims of construction liens by laborers that may be provided under Section 109 of the Construction Lien Act, 1980 PA 497, MCL 570.1109.
D8: ) ss.
B9: County of: | C9: =+Master!C9 -> Kent | D9: )
B11: =IF(G4=0,"",G4) -> Jeff Klaasen | D11: (deponent), being sworn, states the following:
A12: (1) | B12: =+G3 -> Wolven Investments LLC | D12: is the (contractor) (subcontractor) for an improvement to the following real
B13: property in | C13: =+C9 -> Kent | D13: County, Michigan described as follows:
B16: Name of Subcontractor, Supplier or Laborer | D16: Address of Subcontractor, Supplier or Laborer | E16: Telephone # | F16: Type of Improvement Furnished | G16: Total Contract Price | H16: Adjustment to Contract Amount ( +/ -) | I16: Adjusted Contract Price | J16: Amount Already Paid | K16: Current Request | L16: Balance to Complete
A17: 1 | B17: =IF(Master!$B17=0,"",Master!$B17) -> Jack Dykstra Excavating | D17: =IF(Master!$D17=0,"",Master!$D17) -> 3677 3 Mile Rd., Grand Rapids, MI 49534 | E17: =IF(Master!$E17=0,"",Master!$E17) -> 616-453-4827 | F17: =IF(Master!$F17=0,"",Master!$F17) -> GC Contract Amount | G17: =Master!G17 -> 623097.95 | H17: =Master!H17 -> 0 | I17: =+G17+H17 -> 623097.95 | J17: =Master!J17 -> 138897.29 | K17: 9246 | L17: =+I17-J17-K17 -> 474954.66
A18: 2 | B18: =IF(Master!$B18=0,"",Master!$B18) | D18: =IF(Master!$D18=0,"",Master!$D18) | E18: =IF(Master!$E18=0,"",Master!$E18) | F18: =IF(Master!$F18=0,"",Master!$F18) | G18: =Master!G18 -> 0 | H18: =Master!H18 -> 0 | I18: =+G18+H18 -> 0 | J18: =Master!J18 -> 0 | L18: =+I18-J18-K18 -> 0
A19: 3 | B19: =IF(Master!$B19=0,"",Master!$B19) -> Roosien & Associaties | D19: =IF(Master!$D19=0,"",Master!$D19) -> 5055 Plainfield Ave., Grand Rapids, MI 49525 | E19: =IF(Master!$E19=0,"",Master!$E19) -> 616-361-7220 | F19: =IF(Master!$F19=0,"",Master!$F19) -> Engineering Services | G19: =Master!G19 -> 62376 | H19: =Master!H19 -> 0 | I19: =+G19+H19 -> 62376 | J19: =Master!J19 -> 62376 | L19: =+I19-J19-K19 -> 0
A20: 4 | B20: =IF(Master!$B20=0,"",Master!$B20) -> Soils and Structures | D20: =IF(Master!$D20=0,"",Master!$D20) -> 6480 Grand Haven Rd Muskegon MI 49441 | E20: =IF(Master!$E20=0,"",Master!$E20) -> 1-800-933-3959 | F20: =IF(Master!$F20=0,"",Master!$F20) -> Engineering Services | G20: =Master!G20 -> 15930 | H20: =Master!H20 -> 0 | I20: =+G20+H20 -> 15930 | J20: =Master!J20 -> 0 | L20: =+I20-J20-K20 -> 15930
A21: 5 | B21: =IF(Master!$B21=0,"",Master!$B21) | D21: =IF(Master!$D21=0,"",Master!$D21) | E21: =IF(Master!$E21=0,"",Master!$E21) | F21: =IF(Master!$F21=0,"",Master!$F21) -> Engineering Services | G21: =Master!G21 -> 21742.22 | H21: =Master!H21 -> 0 | I21: =+G21+H21 -> 21742.22 | J21: =Master!J21 -> 0 | L21: =+I21-J21-K21 -> 21742.22
A22: 6 | B22: =IF(Master!$B22=0,"",Master!$B22) | D22: =IF(Master!$D22=0,"",Master!$D22) | E22: =IF(Master!$E22=0,"",Master!$E22) | F22: =IF(Master!$F22=0,"",Master!$F22) | G22: =Master!G22 -> 0 | H22: =Master!H22 -> 0 | I22: =+G22+H22 -> 0 | J22: =Master!J22 -> 0 | L22: =+I22-J22-K22 -> 0
A23: 7 | B23: =IF(Master!$B23=0,"",Master!$B23) -> Handicap Sign | D23: =IF(Master!$D23=0,"",Master!$D23) -> 1142 Wealthy St., Grand Rapids, MI 49506 | E23: =IF(Master!$E23=0,"",Master!$E23) -> 616-454-9416 | F23: =IF(Master!$F23=0,"",Master!$F23) -> Common Area Improvements | G23: =Master!G23 -> 424.4 | H23: =Master!H23 -> 0 | I23: =+G23+H23 -> 424.4 | J23: =Master!J23 -> 424.4 | L23: =+I23-J23-K23 -> 0
A24: 8 | B24: =IF(Master!$B24=0,"",Master!$B24) -> Rosendall Well Drilling | D24: =IF(Master!$D24=0,"",Master!$D24) -> 4181 Knapp, Grand Rapids, MI 49525 | E24: =IF(Master!$E24=0,"",Master!$E24) -> 616-363-2683 | F24: =IF(Master!$F24=0,"",Master!$F24) -> Common Area Improvements | G24: =Master!G24 -> 47734 | H24: =Master!H24 -> 0 | I24: =+G24+H24 -> 47734 | J24: =Master!J24 -> 47734 | L24: =+I24-J24-K24 -> 0
A25: 9 | B25: =IF(Master!$B25=0,"",Master!$B25) | D25: =IF(Master!$D25=0,"",Master!$D25) | E25: =IF(Master!$E25=0,"",Master!$E25) | F25: =IF(Master!$F25=0,"",Master!$F25) -> Common Area Improvements | G25: =Master!G25 -> 8214.6 | H25: =Master!H25 -> 0 | I25: =+G25+H25 -> 8214.6 | J25: =Master!J25 -> 0 | L25: =+I25-J25-K25 -> 8214.6
A26: 10 | B26: =IF(Master!$B26=0,"",Master!$B26) | D26: =IF(Master!$D26=0,"",Master!$D26) | E26: =IF(Master!$E26=0,"",Master!$E26) | F26: =IF(Master!$F26=0,"",Master!$F26) | G26: =Master!G26 -> 0 | H26: =Master!H26 -> 0 | I26: =+G26+H26 -> 0 | J26: =Master!J26 -> 0 | L26: =+I26-J26-K26 -> 0
A27: 11 | B27: =IF(Master!$B27=0,"",Master!$B27) | D27: =IF(Master!$D27=0,"",Master!$D27) | E27: =IF(Master!$E27=0,"",Master!$E27) | F27: =IF(Master!$F27=0,"",Master!$F27) | G27: =Master!G27 -> 0 | H27: =Master!H27 -> 0 | I27: =+G27+H27 -> 0 | J27: =Master!J27 -> 0 | L27: =+I27-J27-K27 -> 0
A28: 12 | B28: =IF(Master!$B28=0,"",Master!$B28) | D28: =IF(Master!$D28=0,"",Master!$D28) | E28: =IF(Master!$E28=0,"",Master!$E28) | F28: =IF(Master!$F28=0,"",Master!$F28) | G28: =Master!G28 -> 0 | H28: =Master!H28 -> 0 | I28: =+G28+H28 -> 0 | J28: =Master!J28 -> 0 | L28: =+I28-J28-K28 -> 0
A29: 13 | B29: =IF(Master!$B29=0,"",Master!$B29) -> State of Michigan | D29: =IF(Master!$D29=0,"",Master!$D29) -> Lansing, MI 48909 | E29: =IF(Master!$E29=0,"",Master!$E29) | F29: =IF(Master!$F29=0,"",Master!$F29) -> Permits and Fees | G29: =Master!G29 -> 800 | H29: =Master!H29 -> 0 | I29: =+G29+H29 -> 800 | J29: =Master!J29 -> 800 | L29: =+I29-J29-K29 -> 0
... A35: 19 | B35: =IF(Master!$B35=0,"",Master!$B35) | D35: =IF(Master!$D35=0,"",Master!$D35) | E35: =IF(Master!$E35=0,"",Master!$E35) | F35: =IF(Master!$F35=0,"",Master!$F35) -> Electric, Gas, Street Lights | G35: =Master!G35 -> 16802 | H35: =Master!H35 -> 0 | I35: =+G35+H35 -> 16802 | J35: =Master!J35 -> 0 | L35: =+I35-J35-K35 -> 16802
A36: 20 | B36: =IF(Master!$B36=0,"",Master!$B36) -> Consumers Energy | D36: =IF(Master!$D36=0,"",Master!$D36) -> 530 W Willow St. Lansing MI 48909 | E36: =IF(Master!$E36=0,"",Master!$E36) -> 616-530-4210 | F36: =IF(Master!$F36=0,"",Master!$F36) -> Electric, Gas, Street Lights | G36: =Master!G36 -> 68518 | H36: =Master!H36 -> 0 | I36: =+G36+H36 -> 68518 | J36: =Master!J36 -> 0 | K36: 68518 | L36: =+I36-J36-K36 -> 0
A37: 21 | B37: =IF(Master!$B37=0,"",Master!$B37) -> DTE Energy | D37: =IF(Master!$D37=0,"",Master!$D37) -> 4420 44th St., Grand Rapids, MI 49512 | E37: =IF(Master!$E37=0,"",Master!$E37) -> 616-278-4720 | F37: =IF(Master!$F37=0,"",Master!$F37) -> Electric, Gas, Street Lights | G37: =Master!G37 -> 0 | H37: =Master!H37 -> 0 | I37: =+G37+H37 -> 0 | J37: =Master!J37 -> 0 | L37: =+I37-J37-K37 -> 0
A38: 22 | B38: =IF(Master!$B38=0,"",Master!$B38) | D38: =IF(Master!$D38=0,"",Master!$D38) | E38: =IF(Master!$E38=0,"",Master!$E38) | F38: =IF(Master!$F38=0,"",Master!$F38) -> Professional Services | G38: =Master!G38 -> 5167.5 | H38: =Master!H38 -> 0 | I38: =+G38+H38 -> 5167.5 | J38: =Master!J38 -> 0 | L38: =+I38-J38-K38 -> 5167.5
A39: 23 | B39: =IF(Master!$B39=0,"",Master!$B39) -> Rhodes Mckee | D39: =IF(Master!$D39=0,"",Master!$D39) -> 55 Campau Ave. Grand Rapids MI 49503 | E39: =IF(Master!$E39=0,"",Master!$E39) -> 616-235-3500 | F39: =IF(Master!$F39=0,"",Master!$F39) -> Professional Services | G39: =Master!G39 -> 14832.5 | H39: =Master!H39 -> 0 | I39: =+G39+H39 -> 14832.5 | J39: =Master!J39 -> 14832.5 | L39: =+I39-J39-K39 -> 0
A40: 24 | B40: =IF(Master!$B40=0,"",Master!$B40) | D40: =IF(Master!$D40=0,"",Master!$D40) | E40: =IF(Master!$E40=0,"",Master!$E40) | F40: =IF(Master!$F40=0,"",Master!$F40) | G40: =Master!G40 -> 0 | H40: =Master!H40 -> 0 | I40: =+G40+H40 -> 0 | J40: =Master!J40 -> 0 | L40: =+I40-J40-K40 -> 0
A41: 25 | B41: =IF(Master!$B41=0,"",Master!$B41) | D41: =IF(Master!$D41=0,"",Master!$D41) | E41: =IF(Master!$E41=0,"",Master!$E41) | F41: =IF(Master!$F41=0,"",Master!$F41) | G41: =Master!G41 -> 0 | H41: =Master!H41 -> 0 | I41: =+G41+H41 -> 0 | J41: =Master!J41 -> 0 | L41: =+I41-J41-K41 -> 0
A42: 26 | B42: =IF(Master!$B42=0,"",Master!$B42) | D42: =IF(Master!$D42=0,"",Master!$D42) | E42: =IF(Master!$E42=0,"",Master!$E42) | F42: =IF(Master!$F42=0,"",Master!$F42) | G42: =Master!G42 -> 0 | H42: =Master!H42 -> 0 | I42: =+G42+H42 -> 0 | J42: =Master!J42 -> 0 | L42: =+I42-J42-K42 -> 0
A43: 27 | B43: =IF(Master!$B43=0,"",Master!$B43) | D43: =IF(Master!$D43=0,"",Master!$D43) | E43: =IF(Master!$E43=0,"",Master!$E43) | F43: =IF(Master!$F43=0,"",Master!$F43) | G43: =Master!G43 -> 0 | H43: =Master!H43 -> 0 | I43: =+G43+H43 -> 0 | J43: =Master!J43 -> 0 | L43: =+I43-J43-K43 -> 0
A44: 28 | B44: =IF(Master!$B44=0,"",Master!$B44) | D44: =IF(Master!$D44=0,"",Master!$D44) | E44: =IF(Master!$E44=0,"",Master!$E44) | F44: =IF(Master!$F44=0,"",Master!$F44) -> Contingency | G44: =Master!G44 -> 48532.35 | H44: =Master!H44 -> 0 | I44: =+G44+H44 -> 48532.35 | J44: =Master!J44 -> 0 | L44: =+I44-J44-K44 -> 48532.35
A45: 29 | B45: =IF(Master!$B45=0,"",Master!$B45) | D45: =IF(Master!$D45=0,"",Master!$D45) | E45: =IF(Master!$E45=0,"",Master!$E45) | F45: =IF(Master!$F45=0,"",Master!$F45) -> Interest Carry | G45: =Master!G45 -> 46433.43 | H45: =Master!H45 -> 0 | I45: =+G45+H45 -> 46433.43 | J45: =Master!J45 -> 0 | L45: =+I45-J45-K45 -> 46433.43
A46: 30 | B46: =IF(Master!$B46=0,"",Master!$B46) | D46: =IF(Master!$D46=0,"",Master!$D46) | E46: =IF(Master!$E46=0,"",Master!$E46) | F46: =IF(Master!$F46=0,"",Master!$F46) -> Land | G46: =Master!G46 -> 234300 | H46: =Master!H46 -> 0 | I46: =+G46+H46 -> 234300 | J46: =Master!J46 -> 234300 | L46: =+I46-J46-K46 -> 0
F47: SUBTOTALS | G47: =SUM(G17:G46) -> 1268365.7 | H47: =SUM(H17:H46) -> 0 | I47: =SUM(I17:I46) -> 1268365.7 | J47: =SUM(J17:J46) -> 534239.19 | K47: =SUM(K17:K46) -> 77764 | L47: =SUM(L17:L46) -> 656362.53
B48: WARNING TO OWNER OR LESSEE: An owner or lessee of the property may not rely on this sworn statement to avoid the claim of a subcontractor, supplier, or laborer who has provided a Notice of Furnishing or a laborer who may provide a Notice of Furnishing under Section 109 of the Construction Lien Act, 1980 PA 497, MCL 570.1109, to the designee or to the owner or lessee if the designee is not named or has died.
B52: Name of Subcontractor, Supplier or Laborer | D52: Address of Subcontractor, Supplier or Laborer | E52: Telephone # | F52: Type of Improvement Furnished | G52: Total Contract Price | H52: Adjustment to Contract Amount ( +/ -) | I52: Adjusted Contract Price | J52: Amount Already Paid | K52: Current Request | L52: Balance to Complete
A53: 31 | B53: =IF(Master!$B53=0,"",Master!$B53) | D53: =IF(Master!$D53=0,"",Master!$D53) | E53: =IF(Master!$E53=0,"",Master!$E53) | F53: =IF(Master!$F53=0,"",Master!$F53) | G53: =Master!G53 -> 0 | H53: =Master!H53 -> 0 | I53: =+G53+H53 -> 0 | J53: =Master!J53 -> 0 | L53: =+I53-J53-K53 -> 0
A54: 32 | B54: =IF(Master!$B54=0,"",Master!$B54) | D54: =IF(Master!$D54=0,"",Master!$D54) | E54: =IF(Master!$E54=0,"",Master!$E54) | F54: =IF(Master!$F54=0,"",Master!$F54) | G54: =Master!G54 -> 0 | H54: =Master!H54 -> 0 | I54: =+G54+H54 -> 0 | J54: =Master!J54 -> 0 | L54: =+I54-J54-K54 -> 0
A55: 33 | B55: =IF(Master!$B55=0,"",Master!$B55) | D55: =IF(Master!$D55=0,"",Master!$D55) | E55: =IF(Master!$E55=0,"",Master!$E55) | F55: =IF(Master!$F55=0,"",Master!$F55) | G55: =Master!G55 -> 0 | H55: =Master!H55 -> 0 | I55: =+G55+H55 -> 0 | J55: =Master!J55 -> 0 | L55: =+I55-J55-K55 -> 0
A56: 34 | B56: =IF(Master!$B56=0,"",Master!$B56) | D56: =IF(Master!$D56=0,"",Master!$D56) | E56: =IF(Master!$E56=0,"",Master!$E56) | F56: =IF(Master!$F56=0,"",Master!$F56) | G56: =Master!G56 -> 0 | H56: =Master!H56 -> 0 | I56: =+G56+H56 -> 0 | J56: =Master!J56 -> 0 | L56: =+I56-J56-K56 -> 0
A57: 35 | B57: =IF(Master!$B57=0,"",Master!$B57) | D57: =IF(Master!$D57=0,"",Master!$D57) | E57: =IF(Master!$E57=0,"",Master!$E57) | F57: =IF(Master!$F57=0,"",Master!$F57) | G57: =Master!G57 -> 0 | H57: =Master!H57 -> 0 | I57: =+G57+H57 -> 0 | J57: =Master!J57 -> 0 | L57: =+I57-J57-K57 -> 0
A58: 36 | B58: =IF(Master!$B58=0,"",Master!$B58) | D58: =IF(Master!$D58=0,"",Master!$D58) | E58: =IF(Master!$E58=0,"",Master!$E58) | F58: =IF(Master!$F58=0,"",Master!$F58) | G58: =Master!G58 -> 0 | H58: =Master!H58 -> 0 | I58: =+G58+H58 -> 0 | J58: =Master!J58 -> 0 | L58: =+I58-J58-K58 -> 0
A59: 37 | B59: =IF(Master!$B59=0,"",Master!$B59) | D59: =IF(Master!$D59=0,"",Master!$D59) | E59: =IF(Master!$E59=0,"",Master!$E59) | F59: =IF(Master!$F59=0,"",Master!$F59) | G59: =Master!G59 -> 0 | H59: =Master!H59 -> 0 | I59: =+G59+H59 -> 0 | J59: =Master!J59 -> 0 | L59: =+I59-J59-K59 -> 0
A60: 38 | B60: =IF(Master!$B60=0,"",Master!$B60) | D60: =IF(Master!$D60=0,"",Master!$D60) | E60: =IF(Master!$E60=0,"",Master!$E60) | F60: =IF(Master!$F60=0,"",Master!$F60) | G60: =Master!G60 -> 0 | H60: =Master!H60 -> 0 | I60: =+G60+H60 -> 0 | J60: =Master!J60 -> 0 | L60: =+I60-J60-K60 -> 0
A61: 39 | B61: =IF(Master!$B61=0,"",Master!$B61) | D61: =IF(Master!$D61=0,"",Master!$D61) | E61: =IF(Master!$E61=0,"",Master!$E61) | F61: =IF(Master!$F61=0,"",Master!$F61) | G61: =Master!G61 -> 0 | H61: =Master!H61 -> 0 | I61: =+G61+H61 -> 0 | J61: =Master!J61 -> 0 | L61: =+I61-J61-K61 -> 0
A62: 40 | B62: =IF(Master!$B62=0,"",Master!$B62) | D62: =IF(Master!$D62=0,"",Master!$D62) | E62: =IF(Master!$E62=0,"",Master!$E62) | F62: =IF(Master!$F62=0,"",Master!$F62) | G62: =Master!G62 -> 0 | H62: =Master!H62 -> 0 | I62: =+G62+H62 -> 0 | J62: =Master!J62 -> 0 | L62: =+I62-J62-K62 -> 0
A63: 41 | B63: =IF(Master!$B63=0,"",Master!$B63) | D63: =IF(Master!$D63=0,"",Master!$D63) | E63: =IF(Master!$E63=0,"",Master!$E63) | F63: =IF(Master!$F63=0,"",Master!$F63) | G63: =Master!G63 -> 0 | H63: =Master!H63 -> 0 | I63: =+G63+H63 -> 0 | J63: =Master!J63 -> 0 | L63: =+I63-J63-K63 -> 0
A64: 42 | B64: =IF(Master!$B64=0,"",Master!$B64) | D64: =IF(Master!$D64=0,"",Master!$D64) | E64: =IF(Master!$E64=0,"",Master!$E64) | F64: =IF(Master!$F64=0,"",Master!$F64) | G64: =Master!G64 -> 0 | H64: =Master!H64 -> 0 | I64: =+G64+H64 -> 0 | J64: =Master!J64 -> 0 | L64: =+I64-J64-K64 -> 0
... A82: 60 | B82: =IF(Master!$B82=0,"",Master!$B82) | D82: =IF(Master!$D82=0,"",Master!$D82) | E82: =IF(Master!$E82=0,"",Master!$E82) | F82: =IF(Master!$F82=0,"",Master!$F82) | G82: =Master!G82 -> 0 | H82: =Master!H82 -> 0 | I82: =+G82+H82 -> 0 | J82: =Master!J82 -> 0 | L82: =+I82-J82-K82 -> 0
F83: Total | G83: =SUM(G53:G82)+G47 -> 1268365.7 | H83: =SUM(H53:H82)+H47 -> 0 | I83: =SUM(I53:I82)+I47 -> 1268365.7 | J83: =SUM(J53:J82)+J47 -> 534239.19 | K83: =SUM(K53:K82)+K47 -> 77764 | L83: =SUM(L53:L82)+L47 -> 656362.53
B84: If this sworn statement is in regard to a residential structure (defined as "an individual residential condominium unit or a residential building containing not more than 2 residential units,
B85: the land on which it is or will be located, and all appurtenances, in which the owner or lessee contracting for the improvement is residing or will reside upon completion of the improvement"), on
B86: receipt of this sworn statement, the owner or lessee, or the owner's or lessee's designee must give notice of its receipt, either in writing, or by telephone, or personally, to each subcontractor,
B87: supplier, and laborer who has provided a Notice of Furnishing under Section 109 or, if a Notice of Furnishing is excused under Section 108 or 108A, to each subcontractor, supplier, and
B88: laborer named in the sworn statement. If a subcontractor, supplier, or laborer who has provided a Notice of Furnishing or who is named in the sworn statement makes a request, the
B89: owner, lessee, or designee shall provide the requester a copy of the sworn statement within 10 business days after receiving the request.
D92: ='Example of Residential SS'!D92
D93: (DEPONENT) | F93: DATE
B95: WARNING TO DEPONENT: A person gives a false sworn statement with intent to defraud is
B96: subject to criminal penalties as provided in Section 110 of the Construction Lien Act, 1980 PA 497, MCL570.1110.
C99: Subscribed and sworn to before me on | E99: (date) by
C101: Notary Public | E101: County, Michigan
C103: My Commission expires: | L103: =IF('Example of Residential SS'!L103=0,"",'Example of Residential SS'!L103)

Sheet Draw 2
A1: OWNER'S SWORN STATEMENT - Draw #2
K2: Title Company File #
B3: Owner: | C3: =+Master!C3 -> Wolven Investments LLC | F3: General Contractor Name: | G3: =+Master!G3 -> Wolven Investments LLC | K3: Phone # | L3: =+Master!L3 -> 0
B4: Address of | F4: Person Submitting: | G4: =+Master!G4 -> Jeff Klaasen | K4: Email address | L4: =+Master!L4 -> 0
B5: Improvements: | C5: =+Master!C5 -> 43 North Phase 2 | G5: (authorized person signing sworn statement) | K5: Cell phone # | L5: =+Master!L5 -> 0
B7: State of Michigan | D7: ) | G7: (2) The following is a statement of each subcontractor and supplier, and laborer for whom payment of wages or fringe benefits and withholdings is due but unpaid, with whom the (contractor) (subcontractor) has (contracted) (subcontracted) for performance under the contract with the owner or lessee of the property, and the amounts due to the persons as of the date of this statement are correctly and fully set forth opposite their names. (3) The contractor has not procured material from, or subcontracted with, any person other than those set forth and owes no money for the improvement other than the sums set forth. (4) I make this statement as the (contractor) (subcontractor) or as ____________________ of the (contractor) (subcontractor) to represent to the owner or lessee of the property and his or her agents that the property is free from claims of construction liens, or the possibility of construction liens, except as specifically set forth in this statement except for claims of construction liens by laborers that may be provided under Section 109 of the Construction Lien Act, 1980 PA 497, MCL 570.1109.
D8: ) ss.
B9: County of: | C9: =+Master!C9 -> Kent | D9: )
B11: =IF(G4=0,"",G4) -> Jeff Klaasen | D11: (deponent), being sworn, states the following:
A12: (1) | B12: =+G3 -> Wolven Investments LLC | D12: is the (contractor) (subcontractor) for an improvement to the following real
B13: property in | C13: =+C9 -> Kent | D13: County, Michigan described as follows:
B16: Name of Subcontractor, Supplier or Laborer | D16: Address of Subcontractor, Supplier or Laborer | E16: Telephone # | F16: Type of Improvement Furnished | G16: Total Contract Price | H16: Adjustment to Contract Amount ( +/ -) | I16: Adjusted Contract Price | J16: Amount Already Paid | K16: Current Request | L16: Balance to Complete
A17: 1 | B17: =IF(Master!$B17=0,"",Master!$B17) -> Jack Dykstra Excavating | D17: =IF(Master!$D17=0,"",Master!$D17) -> 3677 3 Mile Rd., Grand Rapids, MI 49534 | E17: =IF(Master!$E17=0,"",Master!$E17) -> 616-453-4827 | F17: =IF(Master!$F17=0,"",Master!$F17) -> GC Contract Amount | G17: =Master!G17 -> 623097.95 | H17: 1228.5 | I17: =+G17+H17 -> 624326.45 | J17: ='Draw 1'!J17+'Draw 1'!K17 -> 148143.29 | K17: 276327.66 | L17: =+I17-J17-K17 -> 199855.5
A18: 2 | B18: =IF(Master!$B18=0,"",Master!$B18) | D18: =IF(Master!$D18=0,"",Master!$D18) | E18: =IF(Master!$E18=0,"",Master!$E18) | F18: =IF(Master!$F18=0,"",Master!$F18) | G18: =Master!G18 -> 0 | H18: =+'Draw 1'!H18 -> 0 | I18: =+G18+H18 -> 0 | J18: ='Draw 1'!J18+'Draw 1'!K18 -> 0 | L18: =+I18-J18-K18 -> 0
A19: 3 | B19: =IF(Master!$B19=0,"",Master!$B19) -> Roosien & Associaties | D19: =IF(Master!$D19=0,"",Master!$D19) -> 5055 Plainfield Ave., Grand Rapids, MI 49525 | E19: =IF(Master!$E19=0,"",Master!$E19) -> 616-361-7220 | F19: =IF(Master!$F19=0,"",Master!$F19) -> Engineering Services | G19: =Master!G19 -> 62376 | H19: 8555 | I19: =+G19+H19 -> 70931 | J19: ='Draw 1'!J19+'Draw 1'!K19 -> 62376 | K19: =1220+4980+2355 -> 8555 | L19: =+I19-J19-K19 -> 0
A20: 4 | B20: =IF(Master!$B20=0,"",Master!$B20) -> Soils and Structures | D20: =IF(Master!$D20=0,"",Master!$D20) -> 6480 Grand Haven Rd Muskegon MI 49441 | E20: =IF(Master!$E20=0,"",Master!$E20) -> 1-800-933-3959 | F20: =IF(Master!$F20=0,"",Master!$F20) -> Engineering Services | G20: =Master!G20 -> 15930 | H20: =+'Draw 1'!H20 -> 0 | I20: =+G20+H20 -> 15930 | J20: ='Draw 1'!J20+'Draw 1'!K20 -> 0 | K20: 1158.5 | L20: =+I20-J20-K20 -> 14771.5
A21: 5 | B21: =IF(Master!$B21=0,"",Master!$B21) | D21: =IF(Master!$D21=0,"",Master!$D21) | E21: =IF(Master!$E21=0,"",Master!$E21) | F21: =IF(Master!$F21=0,"",Master!$F21) -> Engineering Services | G21: =Master!G21 -> 21742.22 | H21: =+'Draw 1'!H21-8555 -> -8555 | I21: =+G21+H21 -> 13187.22 | J21: ='Draw 1'!J21+'Draw 1'!K21 -> 0 | L21: =+I21-J21-K21 -> 13187.22
A22: 6 | B22: =IF(Master!$B22=0,"",Master!$B22) | D22: =IF(Master!$D22=0,"",Master!$D22) | E22: =IF(Master!$E22=0,"",Master!$E22) | F22: =IF(Master!$F22=0,"",Master!$F22) | G22: =Master!G22 -> 0 | H22: =+'Draw 1'!H22 -> 0 | I22: =+G22+H22 -> 0 | J22: ='Draw 1'!J22+'Draw 1'!K22 -> 0 | L22: =+I22-J22-K22 -> 0
A23: 7 | B23: =IF(Master!$B23=0,"",Master!$B23) -> Handicap Sign | D23: =IF(Master!$D23=0,"",Master!$D23) -> 1142 Wealthy St., Grand Rapids, MI 49506 | E23: =IF(Master!$E23=0,"",Master!$E23) -> 616-454-9416 | F23: =IF(Master!$F23=0,"",Master!$F23) -> Common Area Improvements | G23: =Master!G23 -> 424.4 | H23: =+'Draw 1'!H23 -> 0 | I23: =+G23+H23 -> 424.4 | J23: ='Draw 1'!J23+'Draw 1'!K23 -> 424.4 | L23: =+I23-J23-K23 -> 0
A24: 8 | B24: =IF(Master!$B24=0,"",Master!$B24) -> Rosendall Well Drilling | D24: =IF(Master!$D24=0,"",Master!$D24) -> 4181 Knapp, Grand Rapids, MI 49525 | E24: =IF(Master!$E24=0,"",Master!$E24) -> 616-363-2683 | F24: =IF(Master!$F24=0,"",Master!$F24) -> Common Area Improvements | G24: =Master!G24 -> 47734 | H24: =+'Draw 1'!H24 -> 0 | I24: =+G24+H24 -> 47734 | J24: ='Draw 1'!J24+'Draw 1'!K24 -> 47734 | L24: =+I24-J24-K24 -> 0
A25: 9 | B25: =IF(Master!$B25=0,"",Master!$B25) | D25: =IF(Master!$D25=0,"",Master!$D25) | E25: =IF(Master!$E25=0,"",Master!$E25) | F25: =IF(Master!$F25=0,"",Master!$F25) -> Common Area Improvements | G25: =Master!G25 -> 8214.6 | H25: =+'Draw 1'!H25 -> 0 | I25: =+G25+H25 -> 8214.6 | J25: ='Draw 1'!J25+'Draw 1'!K25 -> 0 | L25: =+I25-J25-K25 -> 8214.6
A26: 10 | B26: =IF(Master!$B26=0,"",Master!$B26) | D26: =IF(Master!$D26=0,"",Master!$D26) | E26: =IF(Master!$E26=0,"",Master!$E26) | F26: =IF(Master!$F26=0,"",Master!$F26) | G26: =Master!G26 -> 0 | H26: =+'Draw 1'!H26 -> 0 | I26: =+G26+H26 -> 0 | J26: ='Draw 1'!J26+'Draw 1'!K26 -> 0 | L26: =+I26-J26-K26 -> 0
A27: 11 | B27: =IF(Master!$B27=0,"",Master!$B27) | D27: =IF(Master!$D27=0,"",Master!$D27) | E27: =IF(Master!$E27=0,"",Master!$E27) | F27: =IF(Master!$F27=0,"",Master!$F27) | G27: =Master!G27 -> 0 | H27: =+'Draw 1'!H27 -> 0 | I27: =+G27+H27 -> 0 | J27: ='Draw 1'!J27+'Draw 1'!K27 -> 0 | L27: =+I27-J27-K27 -> 0
A28: 12 | B28: =IF(Master!$B28=0,"",Master!$B28) | D28: =IF(Master!$D28=0,"",Master!$D28) | E28: =IF(Master!$E28=0,"",Master!$E28) | F28: =IF(Master!$F28=0,"",Master!$F28) | G28: =Master!G28 -> 0 | H28: =+'Draw 1'!H28 -> 0 | I28: =+G28+H28 -> 0 | J28: ='Draw 1'!J28+'Draw 1'!K28 -> 0 | L28: =+I28-J28-K28 -> 0
A29: 13 | B29: =IF(Master!$B29=0,"",Master!$B29) -> State of Michigan | D29: =IF(Master!$D29=0,"",Master!$D29) -> Lansing, MI 48909 | E29: =IF(Master!$E29=0,"",Master!$E29) | F29: =IF(Master!$F29=0,"",Master!$F29) -> Permits and Fees | G29: =Master!G29 -> 800 | H29: =+'Draw 1'!H29 -> 0 | I29: =+G29+H29 -> 800 | J29: ='Draw 1'!J29+'Draw 1'!K29 -> 800 | L29: =+I29-J29-K29 -> 0
A30: 14 | B30: =IF(Master!$B30=0,"",Master!$B30) -> Kent County Health Department | D30: =IF(Master!$D30=0,"",Master!$D30) -> 700 Fuller Ave., Grand Rapids, MI 49503 | E30: =IF(Master!$E30=0,"",Master!$E30) -> 616-632-7100 | F30: =IF(Master!$F30=0,"",Master!$F30) -> Permits and Fees | G30: =Master!G30 -> 2635 | H30: =+'Draw 1'!H30 -> 0 | I30: =+G30+H30 -> 2635 | J30: ='Draw 1'!J30+'Draw 1'!K30 -> 2635 | L30: =+I30-J30-K30 -> 0
A31: 15 | B31: =IF(Master!$B31=0,"",Master!$B31) -> Kent County Road Commission | D31: =IF(Master!$D31=0,"",Master!$D31) -> 1500 Scribner, Grand Rapids, MI 49504 | E31: =IF(Master!$E31=0,"",Master!$E31) -> 616-242-6900 | F31: =IF(Master!$F31=0,"",Master!$F31) -> Permits and Fees | G31: =Master!G31 -> 13445 | H31: =+'Draw 1'!H31 -> 0 | I31: =+G31+H31 -> 13445 | J31: ='Draw 1'!J31+'Draw 1'!K31 -> 13445 | L31: =+I31-J31-K31 -> 0
A32: 16 | B32: =IF(Master!$B32=0,"",Master!$B32) -> Kent County Drain Commission | D32: =IF(Master!$D32=0,"",Master!$D32) -> 1500 Scribner, Grand Rapids, MI 49504 | E32: =IF(Master!$E32=0,"",Master!$E32) -> 616-632-7910 | F32: =IF(Master!$F32=0,"",Master!$F32) -> Permits and Fees | G32: =Master!G32 -> 0 | H32: =+'Draw 1'!H32 -> 0 | I32: =+G32+H32 -> 0 | J32: ='Draw 1'!J32+'Draw 1'!K32 -> 0 | L32: =+I32-J32-K32 -> 0
A33: 17 | B33: =IF(Master!$B33=0,"",Master!$B33) -> Algoma Township | D33: =IF(Master!$D33=0,"",Master!$D33) -> 10531 Algoma Ave., Rockford, MI 49341 | E33: =IF(Master!$E33=0,"",Master!$E33) -> 616-866-1583 | F33: =IF(Master!$F33=0,"",Master!$F33) -> Permits and Fees | G33: =Master!G33 -> 18795 | H33: =+'Draw 1'!H33 -> 0 | I33: =+G33+H33 -> 18795 | J33: ='Draw 1'!J33+'Draw 1'!K33 -> 18795 | L33: =+I33-J33-K33 -> 0
... A43: 27 | B43: =IF(Master!$B43=0,"",Master!$B43) | D43: =IF(Master!$D43=0,"",Master!$D43) | E43: =IF(Master!$E43=0,"",Master!$E43) | F43: =IF(Master!$F43=0,"",Master!$F43) | G43: =Master!G43 -> 0 | H43: =+'Draw 1'!H43 -> 0 | I43: =+G43+H43 -> 0 | J43: ='Draw 1'!J43+'Draw 1'!K43 -> 0 | L43: =+I43-J43-K43 -> 0
A44: 28 | B44: =IF(Master!$B44=0,"",Master!$B44) | D44: =IF(Master!$D44=0,"",Master!$D44) | E44: =IF(Master!$E44=0,"",Master!$E44) | F44: =IF(Master!$F44=0,"",Master!$F44) -> Contingency | G44: =Master!G44 -> 48532.35 | H44: -1228.5 | I44: =+G44+H44 -> 47303.85 | J44: ='Draw 1'!J44+'Draw 1'!K44 -> 0 | L44: =+I44-J44-K44 -> 47303.85
A45: 29 | B45: =IF(Master!$B45=0,"",Master!$B45) | D45: =IF(Master!$D45=0,"",Master!$D45) | E45: =IF(Master!$E45=0,"",Master!$E45) | F45: =IF(Master!$F45=0,"",Master!$F45) -> Interest Carry | G45: =Master!G45 -> 46433.43 | H45: =+'Draw 1'!H45 -> 0 | I45: =+G45+H45 -> 46433.43 | J45: ='Draw 1'!J45+'Draw 1'!K45 -> 0 | L45: =+I45-J45-K45 -> 46433.43
A46: 30 | B46: =IF(Master!$B46=0,"",Master!$B46) | D46: =IF(Master!$D46=0,"",Master!$D46) | E46: =IF(Master!$E46=0,"",Master!$E46) | F46: =IF(Master!$F46=0,"",Master!$F46) -> Land | G46: =Master!G46 -> 234300 | H46: =+'Draw 1'!H46 -> 0 | I46: =+G46+H46 -> 234300 | J46: ='Draw 1'!J46+'Draw 1'!K46 -> 234300 | L46: =+I46-J46-K46 -> 0
F47: SUBTOTALS | G47: =SUM(G17:G46) -> 1268365.7 | H47: =SUM(H17:H46) -> 0 | I47: =SUM(I17:I46) -> 1268365.7 | J47: =SUM(J17:J46) -> 612003.19 | K47: =SUM(K17:K46) -> 286041.16 | L47: =SUM(L17:L46) -> 370321.37
B48: WARNING TO OWNER OR LESSEE: An owner or lessee of the property may not rely on this sworn statement to avoid the claim of a subcontractor, supplier, or laborer who has provided a Notice of Furnishing or a laborer who may provide a Notice of Furnishing under Section 109 of the Construction Lien Act, 1980 PA 497, MCL 570.1109, to the designee or to the owner or lessee if the designee is not named or has died.
B52: Name of Subcontractor, Supplier or Laborer | D52: Address of Subcontractor, Supplier or Laborer | E52: Telephone # | F52: Type of Improvement Furnished | G52: Total Contract Price | H52: Adjustment to Contract Amount ( +/ -) | I52: Adjusted Contract Price | J52: Amount Already Paid | K52: Current Request | L52: Balance to Complete
A53: 31 | B53: =IF(Master!$B53=0,"",Master!$B53) | D53: =IF(Master!$D53=0,"",Master!$D53) | E53: =IF(Master!$E53=0,"",Master!$E53) | F53: =IF(Master!$F53=0,"",Master!$F53) | G53: =Master!G53 -> 0 | H53: =+'Draw 1'!H53 -> 0 | I53: =+G53+H53 -> 0 | J53: ='Draw 1'!J53+'Draw 1'!K53 -> 0 | L53: =+I53-J53-K53 -> 0
A54: 32 | B54: =IF(Master!$B54=0,"",Master!$B54) | D54: =IF(Master!$D54=0,"",Master!$D54) | E54: =IF(Master!$E54=0,"",Master!$E54) | F54: =IF(Master!$F54=0,"",Master!$F54) | G54: =Master!G54 -> 0 | H54: =+'Draw 1'!H54 -> 0 | I54: =+G54+H54 -> 0 | J54: ='Draw 1'!J54+'Draw 1'!K54 -> 0 | L54: =+I54-J54-K54 -> 0
A55: 33 | B55: =IF(Master!$B55=0,"",Master!$B55) | D55: =IF(Master!$D55=0,"",Master!$D55) | E55: =IF(Master!$E55=0,"",Master!$E55) | F55: =IF(Master!$F55=0,"",Master!$F55) | G55: =Master!G55 -> 0 | H55: =+'Draw 1'!H55 -> 0 | I55: =+G55+H55 -> 0 | J55: ='Draw 1'!J55+'Draw 1'!K55 -> 0 | L55: =+I55-J55-K55 -> 0
A56: 34 | B56: =IF(Master!$B56=0,"",Master!$B56) | D56: =IF(Master!$D56=0,"",Master!$D56) | E56: =IF(Master!$E56=0,"",Master!$E56) | F56: =IF(Master!$F56=0,"",Master!$F56) | G56: =Master!G56 -> 0 | H56: =+'Draw 1'!H56 -> 0 | I56: =+G56+H56 -> 0 | J56: ='Draw 1'!J56+'Draw 1'!K56 -> 0 | L56: =+I56-J56-K56 -> 0
A57: 35 | B57: =IF(Master!$B57=0,"",Master!$B57) | D57: =IF(Master!$D57=0,"",Master!$D57) | E57: =IF(Master!$E57=0,"",Master!$E57) | F57: =IF(Master!$F57=0,"",Master!$F57) | G57: =Master!G57 -> 0 | H57: =+'Draw 1'!H57 -> 0 | I57: =+G57+H57 -> 0 | J57: ='Draw 1'!J57+'Draw 1'!K57 -> 0 | L57: =+I57-J57-K57 -> 0
A58: 36 | B58: =IF(Master!$B58=0,"",Master!$B58) | D58: =IF(Master!$D58=0,"",Master!$D58) | E58: =IF(Master!$E58=0,"",Master!$E58) | F58: =IF(Master!$F58=0,"",Master!$F58) | G58: =Master!G58 -> 0 | H58: =+'Draw 1'!H58 -> 0 | I58: =+G58+H58 -> 0 | J58: ='Draw 1'!J58+'Draw 1'!K58 -> 0 | L58: =+I58-J58-K58 -> 0
A59: 37 | B59: =IF(Master!$B59=0,"",Master!$B59) | D59: =IF(Master!$D59=0,"",Master!$D59) | E59: =IF(Master!$E59=0,"",Master!$E59) | F59: =IF(Master!$F59=0,"",Master!$F59) | G59: =Master!G59 -> 0 | H59: =+'Draw 1'!H59 -> 0 | I59: =+G59+H59 -> 0 | J59: ='Draw 1'!J59+'Draw 1'!K59 -> 0 | L59: =+I59-J59-K59 -> 0
A60: 38 | B60: =IF(Master!$B60=0,"",Master!$B60) | D60: =IF(Master!$D60=0,"",Master!$D60) | E60: =IF(Master!$E60=0,"",Master!$E60) | F60: =IF(Master!$F60=0,"",Master!$F60) | G60: =Master!G60 -> 0 | H60: =+'Draw 1'!H60 -> 0 | I60: =+G60+H60 -> 0 | J60: ='Draw 1'!J60+'Draw 1'!K60 -> 0 | L60: =+I60-J60-K60 -> 0
A61: 39 | B61: =IF(Master!$B61=0,"",Master!$B61) | D61: =IF(Master!$D61=0,"",Master!$D61) | E61: =IF(Master!$E61=0,"",Master!$E61) | F61: =IF(Master!$F61=0,"",Master!$F61) | G61: =Master!G61 -> 0 | H61: =+'Draw 1'!H61 -> 0 | I61: =+G61+H61 -> 0 | J61: ='Draw 1'!J61+'Draw 1'!K61 -> 0 | L61: =+I61-J61-K61 -> 0
A62: 40 | B62: =IF(Master!$B62=0,"",Master!$B62) | D62: =IF(Master!$D62=0,"",Master!$D62) | E62: =IF(Master!$E62=0,"",Master!$E62) | F62: =IF(Master!$F62=0,"",Master!$F62) | G62: =Master!G62 -> 0 | H62: =+'Draw 1'!H62 -> 0 | I62: =+G62+H62 -> 0 | J62: ='Draw 1'!J62+'Draw 1'!K62 -> 0 | L62: =+I62-J62-K62 -> 0
A63: 41 | B63: =IF(Master!$B63=0,"",Master!$B63) | D63: =IF(Master!$D63=0,"",Master!$D63) | E63: =IF(Master!$E63=0,"",Master!$E63) | F63: =IF(Master!$F63=0,"",Master!$F63) | G63: =Master!G63 -> 0 | H63: =+'Draw 1'!H63 -> 0 | I63: =+G63+H63 -> 0 | J63: ='Draw 1'!J63+'Draw 1'!K63 -> 0 | L63: =+I63-J63-K63 -> 0
A64: 42 | B64: =IF(Master!$B64=0,"",Master!$B64) | D64: =IF(Master!$D64=0,"",Master!$D64) | E64: =IF(Master!$E64=0,"",Master!$E64) | F64: =IF(Master!$F64=0,"",Master!$F64) | G64: =Master!G64 -> 0 | H64: =+'Draw 1'!H64 -> 0 | I64: =+G64+H64 -> 0 | J64: ='Draw 1'!J64+'Draw 1'!K64 -> 0 | L64: =+I64-J64-K64 -> 0
... A82: 60 | B82: =IF(Master!$B82=0,"",Master!$B82) | D82: =IF(Master!$D82=0,"",Master!$D82) | E82: =IF(Master!$E82=0,"",Master!$E82) | F82: =IF(Master!$F82=0,"",Master!$F82) | G82: =Master!G82 -> 0 | H82: =+'Draw 1'!H82 -> 0 | I82: =+G82+H82 -> 0 | J82: ='Draw 1'!J82+'Draw 1'!K82 -> 0 | L82: =+I82-J82-K82 -> 0
F83: Total | G83: =SUM(G53:G82)+G47 -> 1268365.7 | H83: =SUM(H53:H82)+H47 -> 0 | I83: =SUM(I53:I82)+I47 -> 1268365.7 | J83: =SUM(J53:J82)+J47 -> 612003.19 | K83: =SUM(K53:K82)+K47 -> 286041.16 | L83: =SUM(L53:L82)+L47 -> 370321.37
B84: If this sworn statement is in regard to a residential structure (defined as "an individual residential condominium unit or a residential building containing not more than 2 residential units,
B85: the land on which it is or will be located, and all appurtenances, in which the owner or lessee contracting for the improvement is residing or will reside upon completion of the improvement"), on
B86: receipt of this sworn statement, the owner or lessee, or the owner's or lessee's designee must give notice of its receipt, either in writing, or by telephone, or personally, to each subcontractor,
B87: supplier, and laborer who has provided a Notice of Furnishing under Section 109 or, if a Notice of Furnishing is excused under Section 108 or 108A, to each subcontractor, supplier, and
B88: laborer named in the sworn statement. If a subcontractor, supplier, or laborer who has provided a Notice of Furnishing or who is named in the sworn statement makes a request, the
B89: owner, lessee, or designee shall provide the requester a copy of the sworn statement within 10 business days after receiving the request.
D92: ='Example of Residential SS'!D92
D93: (DEPONENT) | F93: DATE
B95: WARNING TO DEPONENT: A person gives a false sworn statement with intent to defraud is
B96: subject to criminal penalties as provided in Section 110 of the Construction Lien Act, 1980 PA 497, MCL570.1110.
C99: Subscribed and sworn to before me on | E99: (date) by
C101: Notary Public | E101: County, Michigan
C103: My Commission expires: | L103: =IF('Example of Residential SS'!L103=0,"",'Example of Residential SS'!L103)

Sheet Draw 3
A1: OWNER'S SWORN STATEMENT - Draw #3
K2: Title Company File #
B3: Owner: | C3: =+Master!C3 -> Wolven Investments LLC | F3: General Contractor Name: | G3: =+Master!G3 -> Wolven Investments LLC | K3: Phone # | L3: =+Master!L3 -> 0
B4: Address of | F4: Person Submitting: | G4: =+Master!G4 -> Jeff Klaasen | K4: Email address | L4: =+Master!L4 -> 0
B5: Improvements: | C5: =+Master!C5 -> 43 North Phase 2 | G5: (authorized person signing sworn statement) | K5: Cell phone # | L5: =+Master!L5 -> 0
B7: State of Michigan | D7: ) | G7: (2) The following is a statement of each subcontractor and supplier, and laborer for whom payment of wages or fringe benefits and withholdings is due but unpaid, with whom the (contractor) (subcontractor) has (contracted) (subcontracted) for performance under the contract with the owner or lessee of the property, and the amounts due to the persons as of the date of this statement are correctly and fully set forth opposite their names. (3) The contractor has not procured material from, or subcontracted with, any person other than those set forth and owes no money for the improvement other than the sums set forth. (4) I make this statement as the (contractor) (subcontractor) or as ____________________ of the (contractor) (subcontractor) to represent to the owner or lessee of the property and his or her agents that the property is free from claims of construction liens, or the possibility of construction liens, except as specifically set forth in this statement except for claims of construction liens by laborers that may be provided under Section 109 of the Construction Lien Act, 1980 PA 497, MCL 570.1109.
D8: ) ss.
B9: County of: | C9: =+Master!C9 -> Kent | D9: )
B11: =IF(G4=0,"",G4) -> Jeff Klaasen | D11: (deponent), being sworn, states the following:
A12: (1) | B12: =+G3 -> Wolven Investments LLC | D12: is the (contractor) (subcontractor) for an improvement to the following real
B13: property in | C13: =+C9 -> Kent | D13: County, Michigan described as follows:
B16: Name of Subcontractor, Supplier or Laborer | D16: Address of Subcontractor, Supplier or Laborer | E16: Telephone # | F16: Type of Improvement Furnished | G16: Total Contract Price | H16: Adjustment to Contract Amount ( +/ -) | I16: Adjusted Contract Price | J16: Amount Already Paid | K16: Current Request | L16: Balance to Complete
A17: 1 | B17: =IF(Master!$B17=0,"",Master!$B17) -> Jack Dykstra Excavating | D17: =IF(Master!$D17=0,"",Master!$D17) -> 3677 3 Mile Rd., Grand Rapids, MI 49534 | E17: =IF(Master!$E17=0,"",Master!$E17) -> 616-453-4827 | F17: =IF(Master!$F17=0,"",Master!$F17) -> GC Contract Amount | G17: =Master!G17 -> 623097.95 | H17: =+'Draw 2'!H17+17306.75 -> 18535.25 | I17: =+G17+H17 -> 641633.2 | J17: ='Draw 2'!J17+'Draw 2'!K17 -> 424470.95 | K17: 127875.25 | L17: =+I17-J17-K17 -> 89287
A18: 2 | B18: =IF(Master!$B18=0,"",Master!$B18) | D18: =IF(Master!$D18=0,"",Master!$D18) | E18: =IF(Master!$E18=0,"",Master!$E18) | F18: =IF(Master!$F18=0,"",Master!$F18) | G18: =Master!G18 -> 0 | H18: =+'Draw 2'!H18 -> 0 | I18: =+G18+H18 -> 0 | J18: ='Draw 2'!J18+'Draw 2'!K18 -> 0 | L18: =+I18-J18-K18 -> 0
A19: 3 | B19: =IF(Master!$B19=0,"",Master!$B19) -> Roosien & Associaties | D19: =IF(Master!$D19=0,"",Master!$D19) -> 5055 Plainfield Ave., Grand Rapids, MI 49525 | E19: =IF(Master!$E19=0,"",Master!$E19) -> 616-361-7220 | F19: =IF(Master!$F19=0,"",Master!$F19) -> Engineering Services | G19: =Master!G19 -> 62376 | H19: =+'Draw 2'!H19+3240 -> 11795 | I19: =+G19+H19 -> 74171 | J19: ='Draw 2'!J19+'Draw 2'!K19 -> 70931 | K19: 3240 | L19: =+I19-J19-K19 -> 0
A20: 4 | B20: =IF(Master!$B20=0,"",Master!$B20) -> Soils and Structures | D20: =IF(Master!$D20=0,"",Master!$D20) -> 6480 Grand Haven Rd Muskegon MI 49441 | E20: =IF(Master!$E20=0,"",Master!$E20) -> 1-800-933-3959 | F20: =IF(Master!$F20=0,"",Master!$F20) -> Engineering Services | G20: =Master!G20 -> 15930 | H20: =+'Draw 2'!H20 -> 0 | I20: =+G20+H20 -> 15930 | J20: ='Draw 2'!J20+'Draw 2'!K20 -> 1158.5 | K20: 924 | L20: =+I20-J20-K20 -> 13847.5
A21: 5 | B21: =IF(Master!$B21=0,"",Master!$B21) | D21: =IF(Master!$D21=0,"",Master!$D21) | E21: =IF(Master!$E21=0,"",Master!$E21) | F21: =IF(Master!$F21=0,"",Master!$F21) -> Engineering Services | G21: =Master!G21 -> 21742.22 | H21: =+'Draw 2'!H21-3240 -> -11795 | I21: =+G21+H21 -> 9947.22 | J21: ='Draw 2'!J21+'Draw 2'!K21 -> 0 | L21: =+I21-J21-K21 -> 9947.22
A22: 6 | B22: =IF(Master!$B22=0,"",Master!$B22) | D22: =IF(Master!$D22=0,"",Master!$D22) | E22: =IF(Master!$E22=0,"",Master!$E22) | F22: =IF(Master!$F22=0,"",Master!$F22) | G22: =Master!G22 -> 0 | H22: =+'Draw 2'!H22 -> 0 | I22: =+G22+H22 -> 0 | J22: ='Draw 2'!J22+'Draw 2'!K22 -> 0 | L22: =+I22-J22-K22 -> 0
A23: 7 | B23: =IF(Master!$B23=0,"",Master!$B23) -> Handicap Sign | D23: =IF(Master!$D23=0,"",Master!$D23) -> 1142 Wealthy St., Grand Rapids, MI 49506 | E23: =IF(Master!$E23=0,"",Master!$E23) -> 616-454-9416 | F23: =IF(Master!$F23=0,"",Master!$F23) -> Common Area Improvements | G23: =Master!G23 -> 424.4 | H23: =+'Draw 2'!H23 -> 0 | I23: =+G23+H23 -> 424.4 | J23: ='Draw 2'!J23+'Draw 2'!K23 -> 424.4 | L23: =+I23-J23-K23 -> 0
A24: 8 | B24: =IF(Master!$B24=0,"",Master!$B24) -> Rosendall Well Drilling | D24: =IF(Master!$D24=0,"",Master!$D24) -> 4181 Knapp, Grand Rapids, MI 49525 | E24: =IF(Master!$E24=0,"",Master!$E24) -> 616-363-2683 | F24: =IF(Master!$F24=0,"",Master!$F24) -> Common Area Improvements | G24: =Master!G24 -> 47734 | H24: =+'Draw 2'!H24 -> 0 | I24: =+G24+H24 -> 47734 | J24: ='Draw 2'!J24+'Draw 2'!K24 -> 47734 | L24: =+I24-J24-K24 -> 0
A25: 9 | B25: =IF(Master!$B25=0,"",Master!$B25) | D25: =IF(Master!$D25=0,"",Master!$D25) | E25: =IF(Master!$E25=0,"",Master!$E25) | F25: =IF(Master!$F25=0,"",Master!$F25) -> Common Area Improvements | G25: =Master!G25 -> 8214.6 | H25: =+'Draw 2'!H25 -> 0 | I25: =+G25+H25 -> 8214.6 | J25: ='Draw 2'!J25+'Draw 2'!K25 -> 0 | L25: =+I25-J25-K25 -> 8214.6
A26: 10 | B26: =IF(Master!$B26=0,"",Master!$B26) | D26: =IF(Master!$D26=0,"",Master!$D26) | E26: =IF(Master!$E26=0,"",Master!$E26) | F26: =IF(Master!$F26=0,"",Master!$F26) | G26: =Master!G26 -> 0 | H26: =+'Draw 2'!H26 -> 0 | I26: =+G26+H26 -> 0 | J26: ='Draw 2'!J26+'Draw 2'!K26 -> 0 | L26: =+I26-J26-K26 -> 0
A27: 11 | B27: =IF(Master!$B27=0,"",Master!$B27) | D27: =IF(Master!$D27=0,"",Master!$D27) | E27: =IF(Master!$E27=0,"",Master!$E27) | F27: =IF(Master!$F27=0,"",Master!$F27) | G27: =Master!G27 -> 0 | H27: =+'Draw 2'!H27 -> 0 | I27: =+G27+H27 -> 0 | J27: ='Draw 2'!J27+'Draw 2'!K27 -> 0 | L27: =+I27-J27-K27 -> 0
A28: 12 | B28: =IF(Master!$B28=0,"",Master!$B28) | D28: =IF(Master!$D28=0,"",Master!$D28) | E28: =IF(Master!$E28=0,"",Master!$E28) | F28: =IF(Master!$F28=0,"",Master!$F28) | G28: =Master!G28 -> 0 | H28: =+'Draw 2'!H28 -> 0 | I28: =+G28+H28 -> 0 | J28: ='Draw 2'!J28+'Draw 2'!K28 -> 0 | L28: =+I28-J28-K28 -> 0
A29: 13 | B29: =IF(Master!$B29=0,"",Master!$B29) -> State of Michigan | D29: =IF(Master!$D29=0,"",Master!$D29) -> Lansing, MI 48909 | E29: =IF(Master!$E29=0,"",Master!$E29) | F29: =IF(Master!$F29=0,"",Master!$F29) -> Permits and Fees | G29: =Master!G29 -> 800 | H29: =+'Draw 2'!H29 -> 0 | I29: =+G29+H29 -> 800 | J29: ='Draw 2'!J29+'Draw 2'!K29 -> 800 | L29: =+I29-J29-K29 -> 0
A30: 14 | B30: =IF(Master!$B30=0,"",Master!$B30) -> Kent County Health Department | D30: =IF(Master!$D30=0,"",Master!$D30) -> 700 Fuller Ave., Grand Rapids, MI 49503 | E30: =IF(Master!$E30=0,"",Master!$E30) -> 616-632-7100 | F30: =IF(Master!$F30=0,"",Master!$F30) -> Permits and Fees | G30: =Master!G30 -> 2635 | H30: =+'Draw 2'!H30 -> 0 | I30: =+G30+H30 -> 2635 | J30: ='Draw 2'!J30+'Draw 2'!K30 -> 2635 | L30: =+I30-J30-K30 -> 0
A31: 15 | B31: =IF(Master!$B31=0,"",Master!$B31) -> Kent County Road Commission | D31: =IF(Master!$D31=0,"",Master!$D31) -> 1500 Scribner, Grand Rapids, MI 49504 | E31: =IF(Master!$E31=0,"",Master!$E31) -> 616-242-6900 | F31: =IF(Master!$F31=0,"",Master!$F31) -> Permits and Fees | G31: =Master!G31 -> 13445 | H31: 675 | I31: =+G31+H31 -> 14120 | J31: ='Draw 2'!J31+'Draw 2'!K31 -> 13445 | K31: 675 | L31: =+I31-J31-K31 -> 0
A32: 16 | B32: =IF(Master!$B32=0,"",Master!$B32) -> Kent County Drain Commission | D32: =IF(Master!$D32=0,"",Master!$D32) -> 1500 Scribner, Grand Rapids, MI 49504 | E32: =IF(Master!$E32=0,"",Master!$E32) -> 616-632-7910 | F32: =IF(Master!$F32=0,"",Master!$F32) -> Permits and Fees | G32: =Master!G32 -> 0 | H32: =+'Draw 2'!H32 -> 0 | I32: =+G32+H32 -> 0 | J32: ='Draw 2'!J32+'Draw 2'!K32 -> 0 | L32: =+I32-J32-K32 -> 0
A33: 17 | B33: =IF(Master!$B33=0,"",Master!$B33) -> Algoma Township | D33: =IF(Master!$D33=0,"",Master!$D33) -> 10531 Algoma Ave., Rockford, MI 49341 | E33: =IF(Master!$E33=0,"",Master!$E33) -> 616-866-1583 | F33: =IF(Master!$F33=0,"",Master!$F33) -> Permits and Fees | G33: =Master!G33 -> 18795 | H33: =+'Draw 2'!H33 -> 0 | I33: =+G33+H33 -> 18795 | J33: ='Draw 2'!J33+'Draw 2'!K33 -> 18795 | L33: =+I33-J33-K33 -> 0
A34: 18 | B34: =IF(Master!$B34=0,"",Master!$B34) | D34: =IF(Master!$D34=0,"",Master!$D34) | E34: =IF(Master!$E34=0,"",Master!$E34) | F34: =IF(Master!$F34=0,"",Master!$F34) -> Permits and Fees | G34: =Master!G34 -> 18585.77 | H34: -675 | I34: =+G34+H34 -> 17910.77 | J34: ='Draw 2'!J34+'Draw 2'!K34 -> 0 | L34: =+I34-J34-K34 -> 17910.77
A35: 19 | B35: =IF(Master!$B35=0,"",Master!$B35) | D35: =IF(Master!$D35=0,"",Master!$D35) | E35: =IF(Master!$E35=0,"",Master!$E35) | F35: =IF(Master!$F35=0,"",Master!$F35) -> Electric, Gas, Street Lights | G35: =Master!G35 -> 16802 | H35: =+'Draw 2'!H35 -> 0 | I35: =+G35+H35 -> 16802 | J35: ='Draw 2'!J35+'Draw 2'!K35 -> 0 | L35: =+I35-J35-K35 -> 16802
A36: 20 | B36: =IF(Master!$B36=0,"",Master!$B36) -> Consumers Energy | D36: =IF(Master!$D36=0,"",Master!$D36) -> 530 W Willow St. Lansing MI 48909 | E36: =IF(Master!$E36=0,"",Master!$E36) -> 616-530-4210 | F36: =IF(Master!$F36=0,"",Master!$F36) -> Electric, Gas, Street Lights | G36: =Master!G36 -> 68518 | H36: =+'Draw 2'!H36 -> 0 | I36: =+G36+H36 -> 68518 | J36: ='Draw 2'!J36+'Draw 2'!K36 -> 68518 | L36: =+I36-J36-K36 -> 0
A37: 21 | B37: =IF(Master!$B37=0,"",Master!$B37) -> DTE Energy | D37: =IF(Master!$D37=0,"",Master!$D37) -> 4420 44th St., Grand Rapids, MI 49512 | E37: =IF(Master!$E37=0,"",Master!$E37) -> 616-278-4720 | F37: =IF(Master!$F37=0,"",Master!$F37) -> Electric, Gas, Street Lights | G37: =Master!G37 -> 0 | H37: =+'Draw 2'!H37 -> 0 | I37: =+G37+H37 -> 0 | J37: ='Draw 2'!J37+'Draw 2'!K37 -> 0 | L37: =+I37-J37-K37 -> 0
A38: 22 | B38: =IF(Master!$B38=0,"",Master!$B38) | D38: =IF(Master!$D38=0,"",Master!$D38) | E38: =IF(Master!$E38=0,"",Master!$E38) | F38: =IF(Master!$F38=0,"",Master!$F38) -> Professional Services | G38: =Master!G38 -> 5167.5 | H38: -747.5 | I38: =+G38+H38 -> 4420 | J38: ='Draw 2'!J38+'Draw 2'!K38 -> 0 | L38: =+I38-J38-K38 -> 4420
A39: 23 | B39: =IF(Master!$B39=0,"",Master!$B39) -> Rhodes Mckee | D39: =IF(Master!$D39=0,"",Master!$D39) -> 55 Campau Ave. Grand Rapids MI 49503 | E39: =IF(Master!$E39=0,"",Master!$E39) -> 616-235-3500 | F39: =IF(Master!$F39=0,"",Master!$F39) -> Professional Services | G39: =Master!G39 -> 14832.5 | H39: 747.5 | I39: =+G39+H39 -> 15580 | J39: ='Draw 2'!J39+'Draw 2'!K39 -> 14832.5 | K39: 747.5 | L39: =+I39-J39-K39 -> 0
A40: 24 | B40: =IF(Master!$B40=0,"",Master!$B40) | D40: =IF(Master!$D40=0,"",Master!$D40) | E40: =IF(Master!$E40=0,"",Master!$E40) | F40: =IF(Master!$F40=0,"",Master!$F40) | G40: =Master!G40 -> 0 | H40: =+'Draw 2'!H40 -> 0 | I40: =+G40+H40 -> 0 | J40: ='Draw 2'!J40+'Draw 2'!K40 -> 0 | L40: =+I40-J40-K40 -> 0
A41: 25 | B41: =IF(Master!$B41=0,"",Master!$B41) | D41: =IF(Master!$D41=0,"",Master!$D41) | E41: =IF(Master!$E41=0,"",Master!$E41) | F41: =IF(Master!$F41=0,"",Master!$F41) | G41: =Master!G41 -> 0 | H41: =+'Draw 2'!H41 -> 0 | I41: =+G41+H41 -> 0 | J41: ='Draw 2'!J41+'Draw 2'!K41 -> 0 | L41: =+I41-J41-K41 -> 0
A42: 26 | B42: =IF(Master!$B42=0,"",Master!$B42) | D42: =IF(Master!$D42=0,"",Master!$D42) | E42: =IF(Master!$E42=0,"",Master!$E42) | F42: =IF(Master!$F42=0,"",Master!$F42) | G42: =Master!G42 -> 0 | H42: =+'Draw 2'!H42 -> 0 | I42: =+G42+H42 -> 0 | J42: ='Draw 2'!J42+'Draw 2'!K42 -> 0 | L42: =+I42-J42-K42 -> 0
A43: 27 | B43: =IF(Master!$B43=0,"",Master!$B43) | D43: =IF(Master!$D43=0,"",Master!$D43) | E43: =IF(Master!$E43=0,"",Master!$E43) | F43: =IF(Master!$F43=0,"",Master!$F43) | G43: =Master!G43 -> 0 | H43: =+'Draw 2'!H43 -> 0 | I43: =+G43+H43 -> 0 | J43: ='Draw 2'!J43+'Draw 2'!K43 -> 0 | L43: =+I43-J43-K43 -> 0
A44: 28 | B44: =IF(Master!$B44=0,"",Master!$B44) | D44: =IF(Master!$D44=0,"",Master!$D44) | E44: =IF(Master!$E44=0,"",Master!$E44) | F44: =IF(Master!$F44=0,"",Master!$F44) -> Contingency | G44: =Master!G44 -> 48532.35 | H44: =+'Draw 2'!H44-17306.75 -> -18535.25 | I44: =+G44+H44 -> 29997.1 | J44: ='Draw 2'!J44+'Draw 2'!K44 -> 0 | L44: =+I44-J44-K44 -> 29997.1
A45: 29 | B45: =IF(Master!$B45=0,"",Master!$B45) | D45: =IF(Master!$D45=0,"",Master!$D45) | E45: =IF(Master!$E45=0,"",Master!$E45) | F45: =IF(Master!$F45=0,"",Master!$F45) -> Interest Carry | G45: =Master!G45 -> 46433.43 | H45: =+'Draw 2'!H45 -> 0 | I45: =+G45+H45 -> 46433.43 | J45: ='Draw 2'!J45+'Draw 2'!K45 -> 0 | K45: =408.63+1527.27 -> 1935.9 | L45: =+I45-J45-K45 -> 44497.53
A46: 30 | B46: =IF(Master!$B46=0,"",Master!$B46) | D46: =IF(Master!$D46=0,"",Master!$D46) | E46: =IF(Master!$E46=0,"",Master!$E46) | F46: =IF(Master!$F46=0,"",Master!$F46) -> Land | G46: =Master!G46 -> 234300 | H46: =+'Draw 2'!H46 -> 0 | I46: =+G46+H46 -> 234300 | J46: ='Draw 2'!J46+'Draw 2'!K46 -> 234300 | L46: =+I46-J46-K46 -> 0
F47: SUBTOTALS | G47: =SUM(G17:G46) -> 1268365.7 | H47: =SUM(H17:H46) -> 0 | I47: =SUM(I17:I46) -> 1268365.7 | J47: =SUM(J17:J46) -> 898044.35 | K47: =SUM(K17:K46) -> 135397.65 | L47: =SUM(L17:L46) -> 234923.72
B48: WARNING TO OWNER OR LESSEE: An owner or lessee of the property may not rely on this sworn statement to avoid the claim of a subcontractor, supplier, or laborer who has provided a Notice of Furnishing or a laborer who may provide a Notice of Furnishing under Section 109 of the Construction Lien Act, 1980 PA 497, MCL 570.1109, to the designee or to the owner or lessee if the designee is not named or has died.
B52: Name of Subcontractor, Supplier or Laborer | D52: Address of Subcontractor, Supplier or Laborer | E52: Telephone # | F52: Type of Improvement Furnished | G52: Total Contract Price | H52: Adjustment to Contract Amount ( +/ -) | I52: Adjusted Contract Price | J52: Amount Already Paid | K52: Current Request | L52: Balance to Complete
A53: 31 | B53: =IF(Master!$B53=0,"",Master!$B53) | D53: =IF(Master!$D53=0,"",Master!$D53) | E53: =IF(Master!$E53=0,"",Master!$E53) | F53: =IF(Master!$F53=0,"",Master!$F53) | G53: =Master!G53 -> 0 | H53: =+'Draw 2'!H53 -> 0 | I53: =+G53+H53 -> 0 | J53: ='Draw 2'!J53+'Draw 2'!K53 -> 0 | L53: =+I53-J53-K53 -> 0
A54: 32 | B54: =IF(Master!$B54=0,"",Master!$B54) | D54: =IF(Master!$D54=0,"",Master!$D54) | E54: =IF(Master!$E54=0,"",Master!$E54) | F54: =IF(Master!$F54=0,"",Master!$F54) | G54: =Master!G54 -> 0 | H54: =+'Draw 2'!H54 -> 0 | I54: =+G54+H54 -> 0 | J54: ='Draw 2'!J54+'Draw 2'!K54 -> 0 | L54: =+I54-J54-K54 -> 0
A55: 33 | B55: =IF(Master!$B55=0,"",Master!$B55) | D55: =IF(Master!$D55=0,"",Master!$D55) | E55: =IF(Master!$E55=0,"",Master!$E55) | F55: =IF(Master!$F55=0,"",Master!$F55) | G55: =Master!G55 -> 0 | H55: =+'Draw 2'!H55 -> 0 | I55: =+G55+H55 -> 0 | J55: ='Draw 2'!J55+'Draw 2'!K55 -> 0 | L55: =+I55-J55-K55 -> 0
A56: 34 | B56: =IF(Master!$B56=0,"",Master!$B56) | D56: =IF(Master!$D56=0,"",Master!$D56) | E56: =IF(Master!$E56=0,"",Master!$E56) | F56: =IF(Master!$F56=0,"",Master!$F56) | G56: =Master!G56 -> 0 | H56: =+'Draw 2'!H56 -> 0 | I56: =+G56+H56 -> 0 | J56: ='Draw 2'!J56+'Draw 2'!K56 -> 0 | L56: =+I56-J56-K56 -> 0
A57: 35 | B57: =IF(Master!$B57=0,"",Master!$B57) | D57: =IF(Master!$D57=0,"",Master!$D57) | E57: =IF(Master!$E57=0,"",Master!$E57) | F57: =IF(Master!$F57=0,"",Master!$F57) | G57: =Master!G57 -> 0 | H57: =+'Draw 2'!H57 -> 0 | I57: =+G57+H57 -> 0 | J57: ='Draw 2'!J57+'Draw 2'!K57 -> 0 | L57: =+I57-J57-K57 -> 0
A58: 36 | B58: =IF(Master!$B58=0,"",Master!$B58) | D58: =IF(Master!$D58=0,"",Master!$D58) | E58: =IF(Master!$E58=0,"",Master!$E58) | F58: =IF(Master!$F58=0,"",Master!$F58) | G58: =Master!G58 -> 0 | H58: =+'Draw 2'!H58 -> 0 | I58: =+G58+H58 -> 0 | J58: ='Draw 2'!J58+'Draw 2'!K58 -> 0 | L58: =+I58-J58-K58 -> 0
A59: 37 | B59: =IF(Master!$B59=0,"",Master!$B59) | D59: =IF(Master!$D59=0,"",Master!$D59) | E59: =IF(Master!$E59=0,"",Master!$E59) | F59: =IF(Master!$F59=0,"",Master!$F59) | G59: =Master!G59 -> 0 | H59: =+'Draw 2'!H59 -> 0 | I59: =+G59+H59 -> 0 | J59: ='Draw 2'!J59+'Draw 2'!K59 -> 0 | L59: =+I59-J59-K59 -> 0
A60: 38 | B60: =IF(Master!$B60=0,"",Master!$B60) | D60: =IF(Master!$D60=0,"",Master!$D60) | E60: =IF(Master!$E60=0,"",Master!$E60) | F60: =IF(Master!$F60=0,"",Master!$F60) | G60: =Master!G60 -> 0 | H60: =+'Draw 2'!H60 -> 0 | I60: =+G60+H60 -> 0 | J60: ='Draw 2'!J60+'Draw 2'!K60 -> 0 | L60: =+I60-J60-K60 -> 0
A61: 39 | B61: =IF(Master!$B61=0,"",Master!$B61) | D61: =IF(Master!$D61=0,"",Master!$D61) | E61: =IF(Master!$E61=0,"",Master!$E61) | F61: =IF(Master!$F61=0,"",Master!$F61) | G61: =Master!G61 -> 0 | H61: =+'Draw 2'!H61 -> 0 | I61: =+G61+H61 -> 0 | J61: ='Draw 2'!J61+'Draw 2'!K61 -> 0 | L61: =+I61-J61-K61 -> 0
A62: 40 | B62: =IF(Master!$B62=0,"",Master!$B62) | D62: =IF(Master!$D62=0,"",Master!$D62) | E62: =IF(Master!$E62=0,"",Master!$E62) | F62: =IF(Master!$F62=0,"",Master!$F62) | G62: =Master!G62 -> 0 | H62: =+'Draw 2'!H62 -> 0 | I62: =+G62+H62 -> 0 | J62: ='Draw 2'!J62+'Draw 2'!K62 -> 0 | L62: =+I62-J62-K62 -> 0
A63: 41 | B63: =IF(Master!$B63=0,"",Master!$B63) | D63: =IF(Master!$D63=0,"",Master!$D63) | E63: =IF(Master!$E63=0,"",Master!$E63) | F63: =IF(Master!$F63=0,"",Master!$F63) | G63: =Master!G63 -> 0 | H63: =+'Draw 2'!H63 -> 0 | I63: =+G63+H63 -> 0 | J63: ='Draw 2'!J63+'Draw 2'!K63 -> 0 | L63: =+I63-J63-K63 -> 0
A64: 42 | B64: =IF(Master!$B64=0,"",Master!$B64) | D64: =IF(Master!$D64=0,"",Master!$D64) | E64: =IF(Master!$E64=0,"",Master!$E64) | F64: =IF(Master!$F64=0,"",Master!$F64) | G64: =Master!G64 -> 0 | H64: =+'Draw 2'!H64 -> 0 | I64: =+G64+H64 -> 0 | J64: ='Draw 2'!J64+'Draw 2'!K64 -> 0 | L64: =+I64-J64-K64 -> 0
... A82: 60 | B82: =IF(Master!$B82=0,"",Master!$B82) | D82: =IF(Master!$D82=0,"",Master!$D82) | E82: =IF(Master!$E82=0,"",Master!$E82) | F82: =IF(Master!$F82=0,"",Master!$F82) | G82: =Master!G82 -> 0 | H82: =+'Draw 2'!H82 -> 0 | I82: =+G82+H82 -> 0 | J82: ='Draw 2'!J82+'Draw 2'!K82 -> 0 | L82: =+I82-J82-K82 -> 0
F83: Total | G83: =SUM(G53:G82)+G47 -> 1268365.7 | H83: =SUM(H53:H82)+H47 -> 0 | I83: =SUM(I53:I82)+I47 -> 1268365.7 | J83: =SUM(J53:J82)+J47 -> 898044.35 | K83: =SUM(K53:K82)+K47 -> 135397.65 | L83: =SUM(L53:L82)+L47 -> 234923.72
B84: If this sworn statement is in regard to a residential structure (defined as "an individual residential condominium unit or a residential building containing not more than 2 residential units,
B85: the land on which it is or will be located, and all appurtenances, in which the owner or lessee contracting for the improvement is residing or will reside upon completion of the improvement"), on
B86: receipt of this sworn statement, the owner or lessee, or the owner's or lessee's designee must give notice of its receipt, either in writing, or by telephone, or personally, to each subcontractor,
B87: supplier, and laborer who has provided a Notice of Furnishing under Section 109 or, if a Notice of Furnishing is excused under Section 108 or 108A, to each subcontractor, supplier, and
B88: laborer named in the sworn statement. If a subcontractor, supplier, or laborer who has provided a Notice of Furnishing or who is named in the sworn statement makes a request, the
B89: owner, lessee, or designee shall provide the requester a copy of the sworn statement within 10 business days after receiving the request.
D92: ='Example of Residential SS'!D92
D93: (DEPONENT) | F93: DATE
B95: WARNING TO DEPONENT: A person gives a false sworn statement with intent to defraud is
B96: subject to criminal penalties as provided in Section 110 of the Construction Lien Act, 1980 PA 497, MCL570.1110.
C99: Subscribed and sworn to before me on | E99: (date) by
C101: Notary Public | E101: County, Michigan
C103: My Commission expires: | L103: =IF('Example of Residential SS'!L103=0,"",'Example of Residential SS'!L103)

Sheet Draw 4
A1: OWNER'S SWORN STATEMENT - Draw #4
K2: Title Company File #
B3: Owner: | C3: =+Master!C3 -> Wolven Investments LLC | F3: General Contractor Name: | G3: =+Master!G3 -> Wolven Investments LLC | K3: Phone # | L3: =+Master!L3 -> 0
B4: Address of | F4: Person Submitting: | G4: =+Master!G4 -> Jeff Klaasen | K4: Email address | L4: =+Master!L4 -> 0
B5: Improvements: | C5: =+Master!C5 -> 43 North Phase 2 | G5: (authorized person signing sworn statement) | K5: Cell phone # | L5: =+Master!L5 -> 0
B7: State of Michigan | D7: ) | G7: (2) The following is a statement of each subcontractor and supplier, and laborer for whom payment of wages or fringe benefits and withholdings is due but unpaid, with whom the (contractor) (subcontractor) has (contracted) (subcontracted) for performance under the contract with the owner or lessee of the property, and the amounts due to the persons as of the date of this statement are correctly and fully set forth opposite their names. (3) The contractor has not procured material from, or subcontracted with, any person other than those set forth and owes no money for the improvement other than the sums set forth. (4) I make this statement as the (contractor) (subcontractor) or as ____________________ of the (contractor) (subcontractor) to represent to the owner or lessee of the property and his or her agents that the property is free from claims of construction liens, or the possibility of construction liens, except as specifically set forth in this statement except for claims of construction liens by laborers that may be provided under Section 109 of the Construction Lien Act, 1980 PA 497, MCL 570.1109.
D8: ) ss.
B9: County of: | C9: =+Master!C9 -> Kent | D9: )
B11: =IF(G4=0,"",G4) -> Jeff Klaasen | D11: (deponent), being sworn, states the following:
A12: (1) | B12: =+G3 -> Wolven Investments LLC | D12: is the (contractor) (subcontractor) for an improvement to the following real
B13: property in | C13: =+C9 -> Kent | D13: County, Michigan described as follows:
B16: Name of Subcontractor, Supplier or Laborer | D16: Address of Subcontractor, Supplier or Laborer | E16: Telephone # | F16: Type of Improvement Furnished | G16: Total Contract Price | H16: Adjustment to Contract Amount ( +/ -) | I16: Adjusted Contract Price | J16: Amount Already Paid | K16: Current Request | L16: Balance to Complete
A17: 1 | B17: =IF(Master!$B17=0,"",Master!$B17) -> Jack Dykstra Excavating | D17: =IF(Master!$D17=0,"",Master!$D17) -> 3677 3 Mile Rd., Grand Rapids, MI 49534 | E17: =IF(Master!$E17=0,"",Master!$E17) -> 616-453-4827 | F17: =IF(Master!$F17=0,"",Master!$F17) -> GC Contract Amount | G17: =Master!G17 -> 623097.95 | H17: ='Draw 3'!H17 -> 18535.25 | I17: =+G17+H17 -> 641633.2 | J17: ='Draw 3'!J17+'Draw 3'!K17 -> 552346.2 | K17: 89287 | L17: =+I17-J17-K17 -> 0
A18: 2 | B18: =IF(Master!$B18=0,"",Master!$B18) | D18: =IF(Master!$D18=0,"",Master!$D18) | E18: =IF(Master!$E18=0,"",Master!$E18) | F18: =IF(Master!$F18=0,"",Master!$F18) | G18: =Master!G18 -> 0 | H18: ='Draw 3'!H18 -> 0 | I18: =+G18+H18 -> 0 | J18: ='Draw 3'!J18+'Draw 3'!K18 -> 0 | L18: =+I18-J18-K18 -> 0
A19: 3 | B19: =IF(Master!$B19=0,"",Master!$B19) -> Roosien & Associaties | D19: =IF(Master!$D19=0,"",Master!$D19) -> 5055 Plainfield Ave., Grand Rapids, MI 49525 | E19: =IF(Master!$E19=0,"",Master!$E19) -> 616-361-7220 | F19: =IF(Master!$F19=0,"",Master!$F19) -> Engineering Services | G19: =Master!G19 -> 62376 | H19: ='Draw 3'!H19+3355 -> 15150 | I19: =+G19+H19 -> 77526 | J19: ='Draw 3'!J19+'Draw 3'!K19 -> 74171 | K19: 3355 | L19: =+I19-J19-K19 -> 0
A20: 4 | B20: =IF(Master!$B20=0,"",Master!$B20) -> Soils and Structures | D20: =IF(Master!$D20=0,"",Master!$D20) -> 6480 Grand Haven Rd Muskegon MI 49441 | E20: =IF(Master!$E20=0,"",Master!$E20) -> 1-800-933-3959 | F20: =IF(Master!$F20=0,"",Master!$F20) -> Engineering Services | G20: =Master!G20 -> 15930 | H20: ='Draw 3'!H20 -> 0 | I20: =+G20+H20 -> 15930 | J20: ='Draw 3'!J20+'Draw 3'!K20 -> 2082.5 | K20: 453 | L20: =+I20-J20-K20 -> 13394.5
A21: 5 | B21: =IF(Master!$B21=0,"",Master!$B21) | D21: =IF(Master!$D21=0,"",Master!$D21) | E21: =IF(Master!$E21=0,"",Master!$E21) | F21: =IF(Master!$F21=0,"",Master!$F21) -> Engineering Services | G21: =Master!G21 -> 21742.22 | H21: ='Draw 3'!H21-3355 -> -15150 | I21: =+G21+H21 -> 6592.22 | J21: ='Draw 3'!J21+'Draw 3'!K21 -> 0 | L21: =+I21-J21-K21 -> 6592.22
A22: 6 | B22: =IF(Master!$B22=0,"",Master!$B22) | D22: =IF(Master!$D22=0,"",Master!$D22) | E22: =IF(Master!$E22=0,"",Master!$E22) | F22: =IF(Master!$F22=0,"",Master!$F22) | G22: =Master!G22 -> 0 | H22: ='Draw 3'!H22 -> 0 | I22: =+G22+H22 -> 0 | J22: ='Draw 3'!J22+'Draw 3'!K22 -> 0 | L22: =+I22-J22-K22 -> 0
A23: 7 | B23: =IF(Master!$B23=0,"",Master!$B23) -> Handicap Sign | D23: =IF(Master!$D23=0,"",Master!$D23) -> 1142 Wealthy St., Grand Rapids, MI 49506 | E23: =IF(Master!$E23=0,"",Master!$E23) -> 616-454-9416 | F23: =IF(Master!$F23=0,"",Master!$F23) -> Common Area Improvements | G23: =Master!G23 -> 424.4 | H23: ='Draw 3'!H23 -> 0 | I23: =+G23+H23 -> 424.4 | J23: ='Draw 3'!J23+'Draw 3'!K23 -> 424.4 | L23: =+I23-J23-K23 -> 0
A24: 8 | B24: =IF(Master!$B24=0,"",Master!$B24) -> Rosendall Well Drilling | D24: =IF(Master!$D24=0,"",Master!$D24) -> 4181 Knapp, Grand Rapids, MI 49525 | E24: =IF(Master!$E24=0,"",Master!$E24) -> 616-363-2683 | F24: =IF(Master!$F24=0,"",Master!$F24) -> Common Area Improvements | G24: =Master!G24 -> 47734 | H24: ='Draw 3'!H24 -> 0 | I24: =+G24+H24 -> 47734 | J24: ='Draw 3'!J24+'Draw 3'!K24 -> 47734 | L24: =+I24-J24-K24 -> 0
A25: 9 | B25: =IF(Master!$B25=0,"",Master!$B25) | D25: =IF(Master!$D25=0,"",Master!$D25) | E25: =IF(Master!$E25=0,"",Master!$E25) | F25: =IF(Master!$F25=0,"",Master!$F25) -> Common Area Improvements | G25: =Master!G25 -> 8214.6 | H25: ='Draw 3'!H25 -> 0 | I25: =+G25+H25 -> 8214.6 | J25: ='Draw 3'!J25+'Draw 3'!K25 -> 0 | L25: =+I25-J25-K25 -> 8214.6
A26: 10 | B26: =IF(Master!$B26=0,"",Master!$B26) | D26: =IF(Master!$D26=0,"",Master!$D26) | E26: =IF(Master!$E26=0,"",Master!$E26) | F26: =IF(Master!$F26=0,"",Master!$F26) | G26: =Master!G26 -> 0 | H26: ='Draw 3'!H26 -> 0 | I26: =+G26+H26 -> 0 | J26: ='Draw 3'!J26+'Draw 3'!K26 -> 0 | L26: =+I26-J26-K26 -> 0
A27: 11 | B27: =IF(Master!$B27=0,"",Master!$B27) | D27: =IF(Master!$D27=0,"",Master!$D27) | E27: =IF(Master!$E27=0,"",Master!$E27) | F27: =IF(Master!$F27=0,"",Master!$F27) | G27: =Master!G27 -> 0 | H27: ='Draw 3'!H27 -> 0 | I27: =+G27+H27 -> 0 | J27: ='Draw 3'!J27+'Draw 3'!K27 -> 0 | L27: =+I27-J27-K27 -> 0
A28: 12 | B28: =IF(Master!$B28=0,"",Master!$B28) | D28: =IF(Master!$D28=0,"",Master!$D28) | E28: =IF(Master!$E28=0,"",Master!$E28) | F28: =IF(Master!$F28=0,"",Master!$F28) | G28: =Master!G28 -> 0 | H28: ='Draw 3'!H28 -> 0 | I28: =+G28+H28 -> 0 | J28: ='Draw 3'!J28+'Draw 3'!K28 -> 0 | L28: =+I28-J28-K28 -> 0
A29: 13 | B29: =IF(Master!$B29=0,"",Master!$B29) -> State of Michigan | D29: =IF(Master!$D29=0,"",Master!$D29) -> Lansing, MI 48909 | E29: =IF(Master!$E29=0,"",Master!$E29) | F29: =IF(Master!$F29=0,"",Master!$F29) -> Permits and Fees | G29: =Master!G29 -> 800 | H29: ='Draw 3'!H29 -> 0 | I29: =+G29+H29 -> 800 | J29: ='Draw 3'!J29+'Draw 3'!K29 -> 800 | L29: =+I29-J29-K29 -> 0
A30: 14 | B30: =IF(Master!$B30=0,"",Master!$B30) -> Kent County Health Department | D30: =IF(Master!$D30=0,"",Master!$D30) -> 700 Fuller Ave., Grand Rapids, MI 49503 | E30: =IF(Master!$E30=0,"",Master!$E30) -> 616-632-7100 | F30: =IF(Master!$F30=0,"",Master!$F30) -> Permits and Fees | G30: =Master!G30 -> 2635 | H30: ='Draw 3'!H30 -> 0 | I30: =+G30+H30 -> 2635 | J30: ='Draw 3'!J30+'Draw 3'!K30 -> 2635 | L30: =+I30-J30-K30 -> 0
A31: 15 | B31: =IF(Master!$B31=0,"",Master!$B31) -> Kent County Road Commission | D31: =IF(Master!$D31=0,"",Master!$D31) -> 1500 Scribner, Grand Rapids, MI 49504 | E31: =IF(Master!$E31=0,"",Master!$E31) -> 616-242-6900 | F31: =IF(Master!$F31=0,"",Master!$F31) -> Permits and Fees | G31: =Master!G31 -> 13445 | H31: ='Draw 3'!H31 -> 675 | I31: =+G31+H31 -> 14120 | J31: ='Draw 3'!J31+'Draw 3'!K31 -> 14120 | L31: =+I31-J31-K31 -> 0
A32: 16 | B32: =IF(Master!$B32=0,"",Master!$B32) -> Kent County Drain Commission | D32: =IF(Master!$D32=0,"",Master!$D32) -> 1500 Scribner, Grand Rapids, MI 49504 | E32: =IF(Master!$E32=0,"",Master!$E32) -> 616-632-7910 | F32: =IF(Master!$F32=0,"",Master!$F32) -> Permits and Fees | G32: =Master!G32 -> 0 | H32: ='Draw 3'!H32 -> 0 | I32: =+G32+H32 -> 0 | J32: ='Draw 3'!J32+'Draw 3'!K32 -> 0 | L32: =+I32-J32-K32 -> 0
A33: 17 | B33: =IF(Master!$B33=0,"",Master!$B33) -> Algoma Township | D33: =IF(Master!$D33=0,"",Master!$D33) -> 10531 Algoma Ave., Rockford, MI 49341 | E33: =IF(Master!$E33=0,"",Master!$E33) -> 616-866-1583 | F33: =IF(Master!$F33=0,"",Master!$F33) -> Permits and Fees | G33: =Master!G33 -> 18795 | H33: ='Draw 3'!H33 -> 0 | I33: =+G33+H33 -> 18795 | J33: ='Draw 3'!J33+'Draw 3'!K33 -> 18795 | L33: =+I33-J33-K33 -> 0
... A37: 21 | B37: =IF(Master!$B37=0,"",Master!$B37) -> DTE Energy | D37: =IF(Master!$D37=0,"",Master!$D37) -> 4420 44th St., Grand Rapids, MI 49512 | E37: =IF(Master!$E37=0,"",Master!$E37) -> 616-278-4720 | F37: =IF(Master!$F37=0,"",Master!$F37) -> Electric, Gas, Street Lights | G37: =Master!G37 -> 0 | H37: ='Draw 3'!H37 -> 0 | I37: =+G37+H37 -> 0 | J37: ='Draw 3'!J37+'Draw 3'!K37 -> 0 | L37: =+I37-J37-K37 -> 0
A38: 22 | B38: =IF(Master!$B38=0,"",Master!$B38) | D38: =IF(Master!$D38=0,"",Master!$D38) | E38: =IF(Master!$E38=0,"",Master!$E38) | F38: =IF(Master!$F38=0,"",Master!$F38) -> Professional Services | G38: =Master!G38 -> 5167.5 | H38: ='Draw 3'!H38-1425 -> -2172.5 | I38: =+G38+H38 -> 2995 | J38: ='Draw 3'!J38+'Draw 3'!K38 -> 0 | L38: =+I38-J38-K38 -> 2995
A39: 23 | B39: =IF(Master!$B39=0,"",Master!$B39) -> Rhodes Mckee | D39: =IF(Master!$D39=0,"",Master!$D39) -> 55 Campau Ave. Grand Rapids MI 49503 | E39: =IF(Master!$E39=0,"",Master!$E39) -> 616-235-3500 | F39: =IF(Master!$F39=0,"",Master!$F39) -> Professional Services | G39: =Master!G39 -> 14832.5 | H39: ='Draw 3'!H39+1425 -> 2172.5 | I39: =+G39+H39 -> 17005 | J39: ='Draw 3'!J39+'Draw 3'!K39 -> 15580 | K39: 1425 | L39: =+I39-J39-K39 -> 0
A40: 24 | B40: =IF(Master!$B40=0,"",Master!$B40) | D40: =IF(Master!$D40=0,"",Master!$D40) | E40: =IF(Master!$E40=0,"",Master!$E40) | F40: =IF(Master!$F40=0,"",Master!$F40) | G40: =Master!G40 -> 0 | H40: ='Draw 3'!H40 -> 0 | I40: =+G40+H40 -> 0 | J40: ='Draw 3'!J40+'Draw 3'!K40 -> 0 | L40: =+I40-J40-K40 -> 0
A41: 25 | B41: =IF(Master!$B41=0,"",Master!$B41) | D41: =IF(Master!$D41=0,"",Master!$D41) | E41: =IF(Master!$E41=0,"",Master!$E41) | F41: =IF(Master!$F41=0,"",Master!$F41) | G41: =Master!G41 -> 0 | H41: ='Draw 3'!H41 -> 0 | I41: =+G41+H41 -> 0 | J41: ='Draw 3'!J41+'Draw 3'!K41 -> 0 | L41: =+I41-J41-K41 -> 0
A42: 26 | B42: =IF(Master!$B42=0,"",Master!$B42) | D42: =IF(Master!$D42=0,"",Master!$D42) | E42: =IF(Master!$E42=0,"",Master!$E42) | F42: =IF(Master!$F42=0,"",Master!$F42) | G42: =Master!G42 -> 0 | H42: ='Draw 3'!H42 -> 0 | I42: =+G42+H42 -> 0 | J42: ='Draw 3'!J42+'Draw 3'!K42 -> 0 | L42: =+I42-J42-K42 -> 0
A43: 27 | B43: =IF(Master!$B43=0,"",Master!$B43) | D43: =IF(Master!$D43=0,"",Master!$D43) | E43: =IF(Master!$E43=0,"",Master!$E43) | F43: =IF(Master!$F43=0,"",Master!$F43) | G43: =Master!G43 -> 0 | H43: ='Draw 3'!H43 -> 0 | I43: =+G43+H43 -> 0 | J43: ='Draw 3'!J43+'Draw 3'!K43 -> 0 | L43: =+I43-J43-K43 -> 0
A44: 28 | B44: =IF(Master!$B44=0,"",Master!$B44) | D44: =IF(Master!$D44=0,"",Master!$D44) | E44: =IF(Master!$E44=0,"",Master!$E44) | F44: =IF(Master!$F44=0,"",Master!$F44) -> Contingency | G44: =Master!G44 -> 48532.35 | H44: ='Draw 3'!H44 -> -18535.25 | I44: =+G44+H44 -> 29997.1 | J44: ='Draw 3'!J44+'Draw 3'!K44 -> 0 | L44: =+I44-J44-K44 -> 29997.1
A45: 29 | B45: =IF(Master!$B45=0,"",Master!$B45) | D45: =IF(Master!$D45=0,"",Master!$D45) | E45: =IF(Master!$E45=0,"",Master!$E45) | F45: =IF(Master!$F45=0,"",Master!$F45) -> Interest Carry | G45: =Master!G45 -> 46433.43 | H45: ='Draw 3'!H45 -> 0 | I45: =+G45+H45 -> 46433.43 | J45: ='Draw 3'!J45+'Draw 3'!K45 -> 1935.9 | K45: 6625.94 | L45: =+I45-J45-K45 -> 37871.59
A46: 30 | B46: =IF(Master!$B46=0,"",Master!$B46) | D46: =IF(Master!$D46=0,"",Master!$D46) | E46: =IF(Master!$E46=0,"",Master!$E46) | F46: =IF(Master!$F46=0,"",Master!$F46) -> Land | G46: =Master!G46 -> 234300 | H46: ='Draw 3'!H46 -> 0 | I46: =+G46+H46 -> 234300 | J46: ='Draw 3'!J46+'Draw 3'!K46 -> 234300 | L46: =+I46-J46-K46 -> 0
F47: SUBTOTALS | G47: =SUM(G17:G46) -> 1268365.7 | H47: =SUM(H17:H46) -> 0 | I47: =SUM(I17:I46) -> 1268365.7 | J47: =SUM(J17:J46) -> 1033442 | K47: =SUM(K17:K46) -> 101145.94 | L47: =SUM(L17:L46) -> 133777.78
B48: WARNING TO OWNER OR LESSEE: An owner or lessee of the property may not rely on this sworn statement to avoid the claim of a subcontractor, supplier, or laborer who has provided a Notice of Furnishing or a laborer who may provide a Notice of Furnishing under Section 109 of the Construction Lien Act, 1980 PA 497, MCL 570.1109, to the designee or to the owner or lessee if the designee is not named or has died.
B52: Name of Subcontractor, Supplier or Laborer | D52: Address of Subcontractor, Supplier or Laborer | E52: Telephone # | F52: Type of Improvement Furnished | G52: Total Contract Price | H52: Adjustment to Contract Amount ( +/ -) | I52: Adjusted Contract Price | J52: Amount Already Paid | K52: Current Request | L52: Balance to Complete
A53: 31 | B53: =IF(Master!$B53=0,"",Master!$B53) | D53: =IF(Master!$D53=0,"",Master!$D53) | E53: =IF(Master!$E53=0,"",Master!$E53) | F53: =IF(Master!$F53=0,"",Master!$F53) | G53: =Master!G53 -> 0 | H53: ='Draw 3'!H53 -> 0 | I53: =+G53+H53 -> 0 | J53: ='Draw 3'!J53+'Draw 3'!K53 -> 0 | L53: =+I53-J53-K53 -> 0
A54: 32 | B54: =IF(Master!$B54=0,"",Master!$B54) | D54: =IF(Master!$D54=0,"",Master!$D54) | E54: =IF(Master!$E54=0,"",Master!$E54) | F54: =IF(Master!$F54=0,"",Master!$F54) | G54: =Master!G54 -> 0 | H54: ='Draw 3'!H54 -> 0 | I54: =+G54+H54 -> 0 | J54: ='Draw 3'!J54+'Draw 3'!K54 -> 0 | L54: =+I54-J54-K54 -> 0
A55: 33 | B55: =IF(Master!$B55=0,"",Master!$B55) | D55: =IF(Master!$D55=0,"",Master!$D55) | E55: =IF(Master!$E55=0,"",Master!$E55) | F55: =IF(Master!$F55=0,"",Master!$F55) | G55: =Master!G55 -> 0 | H55: ='Draw 3'!H55 -> 0 | I55: =+G55+H55 -> 0 | J55: ='Draw 3'!J55+'Draw 3'!K55 -> 0 | L55: =+I55-J55-K55 -> 0
A56: 34 | B56: =IF(Master!$B56=0,"",Master!$B56) | D56: =IF(Master!$D56=0,"",Master!$D56) | E56: =IF(Master!$E56=0,"",Master!$E56) | F56: =IF(Master!$F56=0,"",Master!$F56) | G56: =Master!G56 -> 0 | H56: ='Draw 3'!H56 -> 0 | I56: =+G56+H56 -> 0 | J56: ='Draw 3'!J56+'Draw 3'!K56 -> 0 | L56: =+I56-J56-K56 -> 0
A57: 35 | B57: =IF(Master!$B57=0,"",Master!$B57) | D57: =IF(Master!$D57=0,"",Master!$D57) | E57: =IF(Master!$E57=0,"",Master!$E57) | F57: =IF(Master!$F57=0,"",Master!$F57) | G57: =Master!G57 -> 0 | H57: ='Draw 3'!H57 -> 0 | I57: =+G57+H57 -> 0 | J57: ='Draw 3'!J57+'Draw 3'!K57 -> 0 | L57: =+I57-J57-K57 -> 0
A58: 36 | B58: =IF(Master!$B58=0,"",Master!$B58) | D58: =IF(Master!$D58=0,"",Master!$D58) | E58: =IF(Master!$E58=0,"",Master!$E58) | F58: =IF(Master!$F58=0,"",Master!$F58) | G58: =Master!G58 -> 0 | H58: ='Draw 3'!H58 -> 0 | I58: =+G58+H58 -> 0 | J58: ='Draw 3'!J58+'Draw 3'!K58 -> 0 | L58: =+I58-J58-K58 -> 0
A59: 37 | B59: =IF(Master!$B59=0,"",Master!$B59) | D59: =IF(Master!$D59=0,"",Master!$D59) | E59: =IF(Master!$E59=0,"",Master!$E59) | F59: =IF(Master!$F59=0,"",Master!$F59) | G59: =Master!G59 -> 0 | H59: ='Draw 3'!H59 -> 0 | I59: =+G59+H59 -> 0 | J59: ='Draw 3'!J59+'Draw 3'!K59 -> 0 | L59: =+I59-J59-K59 -> 0
A60: 38 | B60: =IF(Master!$B60=0,"",Master!$B60) | D60: =IF(Master!$D60=0,"",Master!$D60) | E60: =IF(Master!$E60=0,"",Master!$E60) | F60: =IF(Master!$F60=0,"",Master!$F60) | G60: =Master!G60 -> 0 | H60: ='Draw 3'!H60 -> 0 | I60: =+G60+H60 -> 0 | J60: ='Draw 3'!J60+'Draw 3'!K60 -> 0 | L60: =+I60-J60-K60 -> 0
A61: 39 | B61: =IF(Master!$B61=0,"",Master!$B61) | D61: =IF(Master!$D61=0,"",Master!$D61) | E61: =IF(Master!$E61=0,"",Master!$E61) | F61: =IF(Master!$F61=0,"",Master!$F61) | G61: =Master!G61 -> 0 | H61: ='Draw 3'!H61 -> 0 | I61: =+G61+H61 -> 0 | J61: ='Draw 3'!J61+'Draw 3'!K61 -> 0 | L61: =+I61-J61-K61 -> 0
A62: 40 | B62: =IF(Master!$B62=0,"",Master!$B62) | D62: =IF(Master!$D62=0,"",Master!$D62) | E62: =IF(Master!$E62=0,"",Master!$E62) | F62: =IF(Master!$F62=0,"",Master!$F62) | G62: =Master!G62 -> 0 | H62: ='Draw 3'!H62 -> 0 | I62: =+G62+H62 -> 0 | J62: ='Draw 3'!J62+'Draw 3'!K62 -> 0 | L62: =+I62-J62-K62 -> 0
A63: 41 | B63: =IF(Master!$B63=0,"",Master!$B63) | D63: =IF(Master!$D63=0,"",Master!$D63) | E63: =IF(Master!$E63=0,"",Master!$E63) | F63: =IF(Master!$F63=0,"",Master!$F63) | G63: =Master!G63 -> 0 | H63: ='Draw 3'!H63 -> 0 | I63: =+G63+H63 -> 0 | J63: ='Draw 3'!J63+'Draw 3'!K63 -> 0 | L63: =+I63-J63-K63 -> 0
A64: 42 | B64: =IF(Master!$B64=0,"",Master!$B64) | D64: =IF(Master!$D64=0,"",Master!$D64) | E64: =IF(Master!$E64=0,"",Master!$E64) | F64: =IF(Master!$F64=0,"",Master!$F64) | G64: =Master!G64 -> 0 | H64: ='Draw 3'!H64 -> 0 | I64: =+G64+H64 -> 0 | J64: ='Draw 3'!J64+'Draw 3'!K64 -> 0 | L64: =+I64-J64-K64 -> 0
... A82: 60 | B82: =IF(Master!$B82=0,"",Master!$B82) | D82: =IF(Master!$D82=0,"",Master!$D82) | E82: =IF(Master!$E82=0,"",Master!$E82) | F82: =IF(Master!$F82=0,"",Master!$F82) | G82: =Master!G82 -> 0 | H82: ='Draw 3'!H82 -> 0 | I82: =+G82+H82 -> 0 | J82: ='Draw 3'!J82+'Draw 3'!K82 -> 0 | L82: =+I82-J82-K82 -> 0
F83: Total | G83: =SUM(G53:G82)+G47 -> 1268365.7 | H83: =SUM(H53:H82)+H47 -> 0 | I83: =SUM(I53:I82)+I47 -> 1268365.7 | J83: =SUM(J53:J82)+J47 -> 1033442 | K83: =SUM(K53:K82)+K47 -> 101145.94 | L83: =SUM(L53:L82)+L47 -> 133777.78
B84: If this sworn statement is in regard to a residential structure (defined as "an individual residential condominium unit or a residential building containing not more than 2 residential units,
B85: the land on which it is or will be located, and all appurtenances, in which the owner or lessee contracting for the improvement is residing or will reside upon completion of the improvement"), on
B86: receipt of this sworn statement, the owner or lessee, or the owner's or lessee's designee must give notice of its receipt, either in writing, or by telephone, or personally, to each subcontractor,
B87: supplier, and laborer who has provided a Notice of Furnishing under Section 109 or, if a Notice of Furnishing is excused under Section 108 or 108A, to each subcontractor, supplier, and
B88: laborer named in the sworn statement. If a subcontractor, supplier, or laborer who has provided a Notice of Furnishing or who is named in the sworn statement makes a request, the
B89: owner, lessee, or designee shall provide the requester a copy of the sworn statement within 10 business days after receiving the request.
D92: ='Example of Residential SS'!D92
D93: (DEPONENT) | F93: DATE
B95: WARNING TO DEPONENT: A person gives a false sworn statement with intent to defraud is
B96: subject to criminal penalties as provided in Section 110 of the Construction Lien Act, 1980 PA 497, MCL570.1110.
C99: Subscribed and sworn to before me on | E99: (date) by
C101: Notary Public | E101: County, Michigan
C103: My Commission expires: | L103: =IF('Example of Residential SS'!L103=0,"",'Example of Residential SS'!L103)

Sheet Draw 5
A1: OWNER'S SWORN STATEMENT - Draw #5
K2: Title Company File #
B3: Owner: | C3: =+Master!C3 -> Wolven Investments LLC | F3: General Contractor Name: | G3: =+Master!G3 -> Wolven Investments LLC | K3: Phone # | L3: =+Master!L3 -> 0
B4: Address of | F4: Person Submitting: | G4: =+Master!G4 -> Jeff Klaasen | K4: Email address | L4: =+Master!L4 -> 0
B5: Improvements: | C5: =+Master!C5 -> 43 North Phase 2 | G5: (authorized person signing sworn statement) | K5: Cell phone # | L5: =+Master!L5 -> 0
B7: State of Michigan | D7: ) | G7: (2) The following is a statement of each subcontractor and supplier, and laborer for whom payment of wages or fringe benefits and withholdings is due but unpaid, with whom the (contractor) (subcontractor) has (contracted) (subcontracted) for performance under the contract with the owner or lessee of the property, and the amounts due to the persons as of the date of this statement are correctly and fully set forth opposite their names. (3) The contractor has not procured material from, or subcontracted with, any person other than those set forth and owes no money for the improvement other than the sums set forth. (4) I make this statement as the (contractor) (subcontractor) or as ____________________ of the (contractor) (subcontractor) to represent to the owner or lessee of the property and his or her agents that the property is free from claims of construction liens, or the possibility of construction liens, except as specifically set forth in this statement except for claims of construction liens by laborers that may be provided under Section 109 of the Construction Lien Act, 1980 PA 497, MCL 570.1109.
D8: ) ss.
B9: County of: | C9: =+Master!C9 -> Kent | D9: )
B11: =IF(G4=0,"",G4) -> Jeff Klaasen | D11: (deponent), being sworn, states the following:
A12: (1) | B12: =+G3 -> Wolven Investments LLC | D12: is the (contractor) (subcontractor) for an improvement to the following real
B13: property in | C13: =+C9 -> Kent | D13: County, Michigan described as follows:
B16: Name of Subcontractor, Supplier or Laborer | D16: Address of Subcontractor, Supplier or Laborer | E16: Telephone # | F16: Type of Improvement Furnished | G16: Total Contract Price | H16: Adjustment to Contract Amount ( +/ -) | I16: Adjusted Contract Price | J16: Amount Already Paid | K16: Current Request | L16: Balance to Complete
A17: 1 | B17: =IF(Master!$B17=0,"",Master!$B17) -> Jack Dykstra Excavating | D17: =IF(Master!$D17=0,"",Master!$D17) -> 3677 3 Mile Rd., Grand Rapids, MI 49534 | E17: =IF(Master!$E17=0,"",Master!$E17) -> 616-453-4827 | F17: =IF(Master!$F17=0,"",Master!$F17) -> GC Contract Amount | G17: =Master!G17 -> 623097.95 | H17: ='Draw 4'!H17 -> 18535.25 | I17: =+G17+H17 -> 641633.2 | J17: ='Draw 4'!J17+'Draw 4'!K17 -> 641633.2 | L17: =+I17-J17-K17 -> 0
A18: 2 | B18: =IF(Master!$B18=0,"",Master!$B18) | D18: =IF(Master!$D18=0,"",Master!$D18) | E18: =IF(Master!$E18=0,"",Master!$E18) | F18: =IF(Master!$F18=0,"",Master!$F18) | G18: =Master!G18 -> 0 | H18: ='Draw 4'!H18 -> 0 | I18: =+G18+H18 -> 0 | J18: ='Draw 4'!J18+'Draw 4'!K18 -> 0 | L18: =+I18-J18-K18 -> 0
A19: 3 | B19: =IF(Master!$B19=0,"",Master!$B19) -> Roosien & Associaties | D19: =IF(Master!$D19=0,"",Master!$D19) -> 5055 Plainfield Ave., Grand Rapids, MI 49525 | E19: =IF(Master!$E19=0,"",Master!$E19) -> 616-361-7220 | F19: =IF(Master!$F19=0,"",Master!$F19) -> Engineering Services | G19: =Master!G19 -> 62376 | H19: ='Draw 4'!H19 -> 15150 | I19: =+G19+H19 -> 77526 | J19: ='Draw 4'!J19+'Draw 4'!K19 -> 77526 | L19: =+I19-J19-K19 -> 0
A20: 4 | B20: =IF(Master!$B20=0,"",Master!$B20) -> Soils and Structures | D20: =IF(Master!$D20=0,"",Master!$D20) -> 6480 Grand Haven Rd Muskegon MI 49441 | E20: =IF(Master!$E20=0,"",Master!$E20) -> 1-800-933-3959 | F20: =IF(Master!$F20=0,"",Master!$F20) -> Engineering Services | G20: =Master!G20 -> 15930 | H20: ='Draw 4'!H20 -> 0 | I20: =+G20+H20 -> 15930 | J20: ='Draw 4'!J20+'Draw 4'!K20 -> 2535.5 | L20: =+I20-J20-K20 -> 13394.5
A21: 5 | B21: =IF(Master!$B21=0,"",Master!$B21) | D21: =IF(Master!$D21=0,"",Master!$D21) | E21: =IF(Master!$E21=0,"",Master!$E21) | F21: =IF(Master!$F21=0,"",Master!$F21) -> Engineering Services | G21: =Master!G21 -> 21742.22 | H21: ='Draw 4'!H21 -> -15150 | I21: =+G21+H21 -> 6592.22 | J21: ='Draw 4'!J21+'Draw 4'!K21 -> 0 | L21: =+I21-J21-K21 -> 6592.22
A22: 6 | B22: =IF(Master!$B22=0,"",Master!$B22) | D22: =IF(Master!$D22=0,"",Master!$D22) | E22: =IF(Master!$E22=0,"",Master!$E22) | F22: =IF(Master!$F22=0,"",Master!$F22) | G22: =Master!G22 -> 0 | H22: ='Draw 4'!H22 -> 0 | I22: =+G22+H22 -> 0 | J22: ='Draw 4'!J22+'Draw 4'!K22 -> 0 | L22: =+I22-J22-K22 -> 0
A23: 7 | B23: =IF(Master!$B23=0,"",Master!$B23) -> Handicap Sign | D23: =IF(Master!$D23=0,"",Master!$D23) -> 1142 Wealthy St., Grand Rapids, MI 49506 | E23: =IF(Master!$E23=0,"",Master!$E23) -> 616-454-9416 | F23: =IF(Master!$F23=0,"",Master!$F23) -> Common Area Improvements | G23: =Master!G23 -> 424.4 | H23: ='Draw 4'!H23 -> 0 | I23: =+G23+H23 -> 424.4 | J23: ='Draw 4'!J23+'Draw 4'!K23 -> 424.4 | L23: =+I23-J23-K23 -> 0
A24: 8 | B24: =IF(Master!$B24=0,"",Master!$B24) -> Rosendall Well Drilling | D24: =IF(Master!$D24=0,"",Master!$D24) -> 4181 Knapp, Grand Rapids, MI 49525 | E24: =IF(Master!$E24=0,"",Master!$E24) -> 616-363-2683 | F24: =IF(Master!$F24=0,"",Master!$F24) -> Common Area Improvements | G24: =Master!G24 -> 47734 | H24: ='Draw 4'!H24 -> 0 | I24: =+G24+H24 -> 47734 | J24: ='Draw 4'!J24+'Draw 4'!K24 -> 47734 | L24: =+I24-J24-K24 -> 0
A25: 9 | B25: =IF(Master!$B25=0,"",Master!$B25) | D25: =IF(Master!$D25=0,"",Master!$D25) | E25: =IF(Master!$E25=0,"",Master!$E25) | F25: =IF(Master!$F25=0,"",Master!$F25) -> Common Area Improvements | G25: =Master!G25 -> 8214.6 | H25: ='Draw 4'!H25 -> 0 | I25: =+G25+H25 -> 8214.6 | J25: ='Draw 4'!J25+'Draw 4'!K25 -> 0 | L25: =+I25-J25-K25 -> 8214.6
A26: 10 | B26: =IF(Master!$B26=0,"",Master!$B26) | D26: =IF(Master!$D26=0,"",Master!$D26) | E26: =IF(Master!$E26=0,"",Master!$E26) | F26: =IF(Master!$F26=0,"",Master!$F26) | G26: =Master!G26 -> 0 | H26: ='Draw 4'!H26 -> 0 | I26: =+G26+H26 -> 0 | J26: ='Draw 4'!J26+'Draw 4'!K26 -> 0 | L26: =+I26-J26-K26 -> 0
A27: 11 | B27: =IF(Master!$B27=0,"",Master!$B27) | D27: =IF(Master!$D27=0,"",Master!$D27) | E27: =IF(Master!$E27=0,"",Master!$E27) | F27: =IF(Master!$F27=0,"",Master!$F27) | G27: =Master!G27 -> 0 | H27: ='Draw 4'!H27 -> 0 | I27: =+G27+H27 -> 0 | J27: ='Draw 4'!J27+'Draw 4'!K27 -> 0 | L27: =+I27-J27-K27 -> 0
A28: 12 | B28: =IF(Master!$B28=0,"",Master!$B28) | D28: =IF(Master!$D28=0,"",Master!$D28) | E28: =IF(Master!$E28=0,"",Master!$E28) | F28: =IF(Master!$F28=0,"",Master!$F28) | G28: =Master!G28 -> 0 | H28: ='Draw 4'!H28 -> 0 | I28: =+G28+H28 -> 0 | J28: ='Draw 4'!J28+'Draw 4'!K28 -> 0 | L28: =+I28-J28-K28 -> 0
... A46: 30 | B46: =IF(Master!$B46=0,"",Master!$B46) | D46: =IF(Master!$D46=0,"",Master!$D46) | E46: =IF(Master!$E46=0,"",Master!$E46) | F46: =IF(Master!$F46=0,"",Master!$F46) -> Land | G46: =Master!G46 -> 234300 | H46: ='Draw 4'!H46 -> 0 | I46: =+G46+H46 -> 234300 | J46: ='Draw 4'!J46+'Draw 4'!K46 -> 234300 | L46: =+I46-J46-K46 -> 0
F47: SUBTOTALS | G47: =SUM(G17:G46) -> 1268365.7 | H47: =SUM(H17:H46) -> 0 | I47: =SUM(I17:I46) -> 1268365.7 | J47: =SUM(J17:J46) -> 1134587.9 | K47: =SUM(K17:K46) -> 0 | L47: =SUM(L17:L46) -> 133777.78
B48: WARNING TO OWNER OR LESSEE: An owner or lessee of the property may not rely on this sworn statement to avoid the claim of a subcontractor, supplier, or laborer who has provided a Notice of Furnishing or a laborer who may provide a Notice of Furnishing under Section 109 of the Construction Lien Act, 1980 PA 497, MCL 570.1109, to the designee or to the owner or lessee if the designee is not named or has died.
B52: Name of Subcontractor, Supplier or Laborer | D52: Address of Subcontractor, Supplier or Laborer | E52: Telephone # | F52: =IF(Master!$F52=0,"",Master!$F52) -> Type of Improvement Furnished | G52: Total Contract Price | H52: Adjustment to Contract Amount ( +/ -) | I52: Adjusted Contract Price | J52: Amount Already Paid | K52: Current Request | L52: Balance to Complete
A53: 31 | B53: =IF(Master!$B53=0,"",Master!$B53) | D53: =IF(Master!$D53=0,"",Master!$D53) | E53: =IF(Master!$E53=0,"",Master!$E53) | F53: =IF(Master!$F53=0,"",Master!$F53) | G53: =Master!G53 -> 0 | H53: ='Draw 4'!H53 -> 0 | I53: =+G53+H53 -> 0 | J53: ='Draw 4'!J53+'Draw 4'!K53 -> 0 | L53: =+I53-J53-K53 -> 0
A54: 32 | B54: =IF(Master!$B54=0,"",Master!$B54) | D54: =IF(Master!$D54=0,"",Master!$D54) | E54: =IF(Master!$E54=0,"",Master!$E54) | F54: =IF(Master!$F54=0,"",Master!$F54) | G54: =Master!G54 -> 0 | H54: ='Draw 4'!H54 -> 0 | I54: =+G54+H54 -> 0 | J54: ='Draw 4'!J54+'Draw 4'!K54 -> 0 | L54: =+I54-J54-K54 -> 0
A55: 33 | B55: =IF(Master!$B55=0,"",Master!$B55) | D55: =IF(Master!$D55=0,"",Master!$D55) | E55: =IF(Master!$E55=0,"",Master!$E55) | F55: =IF(Master!$F55=0,"",Master!$F55) | G55: =Master!G55 -> 0 | H55: ='Draw 4'!H55 -> 0 | I55: =+G55+H55 -> 0 | J55: ='Draw 4'!J55+'Draw 4'!K55 -> 0 | L55: =+I55-J55-K55 -> 0
A56: 34 | B56: =IF(Master!$B56=0,"",Master!$B56) | D56: =IF(Master!$D56=0,"",Master!$D56) | E56: =IF(Master!$E56=0,"",Master!$E56) | F56: =IF(Master!$F56=0,"",Master!$F56) | G56: =Master!G56 -> 0 | H56: ='Draw 4'!H56 -> 0 | I56: =+G56+H56 -> 0 | J56: ='Draw 4'!J56+'Draw 4'!K56 -> 0 | L56: =+I56-J56-K56 -> 0
A57: 35 | B57: =IF(Master!$B57=0,"",Master!$B57) | D57: =IF(Master!$D57=0,"",Master!$D57) | E57: =IF(Master!$E57=0,"",Master!$E57) | F57: =IF(Master!$F57=0,"",Master!$F57) | G57: =Master!G57 -> 0 | H57: ='Draw 4'!H57 -> 0 | I57: =+G57+H57 -> 0 | J57: ='Draw 4'!J57+'Draw 4'!K57 -> 0 | L57: =+I57-J57-K57 -> 0
A58: 36 | B58: =IF(Master!$B58=0,"",Master!$B58) | D58: =IF(Master!$D58=0,"",Master!$D58) | E58: =IF(Master!$E58=0,"",Master!$E58) | F58: =IF(Master!$F58=0,"",Master!$F58) | G58: =Master!G58 -> 0 | H58: ='Draw 4'!H58 -> 0 | I58: =+G58+H58 -> 0 | J58: ='Draw 4'!J58+'Draw 4'!K58 -> 0 | L58: =+I58-J58-K58 -> 0
A59: 37 | B59: =IF(Master!$B59=0,"",Master!$B59) | D59: =IF(Master!$D59=0,"",Master!$D59) | E59: =IF(Master!$E59=0,"",Master!$E59) | F59: =IF(Master!$F59=0,"",Master!$F59) | G59: =Master!G59 -> 0 | H59: ='Draw 4'!H59 -> 0 | I59: =+G59+H59 -> 0 | J59: ='Draw 4'!J59+'Draw 4'!K59 -> 0 | L59: =+I59-J59-K59 -> 0
A60: 38 | B60: =IF(Master!$B60=0,"",Master!$B60) | D60: =IF(Master!$D60=0,"",Master!$D60) | E60: =IF(Master!$E60=0,"",Master!$E60) | F60: =IF(Master!$F60=0,"",Master!$F60) | G60: =Master!G60 -> 0 | H60: ='Draw 4'!H60 -> 0 | I60: =+G60+H60 -> 0 | J60: ='Draw 4'!J60+'Draw 4'!K60 -> 0 | L60: =+I60-J60-K60 -> 0
A61: 39 | B61: =IF(Master!$B61=0,"",Master!$B61) | D61: =IF(Master!$D61=0,"",Master!$D61) | E61: =IF(Master!$E61=0,"",Master!$E61) | F61: =IF(Master!$F61=0,"",Master!$F61) | G61: =Master!G61 -> 0 | H61: ='Draw 4'!H61 -> 0 | I61: =+G61+H61 -> 0 | J61: ='Draw 4'!J61+'Draw 4'!K61 -> 0 | L61: =+I61-J61-K61 -> 0
A62: 40 | B62: =IF(Master!$B62=0,"",Master!$B62) | D62: =IF(Master!$D62=0,"",Master!$D62) | E62: =IF(Master!$E62=0,"",Master!$E62) | F62: =IF(Master!$F62=0,"",Master!$F62) | G62: =Master!G62 -> 0 | H62: ='Draw 4'!H62 -> 0 | I62: =+G62+H62 -> 0 | J62: ='Draw 4'!J62+'Draw 4'!K62 -> 0 | L62: =+I62-J62-K62 -> 0
A63: 41 | B63: =IF(Master!$B63=0,"",Master!$B63) | D63: =IF(Master!$D63=0,"",Master!$D63) | E63: =IF(Master!$E63=0,"",Master!$E63) | F63: =IF(Master!$F63=0,"",Master!$F63) | G63: =Master!G63 -> 0 | H63: ='Draw 4'!H63 -> 0 | I63: =+G63+H63 -> 0 | J63: ='Draw 4'!J63+'Draw 4'!K63 -> 0 | L63: =+I63-J63-K63 -> 0
A64: 42 | B64: =IF(Master!$B64=0,"",Master!$B64) | D64: =IF(Master!$D64=0,"",Master!$D64) | E64: =IF(Master!$E64=0,"",Master!$E64) | F64: =IF(Master!$F64=0,"",Master!$F64) | G64: =Master!G64 -> 0 | H64: ='Draw 4'!H64 -> 0 | I64: =+G64+H64 -> 0 | J64: ='Draw 4'!J64+'Draw 4'!K64 -> 0 | L64: =+I64-J64-K64 -> 0
... A82: 60 | B82: =IF(Master!$B82=0,"",Master!$B82) | D82: =IF(Master!$D82=0,"",Master!$D82) | E82: =IF(Master!$E82=0,"",Master!$E82) | F82: =IF(Master!$F82=0,"",Master!$F82) | G82: =Master!G82 -> 0 | H82: ='Draw 4'!H82 -> 0 | I82: =+G82+H82 -> 0 | J82: ='Draw 4'!J82+'Draw 4'!K82 -> 0 | L82: =+I82-J82-K82 -> 0
F83: Total | G83: =SUM(G53:G82)+G47 -> 1268365.7 | H83: =SUM(H53:H82)+H47 -> 0 | I83: =SUM(I53:I82)+I47 -> 1268365.7 | J83: =SUM(J53:J82)+J47 -> 1134587.9 | K83: =SUM(K53:K82)+K47 -> 0 | L83: =SUM(L53:L82)+L47 -> 133777.78
B84: If this sworn statement is in regard to a residential structure (defined as "an individual residential condominium unit or a residential building containing not more than 2 residential units,
B85: the land on which it is or will be located, and all appurtenances, in which the owner or lessee contracting for the improvement is residing or will reside upon completion of the improvement"), on
B86: receipt of this sworn statement, the owner or lessee, or the owner's or lessee's designee must give notice of its receipt, either in writing, or by telephone, or personally, to each subcontractor,
B87: supplier, and laborer who has provided a Notice of Furnishing under Section 109 or, if a Notice of Furnishing is excused under Section 108 or 108A, to each subcontractor, supplier, and
B88: laborer named in the sworn statement. If a subcontractor, supplier, or laborer who has provided a Notice of Furnishing or who is named in the sworn statement makes a request, the
B89: owner, lessee, or designee shall provide the requester a copy of the sworn statement within 10 business days after receiving the request.
D92: ='Example of Residential SS'!D92
D93: (DEPONENT) | F93: DATE
B95: WARNING TO DEPONENT: A person gives a false sworn statement with intent to defraud is
B96: subject to criminal penalties as provided in Section 110 of the Construction Lien Act, 1980 PA 497, MCL570.1110.
C99: Subscribed and sworn to before me on | E99: (date) by
C101: Notary Public | E101: County, Michigan
C103: My Commission expires: | L103: =IF('Example of Residential SS'!L103=0,"",'Example of Residential SS'!L103)

Sheet Draw 6
A1: OWNER'S SWORN STATEMENT - Draw #6
K2: Title Company File #
B3: Owner: | C3: =+Master!C3 -> Wolven Investments LLC | F3: General Contractor Name: | G3: =+Master!G3 -> Wolven Investments LLC | K3: Phone # | L3: =+Master!L3 -> 0
B4: Address of | F4: Person Submitting: | G4: =+Master!G4 -> Jeff Klaasen | K4: Email address | L4: =+Master!L4 -> 0
B5: Improvements: | C5: =+Master!C5 -> 43 North Phase 2 | G5: (authorized person signing sworn statement) | K5: Cell phone # | L5: =+Master!L5 -> 0
B7: State of Michigan | D7: ) | G7: (2) The following is a statement of each subcontractor and supplier, and laborer for whom payment of wages or fringe benefits and withholdings is due but unpaid, with whom the (contractor) (subcontractor) has (contracted) (subcontracted) for performance under the contract with the owner or lessee of the property, and the amounts due to the persons as of the date of this statement are correctly and fully set forth opposite their names. (3) The contractor has not procured material from, or subcontracted with, any person other than those set forth and owes no money for the improvement other than the sums set forth. (4) I make this statement as the (contractor) (subcontractor) or as ____________________ of the (contractor) (subcontractor) to represent to the owner or lessee of the property and his or her agents that the property is free from claims of construction liens, or the possibility of construction liens, except as specifically set forth in this statement except for claims of construction liens by laborers that may be provided under Section 109 of the Construction Lien Act, 1980 PA 497, MCL 570.1109.
D8: ) ss.
B9: County of: | C9: =+Master!C9 -> Kent | D9: )
B11: =IF(G4=0,"",G4) -> Jeff Klaasen | D11: (deponent), being sworn, states the following:
A12: (1) | B12: =+G3 -> Wolven Investments LLC | D12: is the (contractor) (subcontractor) for an improvement to the following real
B13: property in | C13: =+C9 -> Kent | D13: County, Michigan described as follows:
B16: Name of Subcontractor, Supplier or Laborer | D16: Address of Subcontractor, Supplier or Laborer | E16: Telephone # | F16: Type of Improvement Furnished | G16: Total Contract Price | H16: Adjustment to Contract Amount ( +/ -) | I16: Adjusted Contract Price | J16: Amount Already Paid | K16: Current Request | L16: Balance to Complete
A17: 1 | B17: =IF(Master!$B17=0,"",Master!$B17) -> Jack Dykstra Excavating | D17: =IF(Master!$D17=0,"",Master!$D17) -> 3677 3 Mile Rd., Grand Rapids, MI 49534 | E17: =IF(Master!$E17=0,"",Master!$E17) -> 616-453-4827 | F17: =IF(Master!$F17=0,"",Master!$F17) -> GC Contract Amount | G17: =Master!G17 -> 623097.95 | H17: ='Draw 5'!H17 -> 18535.25 | I17: =+G17+H17 -> 641633.2 | J17: ='Draw 5'!J17+'Draw 5'!K17 -> 641633.2 | L17: =+I17-J17-K17 -> 0
A18: 2 | B18: =IF(Master!$B18=0,"",Master!$B18) | D18: =IF(Master!$D18=0,"",Master!$D18) | E18: =IF(Master!$E18=0,"",Master!$E18) | F18: =IF(Master!$F18=0,"",Master!$F18) | G18: =Master!G18 -> 0 | H18: ='Draw 5'!H18 -> 0 | I18: =+G18+H18 -> 0 | J18: ='Draw 5'!J18+'Draw 5'!K18 -> 0 | L18: =+I18-J18-K18 -> 0
A19: 3 | B19: =IF(Master!$B19=0,"",Master!$B19) -> Roosien & Associaties | D19: =IF(Master!$D19=0,"",Master!$D19) -> 5055 Plainfield Ave., Grand Rapids, MI 49525 | E19: =IF(Master!$E19=0,"",Master!$E19) -> 616-361-7220 | F19: =IF(Master!$F19=0,"",Master!$F19) -> Engineering Services | G19: =Master!G19 -> 62376 | H19: ='Draw 5'!H19 -> 15150 | I19: =+G19+H19 -> 77526 | J19: ='Draw 5'!J19+'Draw 5'!K19 -> 77526 | L19: =+I19-J19-K19 -> 0
A20: 4 | B20: =IF(Master!$B20=0,"",Master!$B20) -> Soils and Structures | D20: =IF(Master!$D20=0,"",Master!$D20) -> 6480 Grand Haven Rd Muskegon MI 49441 | E20: =IF(Master!$E20=0,"",Master!$E20) -> 1-800-933-3959 | F20: =IF(Master!$F20=0,"",Master!$F20) -> Engineering Services | G20: =Master!G20 -> 15930 | H20: ='Draw 5'!H20 -> 0 | I20: =+G20+H20 -> 15930 | J20: ='Draw 5'!J20+'Draw 5'!K20 -> 2535.5 | L20: =+I20-J20-K20 -> 13394.5
A21: 5 | B21: =IF(Master!$B21=0,"",Master!$B21) | D21: =IF(Master!$D21=0,"",Master!$D21) | E21: =IF(Master!$E21=0,"",Master!$E21) | F21: =IF(Master!$F21=0,"",Master!$F21) -> Engineering Services | G21: =Master!G21 -> 21742.22 | H21: ='Draw 5'!H21 -> -15150 | I21: =+G21+H21 -> 6592.22 | J21: ='Draw 5'!J21+'Draw 5'!K21 -> 0 | L21: =+I21-J21-K21 -> 6592.22
A22: 6 | B22: =IF(Master!$B22=0,"",Master!$B22) | D22: =IF(Master!$D22=0,"",Master!$D22) | E22: =IF(Master!$E22=0,"",Master!$E22) | F22: =IF(Master!$F22=0,"",Master!$F22) | G22: =Master!G22 -> 0 | H22: ='Draw 5'!H22 -> 0 | I22: =+G22+H22 -> 0 | J22: ='Draw 5'!J22+'Draw 5'!K22 -> 0 | L22: =+I22-J22-K22 -> 0
A23: 7 | B23: =IF(Master!$B23=0,"",Master!$B23) -> Handicap Sign | D23: =IF(Master!$D23=0,"",Master!$D23) -> 1142 Wealthy St., Grand Rapids, MI 49506 | E23: =IF(Master!$E23=0,"",Master!$E23) -> 616-454-9416 | F23: =IF(Master!$F23=0,"",Master!$F23) -> Common Area Improvements | G23: =Master!G23 -> 424.4 | H23: ='Draw 5'!H23 -> 0 | I23: =+G23+H23 -> 424.4 | J23: ='Draw 5'!J23+'Draw 5'!K23 -> 424.4 | L23: =+I23-J23-K23 -> 0
A24: 8 | B24: =IF(Master!$B24=0,"",Master!$B24) -> Rosendall Well Drilling | D24: =IF(Master!$D24=0,"",Master!$D24) -> 4181 Knapp, Grand Rapids, MI 49525 | E24: =IF(Master!$E24=0,"",Master!$E24) -> 616-363-2683 | F24: =IF(Master!$F24=0,"",Master!$F24) -> Common Area Improvements | G24: =Master!G24 -> 47734 | H24: ='Draw 5'!H24 -> 0 | I24: =+G24+H24 -> 47734 | J24: ='Draw 5'!J24+'Draw 5'!K24 -> 47734 | L24: =+I24-J24-K24 -> 0
A25: 9 | B25: =IF(Master!$B25=0,"",Master!$B25) | D25: =IF(Master!$D25=0,"",Master!$D25) | E25: =IF(Master!$E25=0,"",Master!$E25) | F25: =IF(Master!$F25=0,"",Master!$F25) -> Common Area Improvements | G25: =Master!G25 -> 8214.6 | H25: ='Draw 5'!H25 -> 0 | I25: =+G25+H25 -> 8214.6 | J25: ='Draw 5'!J25+'Draw 5'!K25 -> 0 | L25: =+I25-J25-K25 -> 8214.6
A26: 10 | B26: =IF(Master!$B26=0,"",Master!$B26) | D26: =IF(Master!$D26=0,"",Master!$D26) | E26: =IF(Master!$E26=0,"",Master!$E26) | F26: =IF(Master!$F26=0,"",Master!$F26) | G26: =Master!G26 -> 0 | H26: ='Draw 5'!H26 -> 0 | I26: =+G26+H26 -> 0 | J26: ='Draw 5'!J26+'Draw 5'!K26 -> 0 | L26: =+I26-J26-K26 -> 0
A27: 11 | B27: =IF(Master!$B27=0,"",Master!$B27) | D27: =IF(Master!$D27=0,"",Master!$D27) | E27: =IF(Master!$E27=0,"",Master!$E27) | F27: =IF(Master!$F27=0,"",Master!$F27) | G27: =Master!G27 -> 0 | H27: ='Draw 5'!H27 -> 0 | I27: =+G27+H27 -> 0 | J27: ='Draw 5'!J27+'Draw 5'!K27 -> 0 | L27: =+I27-J27-K27 -> 0
A28: 12 | B28: =IF(Master!$B28=0,"",Master!$B28) | D28: =IF(Master!$D28=0,"",Master!$D28) | E28: =IF(Master!$E28=0,"",Master!$E28) | F28: =IF(Master!$F28=0,"",Master!$F28) | G28: =Master!G28 -> 0 | H28: ='Draw 5'!H28 -> 0 | I28: =+G28+H28 -> 0 | J28: ='Draw 5'!J28+'Draw 5'!K28 -> 0 | L28: =+I28-J28-K28 -> 0
... A46: 30 | B46: =IF(Master!$B46=0,"",Master!$B46) | D46: =IF(Master!$D46=0,"",Master!$D46) | E46: =IF(Master!$E46=0,"",Master!$E46) | F46: =IF(Master!$F46=0,"",Master!$F46) -> Land | G46: =Master!G46 -> 234300 | H46: ='Draw 5'!H46 -> 0 | I46: =+G46+H46 -> 234300 | J46: ='Draw 5'!J46+'Draw 5'!K46 -> 234300 | L46: =+I46-J46-K46 -> 0
F47: SUBTOTALS | G47: =SUM(G17:G46) -> 1268365.7 | H47: =SUM(H17:H46) -> 0 | I47: =SUM(I17:I46) -> 1268365.7 | J47: =SUM(J17:J46) -> 1134587.9 | K47: =SUM(K17:K46) -> 0 | L47: =SUM(L17:L46) -> 133777.78
B48: WARNING TO OWNER OR LESSEE: An owner or lessee of the property may not rely on this sworn statement to avoid the claim of a subcontractor, supplier, or laborer who has provided a Notice of Furnishing or a laborer who may provide a Notice of Furnishing under Section 109 of the Construction Lien Act, 1980 PA 497, MCL 570.1109, to the designee or to the owner or lessee if the designee is not named or has died.
B52: Name of Subcontractor, Supplier or Laborer | D52: Address of Subcontractor, Supplier or Laborer | E52: Telephone # | F52: Type of Improvement Furnished | G52: Total Contract Price | H52: Adjustment to Contract Amount ( +/ -) | I52: Adjusted Contract Price | J52: Amount Already Paid | K52: Current Request | L52: Balance to Complete
A53: 31 | B53: =IF(Master!$B53=0,"",Master!$B53) | D53: =IF(Master!$D53=0,"",Master!$D53) | E53: =IF(Master!$E53=0,"",Master!$E53) | F53: =IF(Master!$F53=0,"",Master!$F53) | G53: =Master!G53 -> 0 | H53: ='Draw 5'!H53 -> 0 | I53: =+G53+H53 -> 0 | J53: ='Draw 5'!J53+'Draw 5'!K53 -> 0 | L53: =+I53-J53-K53 -> 0
A54: 32 | B54: =IF(Master!$B54=0,"",Master!$B54) | D54: =IF(Master!$D54=0,"",Master!$D54) | E54: =IF(Master!$E54=0,"",Master!$E54) | F54: =IF(Master!$F54=0,"",Master!$F54) | G54: =Master!G54 -> 0 | H54: ='Draw 5'!H54 -> 0 | I54: =+G54+H54 -> 0 | J54: ='Draw 5'!J54+'Draw 5'!K54 -> 0 | L54: =+I54-J54-K54 -> 0
A55: 33 | B55: =IF(Master!$B55=0,"",Master!$B55) | D55: =IF(Master!$D55=0,"",Master!$D55) | E55: =IF(Master!$E55=0,"",Master!$E55) | F55: =IF(Master!$F55=0,"",Master!$F55) | G55: =Master!G55 -> 0 | H55: ='Draw 5'!H55 -> 0 | I55: =+G55+H55 -> 0 | J55: ='Draw 5'!J55+'Draw 5'!K55 -> 0 | L55: =+I55-J55-K55 -> 0
A56: 34 | B56: =IF(Master!$B56=0,"",Master!$B56) | D56: =IF(Master!$D56=0,"",Master!$D56) | E56: =IF(Master!$E56=0,"",Master!$E56) | F56: =IF(Master!$F56=0,"",Master!$F56) | G56: =Master!G56 -> 0 | H56: ='Draw 5'!H56 -> 0 | I56: =+G56+H56 -> 0 | J56: ='Draw 5'!J56+'Draw 5'!K56 -> 0 | L56: =+I56-J56-K56 -> 0
A57: 35 | B57: =IF(Master!$B57=0,"",Master!$B57) | D57: =IF(Master!$D57=0,"",Master!$D57) | E57: =IF(Master!$E57=0,"",Master!$E57) | F57: =IF(Master!$F57=0,"",Master!$F57) | G57: =Master!G57 -> 0 | H57: ='Draw 5'!H57 -> 0 | I57: =+G57+H57 -> 0 | J57: ='Draw 5'!J57+'Draw 5'!K57 -> 0 | L57: =+I57-J57-K57 -> 0
A58: 36 | B58: =IF(Master!$B58=0,"",Master!$B58) | D58: =IF(Master!$D58=0,"",Master!$D58) | E58: =IF(Master!$E58=0,"",Master!$E58) | F58: =IF(Master!$F58=0,"",Master!$F58) | G58: =Master!G58 -> 0 | H58: ='Draw 5'!H58 -> 0 | I58: =+G58+H58 -> 0 | J58: ='Draw 5'!J58+'Draw 5'!K58 -> 0 | L58: =+I58-J58-K58 -> 0
A59: 37 | B59: =IF(Master!$B59=0,"",Master!$B59) | D59: =IF(Master!$D59=0,"",Master!$D59) | E59: =IF(Master!$E59=0,"",Master!$E59) | F59: =IF(Master!$F59=0,"",Master!$F59) | G59: =Master!G59 -> 0 | H59: ='Draw 5'!H59 -> 0 | I59: =+G59+H59 -> 0 | J59: ='Draw 5'!J59+'Draw 5'!K59 -> 0 | L59: =+I59-J59-K59 -> 0
A60: 38 | B60: =IF(Master!$B60=0,"",Master!$B60) | D60: =IF(Master!$D60=0,"",Master!$D60) | E60: =IF(Master!$E60=0,"",Master!$E60) | F60: =IF(Master!$F60=0,"",Master!$F60) | G60: =Master!G60 -> 0 | H60: ='Draw 5'!H60 -> 0 | I60: =+G60+H60 -> 0 | J60: ='Draw 5'!J60+'Draw 5'!K60 -> 0 | L60: =+I60-J60-K60 -> 0
A61: 39 | B61: =IF(Master!$B61=0,"",Master!$B61) | D61: =IF(Master!$D61=0,"",Master!$D61) | E61: =IF(Master!$E61=0,"",Master!$E61) | F61: =IF(Master!$F61=0,"",Master!$F61) | G61: =Master!G61 -> 0 | H61: ='Draw 5'!H61 -> 0 | I61: =+G61+H61 -> 0 | J61: ='Draw 5'!J61+'Draw 5'!K61 -> 0 | L61: =+I61-J61-K61 -> 0
A62: 40 | B62: =IF(Master!$B62=0,"",Master!$B62) | D62: =IF(Master!$D62=0,"",Master!$D62) | E62: =IF(Master!$E62=0,"",Master!$E62) | F62: =IF(Master!$F62=0,"",Master!$F62) | G62: =Master!G62 -> 0 | H62: ='Draw 5'!H62 -> 0 | I62: =+G62+H62 -> 0 | J62: ='Draw 5'!J62+'Draw 5'!K62 -> 0 | L62: =+I62-J62-K62 -> 0
A63: 41 | B63: =IF(Master!$B63=0,"",Master!$B63) | D63: =IF(Master!$D63=0,"",Master!$D63) | E63: =IF(Master!$E63=0,"",Master!$E63) | F63: =IF(Master!$F63=0,"",Master!$F63) | G63: =Master!G63 -> 0 | H63: ='Draw 5'!H63 -> 0 | I63: =+G63+H63 -> 0 | J63: ='Draw 5'!J63+'Draw 5'!K63 -> 0 | L63: =+I63-J63-K63 -> 0
A64: 42 | B64: =IF(Master!$B64=0,"",Master!$B64) | D64: =IF(Master!$D64=0,"",Master!$D64) | E64: =IF(Master!$E64=0,"",Master!$E64) | F64: =IF(Master!$F64=0,"",Master!$F64) | G64: =Master!G64 -> 0 | H64: ='Draw 5'!H64 -> 0 | I64: =+G64+H64 -> 0 | J64: ='Draw 5'!J64+'Draw 5'!K64 -> 0 | L64: =+I64-J64-K64 -> 0
... A82: 60 | B82: =IF(Master!$B82=0,"",Master!$B82) | D82: =IF(Master!$D82=0,"",Master!$D82) | E82: =IF(Master!$E82=0,"",Master!$E82) | F82: =IF(Master!$F82=0,"",Master!$F82) | G82: =Master!G82 -> 0 | H82: ='Draw 5'!H82 -> 0 | I82: =+G82+H82 -> 0 | J82: ='Draw 5'!J82+'Draw 5'!K82 -> 0 | L82: =+I82-J82-K82 -> 0
F83: Total | G83: =SUM(G53:G82)+G47 -> 1268365.7 | H83: =SUM(H53:H82)+H47 -> 0 | I83: =SUM(I53:I82)+I47 -> 1268365.7 | J83: =SUM(J53:J82)+J47 -> 1134587.9 | K83: =SUM(K53:K82)+K47 -> 0 | L83: =SUM(L53:L82)+L47 -> 133777.78
B84: If this sworn statement is in regard to a residential structure (defined as "an individual residential condominium unit or a residential building containing not more than 2 residential units,
B85: the land on which it is or will be located, and all appurtenances, in which the owner or lessee contracting for the improvement is residing or will reside upon completion of the improvement"), on
B86: receipt of this sworn statement, the owner or lessee, or the owner's or lessee's designee must give notice of its receipt, either in writing, or by telephone, or personally, to each subcontractor,
B87: supplier, and laborer who has provided a Notice of Furnishing under Section 109 or, if a Notice of Furnishing is excused under Section 108 or 108A, to each subcontractor, supplier, and
B88: laborer named in the sworn statement. If a subcontractor, supplier, or laborer who has provided a Notice of Furnishing or who is named in the sworn statement makes a request, the
B89: owner, lessee, or designee shall provide the requester a copy of the sworn statement within 10 business days after receiving the request.
D92: ='Example of Residential SS'!D92
D93: (DEPONENT) | F93: DATE
B95: WARNING TO DEPONENT: A person gives a false sworn statement with intent to defraud is
B96: subject to criminal penalties as provided in Section 110 of the Construction Lien Act, 1980 PA 497, MCL570.1110.
C99: Subscribed and sworn to before me on | E99: (date) by
C101: Notary Public | E101: County, Michigan
C103: My Commission expires: | L103: =IF('Example of Residential SS'!L103=0,"",'Example of Residential SS'!L103)

Sheet Draw 7
A1: OWNER'S SWORN STATEMENT - Draw #7
K2: Title Company File #
B3: Owner: | C3: =+Master!C3 -> Wolven Investments LLC | F3: General Contractor Name: | G3: =+Master!G3 -> Wolven Investments LLC | K3: Phone # | L3: =+Master!L3 -> 0
B4: Address of | F4: Person Submitting: | G4: =+Master!G4 -> Jeff Klaasen | K4: Email address | L4: =+Master!L4 -> 0
B5: Improvements: | C5: =+Master!C5 -> 43 North Phase 2 | G5: (authorized person signing sworn statement) | K5: Cell phone # | L5: =+Master!L5 -> 0
B7: State of Michigan | D7: ) | G7: (2) The following is a statement of each subcontractor and supplier, and laborer for whom payment of wages or fringe benefits and withholdings is due but unpaid, with whom the (contractor) (subcontractor) has (contracted) (subcontracted) for performance under the contract with the owner or lessee of the property, and the amounts due to the persons as of the date of this statement are correctly and fully set forth opposite their names. (3) The contractor has not procured material from, or subcontracted with, any person other than those set forth and owes no money for the improvement other than the sums set forth. (4) I make this statement as the (contractor) (subcontractor) or as ____________________ of the (contractor) (subcontractor) to represent to the owner or lessee of the property and his or her agents that the property is free from claims of construction liens, or the possibility of construction liens, except as specifically set forth in this statement except for claims of construction liens by laborers that may be provided under Section 109 of the Construction Lien Act, 1980 PA 497, MCL 570.1109.
D8: ) ss.
B9: County of: | C9: =+Master!C9 -> Kent | D9: )
B11: =IF(G4=0,"",G4) -> Jeff Klaasen | D11: (deponent), being sworn, states the following:
A12: (1) | B12: =+G3 -> Wolven Investments LLC | D12: is the (contractor) (subcontractor) for an improvement to the following real
B13: property in | C13: =+C9 -> Kent | D13: County, Michigan described as follows:
B16: Name of Subcontractor, Supplier or Laborer | D16: Address of Subcontractor, Supplier or Laborer | E16: Telephone # | F16: Type of Improvement Furnished | G16: Total Contract Price | H16: Adjustment to Contract Amount ( +/ -) | I16: Adjusted Contract Price | J16: Amount Already Paid | K16: Current Request | L16: Balance to Complete
A17: 1 | B17: =IF(Master!$B17=0,"",Master!$B17) -> Jack Dykstra Excavating | D17: =IF(Master!$D17=0,"",Master!$D17) -> 3677 3 Mile Rd., Grand Rapids, MI 49534 | E17: =IF(Master!$E17=0,"",Master!$E17) -> 616-453-4827 | F17: =IF(Master!$F17=0,"",Master!$F17) -> GC Contract Amount | G17: =Master!G17 -> 623097.95 | H17: ='Draw 6'!H17 -> 18535.25 | I17: =+G17+H17 -> 641633.2 | J17: ='Draw 6'!J17+'Draw 6'!K17 -> 641633.2 | L17: =+I17-J17-K17 -> 0
A18: 2 | B18: =IF(Master!$B18=0,"",Master!$B18) | D18: =IF(Master!$D18=0,"",Master!$D18) | E18: =IF(Master!$E18=0,"",Master!$E18) | F18: =IF(Master!$F18=0,"",Master!$F18) | G18: =Master!G18 -> 0 | H18: ='Draw 6'!H18 -> 0 | I18: =+G18+H18 -> 0 | J18: ='Draw 6'!J18+'Draw 6'!K18 -> 0 | L18: =+I18-J18-K18 -> 0
A19: 3 | B19: =IF(Master!$B19=0,"",Master!$B19) -> Roosien & Associaties | D19: =IF(Master!$D19=0,"",Master!$D19) -> 5055 Plainfield Ave., Grand Rapids, MI 49525 | E19: =IF(Master!$E19=0,"",Master!$E19) -> 616-361-7220 | F19: =IF(Master!$F19=0,"",Master!$F19) -> Engineering Services | G19: =Master!G19 -> 62376 | H19: ='Draw 6'!H19 -> 15150 | I19: =+G19+H19 -> 77526 | J19: ='Draw 6'!J19+'Draw 6'!K19 -> 77526 | L19: =+I19-J19-K19 -> 0
A20: 4 | B20: =IF(Master!$B20=0,"",Master!$B20) -> Soils and Structures | D20: =IF(Master!$D20=0,"",Master!$D20) -> 6480 Grand Haven Rd Muskegon MI 49441 | E20: =IF(Master!$E20=0,"",Master!$E20) -> 1-800-933-3959 | F20: =IF(Master!$F20=0,"",Master!$F20) -> Engineering Services | G20: =Master!G20 -> 15930 | H20: ='Draw 6'!H20 -> 0 | I20: =+G20+H20 -> 15930 | J20: ='Draw 6'!J20+'Draw 6'!K20 -> 2535.5 | L20: =+I20-J20-K20 -> 13394.5
A21: 5 | B21: =IF(Master!$B21=0,"",Master!$B21) | D21: =IF(Master!$D21=0,"",Master!$D21) | E21: =IF(Master!$E21=0,"",Master!$E21) | F21: =IF(Master!$F21=0,"",Master!$F21) -> Engineering Services | G21: =Master!G21 -> 21742.22 | H21: ='Draw 6'!H21 -> -15150 | I21: =+G21+H21 -> 6592.22 | J21: ='Draw 6'!J21+'Draw 6'!K21 -> 0 | L21: =+I21-J21-K21 -> 6592.22
A22: 6 | B22: =IF(Master!$B22=0,"",Master!$B22) | D22: =IF(Master!$D22=0,"",Master!$D22) | E22: =IF(Master!$E22=0,"",Master!$E22) | F22: =IF(Master!$F22=0,"",Master!$F22) | G22: =Master!G22 -> 0 | H22: ='Draw 6'!H22 -> 0 | I22: =+G22+H22 -> 0 | J22: ='Draw 6'!J22+'Draw 6'!K22 -> 0 | L22: =+I22-J22-K22 -> 0
A23: 7 | B23: =IF(Master!$B23=0,"",Master!$B23) -> Handicap Sign | D23: =IF(Master!$D23=0,"",Master!$D23) -> 1142 Wealthy St., Grand Rapids, MI 49506 | E23: =IF(Master!$E23=0,"",Master!$E23) -> 616-454-9416 | F23: =IF(Master!$F23=0,"",Master!$F23) -> Common Area Improvements | G23: =Master!G23 -> 424.4 | H23: ='Draw 6'!H23 -> 0 | I23: =+G23+H23 -> 424.4 | J23: ='Draw 6'!J23+'Draw 6'!K23 -> 424.4 | L23: =+I23-J23-K23 -> 0
A24: 8 | B24: =IF(Master!$B24=0,"",Master!$B24) -> Rosendall Well Drilling | D24: =IF(Master!$D24=0,"",Master!$D24) -> 4181 Knapp, Grand Rapids, MI 49525 | E24: =IF(Master!$E24=0,"",Master!$E24) -> 616-363-2683 | F24: =IF(Master!$F24=0,"",Master!$F24) -> Common Area Improvements | G24: =Master!G24 -> 47734 | H24: ='Draw 6'!H24 -> 0 | I24: =+G24+H24 -> 47734 | J24: ='Draw 6'!J24+'Draw 6'!K24 -> 47734 | L24: =+I24-J24-K24 -> 0
A25: 9 | B25: =IF(Master!$B25=0,"",Master!$B25) | D25: =IF(Master!$D25=0,"",Master!$D25) | E25: =IF(Master!$E25=0,"",Master!$E25) | F25: =IF(Master!$F25=0,"",Master!$F25) -> Common Area Improvements | G25: =Master!G25 -> 8214.6 | H25: ='Draw 6'!H25 -> 0 | I25: =+G25+H25 -> 8214.6 | J25: ='Draw 6'!J25+'Draw 6'!K25 -> 0 | L25: =+I25-J25-K25 -> 8214.6
A26: 10 | B26: =IF(Master!$B26=0,"",Master!$B26) | D26: =IF(Master!$D26=0,"",Master!$D26) | E26: =IF(Master!$E26=0,"",Master!$E26) | F26: =IF(Master!$F26=0,"",Master!$F26) | G26: =Master!G26 -> 0 | H26: ='Draw 6'!H26 -> 0 | I26: =+G26+H26 -> 0 | J26: ='Draw 6'!J26+'Draw 6'!K26 -> 0 | L26: =+I26-J26-K26 -> 0
A27: 11 | B27: =IF(Master!$B27=0,"",Master!$B27) | D27: =IF(Master!$D27=0,"",Master!$D27) | E27: =IF(Master!$E27=0,"",Master!$E27) | F27: =IF(Master!$F27=0,"",Master!$F27) | G27: =Master!G27 -> 0 | H27: ='Draw 6'!H27 -> 0 | I27: =+G27+H27 -> 0 | J27: ='Draw 6'!J27+'Draw 6'!K27 -> 0 | L27: =+I27-J27-K27 -> 0
A28: 12 | B28: =IF(Master!$B28=0,"",Master!$B28) | D28: =IF(Master!$D28=0,"",Master!$D28) | E28: =IF(Master!$E28=0,"",Master!$E28) | F28: =IF(Master!$F28=0,"",Master!$F28) | G28: =Master!G28 -> 0 | H28: ='Draw 6'!H28 -> 0 | I28: =+G28+H28 -> 0 | J28: ='Draw 6'!J28+'Draw 6'!K28 -> 0 | L28: =+I28-J28-K28 -> 0
... A46: 30 | B46: =IF(Master!$B46=0,"",Master!$B46) | D46: =IF(Master!$D46=0,"",Master!$D46) | E46: =IF(Master!$E46=0,"",Master!$E46) | F46: =IF(Master!$F46=0,"",Master!$F46) -> Land | G46: =Master!G46 -> 234300 | H46: ='Draw 6'!H46 -> 0 | I46: =+G46+H46 -> 234300 | J46: ='Draw 6'!J46+'Draw 6'!K46 -> 234300 | L46: =+I46-J46-K46 -> 0
F47: SUBTOTALS | G47: =SUM(G17:G46) -> 1268365.7 | H47: =SUM(H17:H46) -> 0 | I47: =SUM(I17:I46) -> 1268365.7 | J47: =SUM(J17:J46) -> 1134587.9 | K47: =SUM(K17:K46) -> 0 | L47: =SUM(L17:L46) -> 133777.78
B48: WARNING TO OWNER OR LESSEE: An owner or lessee of the property may not rely on this sworn statement to avoid the claim of a subcontractor, supplier, or laborer who has provided a Notice of Furnishing or a laborer who may provide a Notice of Furnishing under Section 109 of the Construction Lien Act, 1980 PA 497, MCL 570.1109, to the designee or to the owner or lessee if the designee is not named or has died.
B52: Name of Subcontractor, Supplier or Laborer | D52: Address of Subcontractor, Supplier or Laborer | E52: Telephone # | F52: Type of Improvement Furnished | G52: Total Contract Price | H52: Adjustment to Contract Amount ( +/ -) | I52: Adjusted Contract Price | J52: Amount Already Paid | K52: Current Request | L52: Balance to Complete
A53: 31 | B53: =IF(Master!$B53=0,"",Master!$B53) | D53: =IF(Master!$D53=0,"",Master!$D53) | E53: =IF(Master!$E53=0,"",Master!$E53) | F53: =IF(Master!$F53=0,"",Master!$F53) | G53: =Master!G53 -> 0 | H53: ='Draw 6'!H53 -> 0 | I53: =+G53+H53 -> 0 | J53: ='Draw 6'!J53+'Draw 6'!K53 -> 0 | L53: =+I53-J53-K53 -> 0
A54: 32 | B54: =IF(Master!$B54=0,"",Master!$B54) | D54: =IF(Master!$D54=0,"",Master!$D54) | E54: =IF(Master!$E54=0,"",Master!$E54) | F54: =IF(Master!$F54=0,"",Master!$F54) | G54: =Master!G54 -> 0 | H54: ='Draw 6'!H54 -> 0 | I54: =+G54+H54 -> 0 | J54: ='Draw 6'!J54+'Draw 6'!K54 -> 0 | L54: =+I54-J54-K54 -> 0
A55: 33 | B55: =IF(Master!$B55=0,"",Master!$B55) | D55: =IF(Master!$D55=0,"",Master!$D55) | E55: =IF(Master!$E55=0,"",Master!$E55) | F55: =IF(Master!$F55=0,"",Master!$F55) | G55: =Master!G55 -> 0 | H55: ='Draw 6'!H55 -> 0 | I55: =+G55+H55 -> 0 | J55: ='Draw 6'!J55+'Draw 6'!K55 -> 0 | L55: =+I55-J55-K55 -> 0
A56: 34 | B56: =IF(Master!$B56=0,"",Master!$B56) | D56: =IF(Master!$D56=0,"",Master!$D56) | E56: =IF(Master!$E56=0,"",Master!$E56) | F56: =IF(Master!$F56=0,"",Master!$F56) | G56: =Master!G56 -> 0 | H56: ='Draw 6'!H56 -> 0 | I56: =+G56+H56 -> 0 | J56: ='Draw 6'!J56+'Draw 6'!K56 -> 0 | L56: =+I56-J56-K56 -> 0
A57: 35 | B57: =IF(Master!$B57=0,"",Master!$B57) | D57: =IF(Master!$D57=0,"",Master!$D57) | E57: =IF(Master!$E57=0,"",Master!$E57) | F57: =IF(Master!$F57=0,"",Master!$F57) | G57: =Master!G57 -> 0 | H57: ='Draw 6'!H57 -> 0 | I57: =+G57+H57 -> 0 | J57: ='Draw 6'!J57+'Draw 6'!K57 -> 0 | L57: =+I57-J57-K57 -> 0
A58: 36 | B58: =IF(Master!$B58=0,"",Master!$B58) | D58: =IF(Master!$D58=0,"",Master!$D58) | E58: =IF(Master!$E58=0,"",Master!$E58) | F58: =IF(Master!$F58=0,"",Master!$F58) | G58: =Master!G58 -> 0 | H58: ='Draw 6'!H58 -> 0 | I58: =+G58+H58 -> 0 | J58: ='Draw 6'!J58+'Draw 6'!K58 -> 0 | L58: =+I58-J58-K58 -> 0
A59: 37 | B59: =IF(Master!$B59=0,"",Master!$B59) | D59: =IF(Master!$D59=0,"",Master!$D59) | E59: =IF(Master!$E59=0,"",Master!$E59) | F59: =IF(Master!$F59=0,"",Master!$F59) | G59: =Master!G59 -> 0 | H59: ='Draw 6'!H59 -> 0 | I59: =+G59+H59 -> 0 | J59: ='Draw 6'!J59+'Draw 6'!K59 -> 0 | L59: =+I59-J59-K59 -> 0
A60: 38 | B60: =IF(Master!$B60=0,"",Master!$B60) | D60: =IF(Master!$D60=0,"",Master!$D60) | E60: =IF(Master!$E60=0,"",Master!$E60) | F60: =IF(Master!$F60=0,"",Master!$F60) | G60: =Master!G60 -> 0 | H60: ='Draw 6'!H60 -> 0 | I60: =+G60+H60 -> 0 | J60: ='Draw 6'!J60+'Draw 6'!K60 -> 0 | L60: =+I60-J60-K60 -> 0
A61: 39 | B61: =IF(Master!$B61=0,"",Master!$B61) | D61: =IF(Master!$D61=0,"",Master!$D61) | E61: =IF(Master!$E61=0,"",Master!$E61) | F61: =IF(Master!$F61=0,"",Master!$F61) | G61: =Master!G61 -> 0 | H61: ='Draw 6'!H61 -> 0 | I61: =+G61+H61 -> 0 | J61: ='Draw 6'!J61+'Draw 6'!K61 -> 0 | L61: =+I61-J61-K61 -> 0
A62: 40 | B62: =IF(Master!$B62=0,"",Master!$B62) | D62: =IF(Master!$D62=0,"",Master!$D62) | E62: =IF(Master!$E62=0,"",Master!$E62) | F62: =IF(Master!$F62=0,"",Master!$F62) | G62: =Master!G62 -> 0 | H62: ='Draw 6'!H62 -> 0 | I62: =+G62+H62 -> 0 | J62: ='Draw 6'!J62+'Draw 6'!K62 -> 0 | L62: =+I62-J62-K62 -> 0
A63: 41 | B63: =IF(Master!$B63=0,"",Master!$B63) | D63: =IF(Master!$D63=0,"",Master!$D63) | E63: =IF(Master!$E63=0,"",Master!$E63) | F63: =IF(Master!$F63=0,"",Master!$F63) | G63: =Master!G63 -> 0 | H63: ='Draw 6'!H63 -> 0 | I63: =+G63+H63 -> 0 | J63: ='Draw 6'!J63+'Draw 6'!K63 -> 0 | L63: =+I63-J63-K63 -> 0
A64: 42 | B64: =IF(Master!$B64=0,"",Master!$B64) | D64: =IF(Master!$D64=0,"",Master!$D64) | E64: =IF(Master!$E64=0,"",Master!$E64) | F64: =IF(Master!$F64=0,"",Master!$F64) | G64: =Master!G64 -> 0 | H64: ='Draw 6'!H64 -> 0 | I64: =+G64+H64 -> 0 | J64: ='Draw 6'!J64+'Draw 6'!K64 -> 0 | L64: =+I64-J64-K64 -> 0
... A82: 60 | B82: =IF(Master!$B82=0,"",Master!$B82) | D82: =IF(Master!$D82=0,"",Master!$D82) | E82: =IF(Master!$E82=0,"",Master!$E82) | F82: =IF(Master!$F82=0,"",Master!$F82) | G82: =Master!G82 -> 0 | H82: ='Draw 6'!H82 -> 0 | I82: =+G82+H82 -> 0 | J82: ='Draw 6'!J82+'Draw 6'!K82 -> 0 | L82: =+I82-J82-K82 -> 0
F83: Total | G83: =SUM(G53:G82)+G47 -> 1268365.7 | H83: =SUM(H53:H82)+H47 -> 0 | I83: =SUM(I53:I82)+I47 -> 1268365.7 | J83: =SUM(J53:J82)+J47 -> 1134587.9 | K83: =SUM(K53:K82)+K47 -> 0 | L83: =SUM(L53:L82)+L47 -> 133777.78
B84: If this sworn statement is in regard to a residential structure (defined as "an individual residential condominium unit or a residential building containing not more than 2 residential units,
B85: the land on which it is or will be located, and all appurtenances, in which the owner or lessee contracting for the improvement is residing or will reside upon completion of the improvement"), on
B86: receipt of this sworn statement, the owner or lessee, or the owner's or lessee's designee must give notice of its receipt, either in writing, or by telephone, or personally, to each subcontractor,
B87: supplier, and laborer who has provided a Notice of Furnishing under Section 109 or, if a Notice of Furnishing is excused under Section 108 or 108A, to each subcontractor, supplier, and
B88: laborer named in the sworn statement. If a subcontractor, supplier, or laborer who has provided a Notice of Furnishing or who is named in the sworn statement makes a request, the
B89: owner, lessee, or designee shall provide the requester a copy of the sworn statement within 10 business days after receiving the request.
D92: ='Example of Residential SS'!D92
D93: (DEPONENT) | F93: DATE
B95: WARNING TO DEPONENT: A person gives a false sworn statement with intent to defraud is
B96: subject to criminal penalties as provided in Section 110 of the Construction Lien Act, 1980 PA 497, MCL570.1110.
C99: Subscribed and sworn to before me on | E99: (date) by
C101: Notary Public | E101: County, Michigan
C103: My Commission expires: | L103: =IF('Example of Residential SS'!L103=0,"",'Example of Residential SS'!L103)

Sheet Draw 8
A1: OWNER'S SWORN STATEMENT - Draw #8
K2: Title Company File #
B3: Owner: | C3: =+Master!C3 -> Wolven Investments LLC | F3: General Contractor Name: | G3: =+Master!G3 -> Wolven Investments LLC | K3: Phone # | L3: =+Master!L3 -> 0
B4: Address of | F4: Person Submitting: | G4: =+Master!G4 -> Jeff Klaasen | K4: Email address | L4: =+Master!L4 -> 0
B5: Improvements: | C5: =+Master!C5 -> 43 North Phase 2 | G5: (authorized person signing sworn statement) | K5: Cell phone # | L5: =+Master!L5 -> 0
B7: State of Michigan | D7: ) | G7: (2) The following is a statement of each subcontractor and supplier, and laborer for whom payment of wages or fringe benefits and withholdings is due but unpaid, with whom the (contractor) (subcontractor) has (contracted) (subcontracted) for performance under the contract with the owner or lessee of the property, and the amounts due to the persons as of the date of this statement are correctly and fully set forth opposite their names. (3) The contractor has not procured material from, or subcontracted with, any person other than those set forth and owes no money for the improvement other than the sums set forth. (4) I make this statement as the (contractor) (subcontractor) or as ____________________ of the (contractor) (subcontractor) to represent to the owner or lessee of the property and his or her agents that the property is free from claims of construction liens, or the possibility of construction liens, except as specifically set forth in this statement except for claims of construction liens by laborers that may be provided under Section 109 of the Construction Lien Act, 1980 PA 497, MCL 570.1109.
D8: ) ss.
B9: County of: | C9: =+Master!C9 -> Kent | D9: )
B11: =IF(G4=0,"",G4) -> Jeff Klaasen | D11: (deponent), being sworn, states the following:
A12: (1) | B12: =+G3 -> Wolven Investments LLC | D12: is the (contractor) (subcontractor) for an improvement to the following real
B13: property in | C13: =+C9 -> Kent | D13: County, Michigan described as follows:
B16: Name of Subcontractor, Supplier or Laborer | D16: Address of Subcontractor, Supplier or Laborer | E16: Telephone # | F16: Type of Improvement Furnished | G16: Total Contract Price | H16: Adjustment to Contract Amount ( +/ -) | I16: Adjusted Contract Price | J16: Amount Already Paid | K16: Current Request | L16: Balance to Complete
A17: 1 | B17: =IF(Master!$B17=0,"",Master!$B17) -> Jack Dykstra Excavating | D17: =IF(Master!$D17=0,"",Master!$D17) -> 3677 3 Mile Rd., Grand Rapids, MI 49534 | E17: =IF(Master!$E17=0,"",Master!$E17) -> 616-453-4827 | F17: =IF(Master!$F17=0,"",Master!$F17) -> GC Contract Amount | G17: =Master!G17 -> 623097.95 | H17: ='Draw 7'!H17 -> 18535.25 | I17: =+G17+H17 -> 641633.2 | J17: ='Draw 7'!J17+'Draw 7'!K17 -> 641633.2 | L17: =+I17-J17-K17 -> 0
A18: 2 | B18: =IF(Master!$B18=0,"",Master!$B18) | D18: =IF(Master!$D18=0,"",Master!$D18) | E18: =IF(Master!$E18=0,"",Master!$E18) | F18: =IF(Master!$F18=0,"",Master!$F18) | G18: =Master!G18 -> 0 | H18: ='Draw 7'!H18 -> 0 | I18: =+G18+H18 -> 0 | J18: ='Draw 7'!J18+'Draw 7'!K18 -> 0 | L18: =+I18-J18-K18 -> 0
A19: 3 | B19: =IF(Master!$B19=0,"",Master!$B19) -> Roosien & Associaties | D19: =IF(Master!$D19=0,"",Master!$D19) -> 5055 Plainfield Ave., Grand Rapids, MI 49525 | E19: =IF(Master!$E19=0,"",Master!$E19) -> 616-361-7220 | F19: =IF(Master!$F19=0,"",Master!$F19) -> Engineering Services | G19: =Master!G19 -> 62376 | H19: ='Draw 7'!H19 -> 15150 | I19: =+G19+H19 -> 77526 | J19: ='Draw 7'!J19+'Draw 7'!K19 -> 77526 | L19: =+I19-J19-K19 -> 0
A20: 4 | B20: =IF(Master!$B20=0,"",Master!$B20) -> Soils and Structures | D20: =IF(Master!$D20=0,"",Master!$D20) -> 6480 Grand Haven Rd Muskegon MI 49441 | E20: =IF(Master!$E20=0,"",Master!$E20) -> 1-800-933-3959 | F20: =IF(Master!$F20=0,"",Master!$F20) -> Engineering Services | G20: =Master!G20 -> 15930 | H20: ='Draw 7'!H20 -> 0 | I20: =+G20+H20 -> 15930 | J20: ='Draw 7'!J20+'Draw 7'!K20 -> 2535.5 | L20: =+I20-J20-K20 -> 13394.5
A21: 5 | B21: =IF(Master!$B21=0,"",Master!$B21) | D21: =IF(Master!$D21=0,"",Master!$D21) | E21: =IF(Master!$E21=0,"",Master!$E21) | F21: =IF(Master!$F21=0,"",Master!$F21) -> Engineering Services | G21: =Master!G21 -> 21742.22 | H21: ='Draw 7'!H21 -> -15150 | I21: =+G21+H21 -> 6592.22 | J21: ='Draw 7'!J21+'Draw 7'!K21 -> 0 | L21: =+I21-J21-K21 -> 6592.22
A22: 6 | B22: =IF(Master!$B22=0,"",Master!$B22) | D22: =IF(Master!$D22=0,"",Master!$D22) | E22: =IF(Master!$E22=0,"",Master!$E22) | F22: =IF(Master!$F22=0,"",Master!$F22) | G22: =Master!G22 -> 0 | H22: ='Draw 7'!H22 -> 0 | I22: =+G22+H22 -> 0 | J22: ='Draw 7'!J22+'Draw 7'!K22 -> 0 | L22: =+I22-J22-K22 -> 0
A23: 7 | B23: =IF(Master!$B23=0,"",Master!$B23) -> Handicap Sign | D23: =IF(Master!$D23=0,"",Master!$D23) -> 1142 Wealthy St., Grand Rapids, MI 49506 | E23: =IF(Master!$E23=0,"",Master!$E23) -> 616-454-9416 | F23: =IF(Master!$F23=0,"",Master!$F23) -> Common Area Improvements | G23: =Master!G23 -> 424.4 | H23: ='Draw 7'!H23 -> 0 | I23: =+G23+H23 -> 424.4 | J23: ='Draw 7'!J23+'Draw 7'!K23 -> 424.4 | L23: =+I23-J23-K23 -> 0
A24: 8 | B24: =IF(Master!$B24=0,"",Master!$B24) -> Rosendall Well Drilling | D24: =IF(Master!$D24=0,"",Master!$D24) -> 4181 Knapp, Grand Rapids, MI 49525 | E24: =IF(Master!$E24=0,"",Master!$E24) -> 616-363-2683 | F24: =IF(Master!$F24=0,"",Master!$F24) -> Common Area Improvements | G24: =Master!G24 -> 47734 | H24: ='Draw 7'!H24 -> 0 | I24: =+G24+H24 -> 47734 | J24: ='Draw 7'!J24+'Draw 7'!K24 -> 47734 | L24: =+I24-J24-K24 -> 0
A25: 9 | B25: =IF(Master!$B25=0,"",Master!$B25) | D25: =IF(Master!$D25=0,"",Master!$D25) | E25: =IF(Master!$E25=0,"",Master!$E25) | F25: =IF(Master!$F25=0,"",Master!$F25) -> Common Area Improvements | G25: =Master!G25 -> 8214.6 | H25: ='Draw 7'!H25 -> 0 | I25: =+G25+H25 -> 8214.6 | J25: ='Draw 7'!J25+'Draw 7'!K25 -> 0 | L25: =+I25-J25-K25 -> 8214.6
A26: 10 | B26: =IF(Master!$B26=0,"",Master!$B26) | D26: =IF(Master!$D26=0,"",Master!$D26) | E26: =IF(Master!$E26=0,"",Master!$E26) | F26: =IF(Master!$F26=0,"",Master!$F26) | G26: =Master!G26 -> 0 | H26: ='Draw 7'!H26 -> 0 | I26: =+G26+H26 -> 0 | J26: ='Draw 7'!J26+'Draw 7'!K26 -> 0 | L26: =+I26-J26-K26 -> 0
A27: 11 | B27: =IF(Master!$B27=0,"",Master!$B27) | D27: =IF(Master!$D27=0,"",Master!$D27) | E27: =IF(Master!$E27=0,"",Master!$E27) | F27: =IF(Master!$F27=0,"",Master!$F27) | G27: =Master!G27 -> 0 | H27: ='Draw 7'!H27 -> 0 | I27: =+G27+H27 -> 0 | J27: ='Draw 7'!J27+'Draw 7'!K27 -> 0 | L27: =+I27-J27-K27 -> 0
A28: 12 | B28: =IF(Master!$B28=0,"",Master!$B28) | D28: =IF(Master!$D28=0,"",Master!$D28) | E28: =IF(Master!$E28=0,"",Master!$E28) | F28: =IF(Master!$F28=0,"",Master!$F28) | G28: =Master!G28 -> 0 | H28: ='Draw 7'!H28 -> 0 | I28: =+G28+H28 -> 0 | J28: ='Draw 7'!J28+'Draw 7'!K28 -> 0 | L28: =+I28-J28-K28 -> 0
... A46: 30 | B46: =IF(Master!$B46=0,"",Master!$B46) | D46: =IF(Master!$D46=0,"",Master!$D46) | E46: =IF(Master!$E46=0,"",Master!$E46) | F46: =IF(Master!$F46=0,"",Master!$F46) -> Land | G46: =Master!G46 -> 234300 | H46: ='Draw 7'!H46 -> 0 | I46: =+G46+H46 -> 234300 | J46: ='Draw 7'!J46+'Draw 7'!K46 -> 234300 | L46: =+I46-J46-K46 -> 0
F47: SUBTOTALS | G47: =SUM(G17:G46) -> 1268365.7 | H47: =SUM(H17:H46) -> 0 | I47: =SUM(I17:I46) -> 1268365.7 | J47: =SUM(J17:J46) -> 1134587.9 | K47: =SUM(K17:K46) -> 0 | L47: =SUM(L17:L46) -> 133777.78
B48: WARNING TO OWNER OR LESSEE: An owner or lessee of the property may not rely on this sworn statement to avoid the claim of a subcontractor, supplier, or laborer who has provided a Notice of Furnishing or a laborer who may provide a Notice of Furnishing under Section 109 of the Construction Lien Act, 1980 PA 497, MCL 570.1109, to the designee or to the owner or lessee if the designee is not named or has died.
B52: Name of Subcontractor, Supplier or Laborer | D52: Address of Subcontractor, Supplier or Laborer | E52: Telephone # | F52: Type of Improvement Furnished | G52: Total Contract Price | H52: Adjustment to Contract Amount ( +/ -) | I52: Adjusted Contract Price | J52: Amount Already Paid | K52: Current Request | L52: Balance to Complete
A53: 31 | B53: =IF(Master!$B53=0,"",Master!$B53) | D53: =IF(Master!$D53=0,"",Master!$D53) | E53: =IF(Master!$E53=0,"",Master!$E53) | F53: =IF(Master!$F53=0,"",Master!$F53) | G53: =Master!G53 -> 0 | H53: ='Draw 7'!H53 -> 0 | I53: =+G53+H53 -> 0 | J53: ='Draw 7'!J53+'Draw 7'!K53 -> 0 | L53: =+I53-J53-K53 -> 0
A54: 32 | B54: =IF(Master!$B54=0,"",Master!$B54) | D54: =IF(Master!$D54=0,"",Master!$D54) | E54: =IF(Master!$E54=0,"",Master!$E54) | F54: =IF(Master!$F54=0,"",Master!$F54) | G54: =Master!G54 -> 0 | H54: ='Draw 7'!H54 -> 0 | I54: =+G54+H54 -> 0 | J54: ='Draw 7'!J54+'Draw 7'!K54 -> 0 | L54: =+I54-J54-K54 -> 0
A55: 33 | B55: =IF(Master!$B55=0,"",Master!$B55) | D55: =IF(Master!$D55=0,"",Master!$D55) | E55: =IF(Master!$E55=0,"",Master!$E55) | F55: =IF(Master!$F55=0,"",Master!$F55) | G55: =Master!G55 -> 0 | H55: ='Draw 7'!H55 -> 0 | I55: =+G55+H55 -> 0 | J55: ='Draw 7'!J55+'Draw 7'!K55 -> 0 | L55: =+I55-J55-K55 -> 0
A56: 34 | B56: =IF(Master!$B56=0,"",Master!$B56) | D56: =IF(Master!$D56=0,"",Master!$D56) | E56: =IF(Master!$E56=0,"",Master!$E56) | F56: =IF(Master!$F56=0,"",Master!$F56) | G56: =Master!G56 -> 0 | H56: ='Draw 7'!H56 -> 0 | I56: =+G56+H56 -> 0 | J56: ='Draw 7'!J56+'Draw 7'!K56 -> 0 | L56: =+I56-J56-K56 -> 0
A57: 35 | B57: =IF(Master!$B57=0,"",Master!$B57) | D57: =IF(Master!$D57=0,"",Master!$D57) | E57: =IF(Master!$E57=0,"",Master!$E57) | F57: =IF(Master!$F57=0,"",Master!$F57) | G57: =Master!G57 -> 0 | H57: ='Draw 7'!H57 -> 0 | I57: =+G57+H57 -> 0 | J57: ='Draw 7'!J57+'Draw 7'!K57 -> 0 | L57: =+I57-J57-K57 -> 0
A58: 36 | B58: =IF(Master!$B58=0,"",Master!$B58) | D58: =IF(Master!$D58=0,"",Master!$D58) | E58: =IF(Master!$E58=0,"",Master!$E58) | F58: =IF(Master!$F58=0,"",Master!$F58) | G58: =Master!G58 -> 0 | H58: ='Draw 7'!H58 -> 0 | I58: =+G58+H58 -> 0 | J58: ='Draw 7'!J58+'Draw 7'!K58 -> 0 | L58: =+I58-J58-K58 -> 0
A59: 37 | B59: =IF(Master!$B59=0,"",Master!$B59) | D59: =IF(Master!$D59=0,"",Master!$D59) | E59: =IF(Master!$E59=0,"",Master!$E59) | F59: =IF(Master!$F59=0,"",Master!$F59) | G59: =Master!G59 -> 0 | H59: ='Draw 7'!H59 -> 0 | I59: =+G59+H59 -> 0 | J59: ='Draw 7'!J59+'Draw 7'!K59 -> 0 | L59: =+I59-J59-K59 -> 0
A60: 38 | B60: =IF(Master!$B60=0,"",Master!$B60) | D60: =IF(Master!$D60=0,"",Master!$D60) | E60: =IF(Master!$E60=0,"",Master!$E60) | F60: =IF(Master!$F60=0,"",Master!$F60) | G60: =Master!G60 -> 0 | H60: ='Draw 7'!H60 -> 0 | I60: =+G60+H60 -> 0 | J60: ='Draw 7'!J60+'Draw 7'!K60 -> 0 | L60: =+I60-J60-K60 -> 0
A61: 39 | B61: =IF(Master!$B61=0,"",Master!$B61) | D61: =IF(Master!$D61=0,"",Master!$D61) | E61: =IF(Master!$E61=0,"",Master!$E61) | F61: =IF(Master!$F61=0,"",Master!$F61) | G61: =Master!G61 -> 0 | H61: ='Draw 7'!H61 -> 0 | I61: =+G61+H61 -> 0 | J61: ='Draw 7'!J61+'Draw 7'!K61 -> 0 | L61: =+I61-J61-K61 -> 0
A62: 40 | B62: =IF(Master!$B62=0,"",Master!$B62) | D62: =IF(Master!$D62=0,"",Master!$D62) | E62: =IF(Master!$E62=0,"",Master!$E62) | F62: =IF(Master!$F62=0,"",Master!$F62) | G62: =Master!G62 -> 0 | H62: ='Draw 7'!H62 -> 0 | I62: =+G62+H62 -> 0 | J62: ='Draw 7'!J62+'Draw 7'!K62 -> 0 | L62: =+I62-J62-K62 -> 0
A63: 41 | B63: =IF(Master!$B63=0,"",Master!$B63) | D63: =IF(Master!$D63=0,"",Master!$D63) | E63: =IF(Master!$E63=0,"",Master!$E63) | F63: =IF(Master!$F63=0,"",Master!$F63) | G63: =Master!G63 -> 0 | H63: ='Draw 7'!H63 -> 0 | I63: =+G63+H63 -> 0 | J63: ='Draw 7'!J63+'Draw 7'!K63 -> 0 | L63: =+I63-J63-K63 -> 0
A64: 42 | B64: =IF(Master!$B64=0,"",Master!$B64) | D64: =IF(Master!$D64=0,"",Master!$D64) | E64: =IF(Master!$E64=0,"",Master!$E64) | F64: =IF(Master!$F64=0,"",Master!$F64) | G64: =Master!G64 -> 0 | H64: ='Draw 7'!H64 -> 0 | I64: =+G64+H64 -> 0 | J64: ='Draw 7'!J64+'Draw 7'!K64 -> 0 | L64: =+I64-J64-K64 -> 0
... A82: 60 | B82: =IF(Master!$B82=0,"",Master!$B82) | D82: =IF(Master!$D82=0,"",Master!$D82) | E82: =IF(Master!$E82=0,"",Master!$E82) | F82: =IF(Master!$F82=0,"",Master!$F82) | G82: =Master!G82 -> 0 | H82: ='Draw 7'!H82 -> 0 | I82: =+G82+H82 -> 0 | J82: ='Draw 7'!J82+'Draw 7'!K82 -> 0 | L82: =+I82-J82-K82 -> 0
F83: Total | G83: =SUM(G53:G82)+G47 -> 1268365.7 | H83: =SUM(H53:H82)+H47 -> 0 | I83: =SUM(I53:I82)+I47 -> 1268365.7 | J83: =SUM(J53:J82)+J47 -> 1134587.9 | K83: =SUM(K53:K82)+K47 -> 0 | L83: =SUM(L53:L82)+L47 -> 133777.78
B84: If this sworn statement is in regard to a residential structure (defined as "an individual residential condominium unit or a residential building containing not more than 2 residential units,
B85: the land on which it is or will be located, and all appurtenances, in which the owner or lessee contracting for the improvement is residing or will reside upon completion of the improvement"), on
B86: receipt of this sworn statement, the owner or lessee, or the owner's or lessee's designee must give notice of its receipt, either in writing, or by telephone, or personally, to each subcontractor,
B87: supplier, and laborer who has provided a Notice of Furnishing under Section 109 or, if a Notice of Furnishing is excused under Section 108 or 108A, to each subcontractor, supplier, and
B88: laborer named in the sworn statement. If a subcontractor, supplier, or laborer who has provided a Notice of Furnishing or who is named in the sworn statement makes a request, the
B89: owner, lessee, or designee shall provide the requester a copy of the sworn statement within 10 business days after receiving the request.
D92: ='Example of Residential SS'!D92
D93: (DEPONENT) | F93: DATE
B95: WARNING TO DEPONENT: A person gives a false sworn statement with intent to defraud is
B96: subject to criminal penalties as provided in Section 110 of the Construction Lien Act, 1980 PA 497, MCL570.1110.
C99: Subscribed and sworn to before me on | E99: (date) by
C101: Notary Public | E101: County, Michigan
C103: My Commission expires: | L103: =IF('Example of Residential SS'!L103=0,"",'Example of Residential SS'!L103)

Sheet Draw 9
A1: OWNER'S SWORN STATEMENT - Draw #9
K2: Title Company File #
B3: Owner: | C3: =+Master!C3 -> Wolven Investments LLC | F3: General Contractor Name: | G3: =+Master!G3 -> Wolven Investments LLC | K3: Phone # | L3: =+Master!L3 -> 0
B4: Address of | F4: Person Submitting: | G4: =+Master!G4 -> Jeff Klaasen | K4: Email address | L4: =+Master!L4 -> 0
B5: Improvements: | C5: =+Master!C5 -> 43 North Phase 2 | G5: (authorized person signing sworn statement) | K5: Cell phone # | L5: =+Master!L5 -> 0
B7: State of Michigan | D7: ) | G7: (2) The following is a statement of each subcontractor and supplier, and laborer for whom payment of wages or fringe benefits and withholdings is due but unpaid, with whom the (contractor) (subcontractor) has (contracted) (subcontracted) for performance under the contract with the owner or lessee of the property, and the amounts due to the persons as of the date of this statement are correctly and fully set forth opposite their names. (3) The contractor has not procured material from, or subcontracted with, any person other than those set forth and owes no money for the improvement other than the sums set forth. (4) I make this statement as the (contractor) (subcontractor) or as ____________________ of the (contractor) (subcontractor) to represent to the owner or lessee of the property and his or her agents that the property is free from claims of construction liens, or the possibility of construction liens, except as specifically set forth in this statement except for claims of construction liens by laborers that may be provided under Section 109 of the Construction Lien Act, 1980 PA 497, MCL 570.1109.
D8: ) ss.
B9: County of: | C9: =+Master!C9 -> Kent | D9: )
B11: =IF(G4=0,"",G4) -> Jeff Klaasen | D11: (deponent), being sworn, states the following:
A12: (1) | B12: =+G3 -> Wolven Investments LLC | D12: is the (contractor) (subcontractor) for an improvement to the following real
B13: property in | C13: =+C9 -> Kent | D13: County, Michigan described as follows:
B16: Name of Subcontractor, Supplier or Laborer | D16: Address of Subcontractor, Supplier or Laborer | E16: Telephone # | F16: Type of Improvement Furnished | G16: Total Contract Price | H16: Adjustment to Contract Amount ( +/ -) | I16: Adjusted Contract Price | J16: Amount Already Paid | K16: Current Request | L16: Balance to Complete
A17: 1 | B17: =IF(Master!$B17=0,"",Master!$B17) -> Jack Dykstra Excavating | D17: =IF(Master!$D17=0,"",Master!$D17) -> 3677 3 Mile Rd., Grand Rapids, MI 49534 | E17: =IF(Master!$E17=0,"",Master!$E17) -> 616-453-4827 | F17: =IF(Master!$F17=0,"",Master!$F17) -> GC Contract Amount | G17: =Master!G17 -> 623097.95 | H17: ='Draw 8'!H17 -> 18535.25 | I17: =+G17+H17 -> 641633.2 | J17: ='Draw 8'!J17+'Draw 8'!K17 -> 641633.2 | L17: =+I17-J17-K17 -> 0
A18: 2 | B18: =IF(Master!$B18=0,"",Master!$B18) | D18: =IF(Master!$D18=0,"",Master!$D18) | E18: =IF(Master!$E18=0,"",Master!$E18) | F18: =IF(Master!$F18=0,"",Master!$F18) | G18: =Master!G18 -> 0 | H18: ='Draw 8'!H18 -> 0 | I18: =+G18+H18 -> 0 | J18: ='Draw 8'!J18+'Draw 8'!K18 -> 0 | L18: =+I18-J18-K18 -> 0
A19: 3 | B19: =IF(Master!$B19=0,"",Master!$B19) -> Roosien & Associaties | D19: =IF(Master!$D19=0,"",Master!$D19) -> 5055 Plainfield Ave., Grand Rapids, MI 49525 | E19: =IF(Master!$E19=0,"",Master!$E19) -> 616-361-7220 | F19: =IF(Master!$F19=0,"",Master!$F19) -> Engineering Services | G19: =Master!G19 -> 62376 | H19: ='Draw 8'!H19 -> 15150 | I19: =+G19+H19 -> 77526 | J19: ='Draw 8'!J19+'Draw 8'!K19 -> 77526 | L19: =+I19-J19-K19 -> 0
A20: 4 | B20: =IF(Master!$B20=0,"",Master!$B20) -> Soils and Structures | D20: =IF(Master!$D20=0,"",Master!$D20) -> 6480 Grand Haven Rd Muskegon MI 49441 | E20: =IF(Master!$E20=0,"",Master!$E20) -> 1-800-933-3959 | F20: =IF(Master!$F20=0,"",Master!$F20) -> Engineering Services | G20: =Master!G20 -> 15930 | H20: ='Draw 8'!H20 -> 0 | I20: =+G20+H20 -> 15930 | J20: ='Draw 8'!J20+'Draw 8'!K20 -> 2535.5 | L20: =+I20-J20-K20 -> 13394.5
A21: 5 | B21: =IF(Master!$B21=0,"",Master!$B21) | D21: =IF(Master!$D21=0,"",Master!$D21) | E21: =IF(Master!$E21=0,"",Master!$E21) | F21: =IF(Master!$F21=0,"",Master!$F21) -> Engineering Services | G21: =Master!G21 -> 21742.22 | H21: ='Draw 8'!H21 -> -15150 | I21: =+G21+H21 -> 6592.22 | J21: ='Draw 8'!J21+'Draw 8'!K21 -> 0 | L21: =+I21-J21-K21 -> 6592.22
A22: 6 | B22: =IF(Master!$B22=0,"",Master!$B22) | D22: =IF(Master!$D22=0,"",Master!$D22) | E22: =IF(Master!$E22=0,"",Master!$E22) | F22: =IF(Master!$F22=0,"",Master!$F22) | G22: =Master!G22 -> 0 | H22: ='Draw 8'!H22 -> 0 | I22: =+G22+H22 -> 0 | J22: ='Draw 8'!J22+'Draw 8'!K22 -> 0 | L22: =+I22-J22-K22 -> 0
A23: 7 | B23: =IF(Master!$B23=0,"",Master!$B23) -> Handicap Sign | D23: =IF(Master!$D23=0,"",Master!$D23) -> 1142 Wealthy St., Grand Rapids, MI 49506 | E23: =IF(Master!$E23=0,"",Master!$E23) -> 616-454-9416 | F23: =IF(Master!$F23=0,"",Master!$F23) -> Common Area Improvements | G23: =Master!G23 -> 424.4 | H23: ='Draw 8'!H23 -> 0 | I23: =+G23+H23 -> 424.4 | J23: ='Draw 8'!J23+'Draw 8'!K23 -> 424.4 | L23: =+I23-J23-K23 -> 0
A24: 8 | B24: =IF(Master!$B24=0,"",Master!$B24) -> Rosendall Well Drilling | D24: =IF(Master!$D24=0,"",Master!$D24) -> 4181 Knapp, Grand Rapids, MI 49525 | E24: =IF(Master!$E24=0,"",Master!$E24) -> 616-363-2683 | F24: =IF(Master!$F24=0,"",Master!$F24) -> Common Area Improvements | G24: =Master!G24 -> 47734 | H24: ='Draw 8'!H24 -> 0 | I24: =+G24+H24 -> 47734 | J24: ='Draw 8'!J24+'Draw 8'!K24 -> 47734 | L24: =+I24-J24-K24 -> 0
A25: 9 | B25: =IF(Master!$B25=0,"",Master!$B25) | D25: =IF(Master!$D25=0,"",Master!$D25) | E25: =IF(Master!$E25=0,"",Master!$E25) | F25: =IF(Master!$F25=0,"",Master!$F25) -> Common Area Improvements | G25: =Master!G25 -> 8214.6 | H25: ='Draw 8'!H25 -> 0 | I25: =+G25+H25 -> 8214.6 | J25: ='Draw 8'!J25+'Draw 8'!K25 -> 0 | L25: =+I25-J25-K25 -> 8214.6
A26: 10 | B26: =IF(Master!$B26=0,"",Master!$B26) | D26: =IF(Master!$D26=0,"",Master!$D26) | E26: =IF(Master!$E26=0,"",Master!$E26) | F26: =IF(Master!$F26=0,"",Master!$F26) | G26: =Master!G26 -> 0 | H26: ='Draw 8'!H26 -> 0 | I26: =+G26+H26 -> 0 | J26: ='Draw 8'!J26+'Draw 8'!K26 -> 0 | L26: =+I26-J26-K26 -> 0
A27: 11 | B27: =IF(Master!$B27=0,"",Master!$B27) | D27: =IF(Master!$D27=0,"",Master!$D27) | E27: =IF(Master!$E27=0,"",Master!$E27) | F27: =IF(Master!$F27=0,"",Master!$F27) | G27: =Master!G27 -> 0 | H27: ='Draw 8'!H27 -> 0 | I27: =+G27+H27 -> 0 | J27: ='Draw 8'!J27+'Draw 8'!K27 -> 0 | L27: =+I27-J27-K27 -> 0
A28: 12 | B28: =IF(Master!$B28=0,"",Master!$B28) | D28: =IF(Master!$D28=0,"",Master!$D28) | E28: =IF(Master!$E28=0,"",Master!$E28) | F28: =IF(Master!$F28=0,"",Master!$F28) | G28: =Master!G28 -> 0 | H28: ='Draw 8'!H28 -> 0 | I28: =+G28+H28 -> 0 | J28: ='Draw 8'!J28+'Draw 8'!K28 -> 0 | L28: =+I28-J28-K28 -> 0
... A46: 30 | B46: =IF(Master!$B46=0,"",Master!$B46) | D46: =IF(Master!$D46=0,"",Master!$D46) | E46: =IF(Master!$E46=0,"",Master!$E46) | F46: =IF(Master!$F46=0,"",Master!$F46) -> Land | G46: =Master!G46 -> 234300 | H46: ='Draw 8'!H46 -> 0 | I46: =+G46+H46 -> 234300 | J46: ='Draw 8'!J46+'Draw 8'!K46 -> 234300 | L46: =+I46-J46-K46 -> 0
F47: SUBTOTALS | G47: =SUM(G17:G46) -> 1268365.7 | H47: =SUM(H17:H46) -> 0 | I47: =SUM(I17:I46) -> 1268365.7 | J47: =SUM(J17:J46) -> 1134587.9 | K47: =SUM(K17:K46) -> 0 | L47: =SUM(L17:L46) -> 133777.78
B48: WARNING TO OWNER OR LESSEE: An owner or lessee of the property may not rely on this sworn statement to avoid the claim of a subcontractor, supplier, or laborer who has provided a Notice of Furnishing or a laborer who may provide a Notice of Furnishing under Section 109 of the Construction Lien Act, 1980 PA 497, MCL 570.1109, to the designee or to the owner or lessee if the designee is not named or has died.
B52: Name of Subcontractor, Supplier or Laborer | D52: Address of Subcontractor, Supplier or Laborer | E52: Telephone # | F52: Type of Improvement Furnished | G52: Total Contract Price | H52: Adjustment to Contract Amount ( +/ -) | I52: Adjusted Contract Price | J52: Amount Already Paid | K52: Current Request | L52: Balance to Complete
A53: 31 | B53: =IF(Master!$B53=0,"",Master!$B53) | D53: =IF(Master!$D53=0,"",Master!$D53) | E53: =IF(Master!$E53=0,"",Master!$E53) | F53: =IF(Master!$F53=0,"",Master!$F53) | G53: =Master!G53 -> 0 | H53: ='Draw 8'!H53 -> 0 | I53: =+G53+H53 -> 0 | J53: ='Draw 8'!J53+'Draw 8'!K53 -> 0 | L53: =+I53-J53-K53 -> 0
A54: 32 | B54: =IF(Master!$B54=0,"",Master!$B54) | D54: =IF(Master!$D54=0,"",Master!$D54) | E54: =IF(Master!$E54=0,"",Master!$E54) | F54: =IF(Master!$F54=0,"",Master!$F54) | G54: =Master!G54 -> 0 | H54: ='Draw 8'!H54 -> 0 | I54: =+G54+H54 -> 0 | J54: ='Draw 8'!J54+'Draw 8'!K54 -> 0 | L54: =+I54-J54-K54 -> 0
A55: 33 | B55: =IF(Master!$B55=0,"",Master!$B55) | D55: =IF(Master!$D55=0,"",Master!$D55) | E55: =IF(Master!$E55=0,"",Master!$E55) | F55: =IF(Master!$F55=0,"",Master!$F55) | G55: =Master!G55 -> 0 | H55: ='Draw 8'!H55 -> 0 | I55: =+G55+H55 -> 0 | J55: ='Draw 8'!J55+'Draw 8'!K55 -> 0 | L55: =+I55-J55-K55 -> 0
A56: 34 | B56: =IF(Master!$B56=0,"",Master!$B56) | D56: =IF(Master!$D56=0,"",Master!$D56) | E56: =IF(Master!$E56=0,"",Master!$E56) | F56: =IF(Master!$F56=0,"",Master!$F56) | G56: =Master!G56 -> 0 | H56: ='Draw 8'!H56 -> 0 | I56: =+G56+H56 -> 0 | J56: ='Draw 8'!J56+'Draw 8'!K56 -> 0 | L56: =+I56-J56-K56 -> 0
A57: 35 | B57: =IF(Master!$B57=0,"",Master!$B57) | D57: =IF(Master!$D57=0,"",Master!$D57) | E57: =IF(Master!$E57=0,"",Master!$E57) | F57: =IF(Master!$F57=0,"",Master!$F57) | G57: =Master!G57 -> 0 | H57: ='Draw 8'!H57 -> 0 | I57: =+G57+H57 -> 0 | J57: ='Draw 8'!J57+'Draw 8'!K57 -> 0 | L57: =+I57-J57-K57 -> 0
A58: 36 | B58: =IF(Master!$B58=0,"",Master!$B58) | D58: =IF(Master!$D58=0,"",Master!$D58) | E58: =IF(Master!$E58=0,"",Master!$E58) | F58: =IF(Master!$F58=0,"",Master!$F58) | G58: =Master!G58 -> 0 | H58: ='Draw 8'!H58 -> 0 | I58: =+G58+H58 -> 0 | J58: ='Draw 8'!J58+'Draw 8'!K58 -> 0 | L58: =+I58-J58-K58 -> 0
A59: 37 | B59: =IF(Master!$B59=0,"",Master!$B59) | D59: =IF(Master!$D59=0,"",Master!$D59) | E59: =IF(Master!$E59=0,"",Master!$E59) | F59: =IF(Master!$F59=0,"",Master!$F59) | G59: =Master!G59 -> 0 | H59: ='Draw 8'!H59 -> 0 | I59: =+G59+H59 -> 0 | J59: ='Draw 8'!J59+'Draw 8'!K59 -> 0 | L59: =+I59-J59-K59 -> 0
A60: 38 | B60: =IF(Master!$B60=0,"",Master!$B60) | D60: =IF(Master!$D60=0,"",Master!$D60) | E60: =IF(Master!$E60=0,"",Master!$E60) | F60: =IF(Master!$F60=0,"",Master!$F60) | G60: =Master!G60 -> 0 | H60: ='Draw 8'!H60 -> 0 | I60: =+G60+H60 -> 0 | J60: ='Draw 8'!J60+'Draw 8'!K60 -> 0 | L60: =+I60-J60-K60 -> 0
A61: 39 | B61: =IF(Master!$B61=0,"",Master!$B61) | D61: =IF(Master!$D61=0,"",Master!$D61) | E61: =IF(Master!$E61=0,"",Master!$E61) | F61: =IF(Master!$F61=0,"",Master!$F61) | G61: =Master!G61 -> 0 | H61: ='Draw 8'!H61 -> 0 | I61: =+G61+H61 -> 0 | J61: ='Draw 8'!J61+'Draw 8'!K61 -> 0 | L61: =+I61-J61-K61 -> 0
A62: 40 | B62: =IF(Master!$B62=0,"",Master!$B62) | D62: =IF(Master!$D62=0,"",Master!$D62) | E62: =IF(Master!$E62=0,"",Master!$E62) | F62: =IF(Master!$F62=0,"",Master!$F62) | G62: =Master!G62 -> 0 | H62: ='Draw 8'!H62 -> 0 | I62: =+G62+H62 -> 0 | J62: ='Draw 8'!J62+'Draw 8'!K62 -> 0 | L62: =+I62-J62-K62 -> 0
A63: 41 | B63: =IF(Master!$B63=0,"",Master!$B63) | D63: =IF(Master!$D63=0,"",Master!$D63) | E63: =IF(Master!$E63=0,"",Master!$E63) | F63: =IF(Master!$F63=0,"",Master!$F63) | G63: =Master!G63 -> 0 | H63: ='Draw 8'!H63 -> 0 | I63: =+G63+H63 -> 0 | J63: ='Draw 8'!J63+'Draw 8'!K63 -> 0 | L63: =+I63-J63-K63 -> 0
A64: 42 | B64: =IF(Master!$B64=0,"",Master!$B64) | D64: =IF(Master!$D64=0,"",Master!$D64) | E64: =IF(Master!$E64=0,"",Master!$E64) | F64: =IF(Master!$F64=0,"",Master!$F64) | G64: =Master!G64 -> 0 | H64: ='Draw 8'!H64 -> 0 | I64: =+G64+H64 -> 0 | J64: ='Draw 8'!J64+'Draw 8'!K64 -> 0 | L64: =+I64-J64-K64 -> 0
... A82: 60 | B82: =IF(Master!$B82=0,"",Master!$B82) | D82: =IF(Master!$D82=0,"",Master!$D82) | E82: =IF(Master!$E82=0,"",Master!$E82) | F82: =IF(Master!$F82=0,"",Master!$F82) | G82: =Master!G82 -> 0 | H82: ='Draw 8'!H82 -> 0 | I82: =+G82+H82 -> 0 | J82: ='Draw 8'!J82+'Draw 8'!K82 -> 0 | L82: =+I82-J82-K82 -> 0
F83: Total | G83: =SUM(G53:G82)+G47 -> 1268365.7 | H83: =SUM(H53:H82)+H47 -> 0 | I83: =SUM(I53:I82)+I47 -> 1268365.7 | J83: =SUM(J53:J82)+J47 -> 1134587.9 | K83: =SUM(K53:K82)+K47 -> 0 | L83: =SUM(L53:L82)+L47 -> 133777.78
B84: If this sworn statement is in regard to a residential structure (defined as "an individual residential condominium unit or a residential building containing not more than 2 residential units,
B85: the land on which it is or will be located, and all appurtenances, in which the owner or lessee contracting for the improvement is residing or will reside upon completion of the improvement"), on
B86: receipt of this sworn statement, the owner or lessee, or the owner's or lessee's designee must give notice of its receipt, either in writing, or by telephone, or personally, to each subcontractor,
B87: supplier, and laborer who has provided a Notice of Furnishing under Section 109 or, if a Notice of Furnishing is excused under Section 108 or 108A, to each subcontractor, supplier, and
B88: laborer named in the sworn statement. If a subcontractor, supplier, or laborer who has provided a Notice of Furnishing or who is named in the sworn statement makes a request, the
B89: owner, lessee, or designee shall provide the requester a copy of the sworn statement within 10 business days after receiving the request.
D92: ='Example of Residential SS'!D92
D93: (DEPONENT) | F93: DATE
B95: WARNING TO DEPONENT: A person gives a false sworn statement with intent to defraud is
B96: subject to criminal penalties as provided in Section 110 of the Construction Lien Act, 1980 PA 497, MCL570.1110.
C99: Subscribed and sworn to before me on | E99: (date) by
C101: Notary Public | E101: County, Michigan
C103: My Commission expires: | L103: =IF('Example of Residential SS'!L103=0,"",'Example of Residential SS'!L103)

Sheet Draw 10
A1: OWNER'S SWORN STATEMENT - Draw #10
K2: Title Company File #
B3: Owner: | C3: =+Master!C3 -> Wolven Investments LLC | F3: General Contractor Name: | G3: =+Master!G3 -> Wolven Investments LLC | K3: Phone # | L3: =+Master!L3 -> 0
B4: Address of | F4: Person Submitting: | G4: =+Master!G4 -> Jeff Klaasen | K4: Email address | L4: =+Master!L4 -> 0
B5: Improvements: | C5: =+Master!C5 -> 43 North Phase 2 | G5: (authorized person signing sworn statement) | K5: Cell phone # | L5: =+Master!L5 -> 0
B7: State of Michigan | D7: ) | G7: (2) The following is a statement of each subcontractor and supplier, and laborer for whom payment of wages or fringe benefits and withholdings is due but unpaid, with whom the (contractor) (subcontractor) has (contracted) (subcontracted) for performance under the contract with the owner or lessee of the property, and the amounts due to the persons as of the date of this statement are correctly and fully set forth opposite their names. (3) The contractor has not procured material from, or subcontracted with, any person other than those set forth and owes no money for the improvement other than the sums set forth. (4) I make this statement as the (contractor) (subcontractor) or as ____________________ of the (contractor) (subcontractor) to represent to the owner or lessee of the property and his or her agents that the property is free from claims of construction liens, or the possibility of construction liens, except as specifically set forth in this statement except for claims of construction liens by laborers that may be provided under Section 109 of the Construction Lien Act, 1980 PA 497, MCL 570.1109.
D8: ) ss.
B9: County of: | C9: =+Master!C9 -> Kent | D9: )
B11: =IF(G4=0,"",G4) -> Jeff Klaasen | D11: (deponent), being sworn, states the following:
A12: (1) | B12: =+G3 -> Wolven Investments LLC | D12: is the (contractor) (subcontractor) for an improvement to the following real
B13: property in | C13: =+C9 -> Kent | D13: County, Michigan described as follows:
B16: Name of Subcontractor, Supplier or Laborer | D16: Address of Subcontractor, Supplier or Laborer | E16: Telephone # | F16: Type of Improvement Furnished | G16: Total Contract Price | H16: Adjustment to Contract Amount ( +/ -) | I16: Adjusted Contract Price | J16: Amount Already Paid | K16: Current Request | L16: Balance to Complete
A17: 1 | B17: =IF(Master!$B17=0,"",Master!$B17) -> Jack Dykstra Excavating | D17: =IF(Master!$D17=0,"",Master!$D17) -> 3677 3 Mile Rd., Grand Rapids, MI 49534 | E17: =IF(Master!$E17=0,"",Master!$E17) -> 616-453-4827 | F17: =IF(Master!$F17=0,"",Master!$F17) -> GC Contract Amount | G17: =Master!G17 -> 623097.95 | H17: ='Draw 9'!H17 -> 18535.25 | I17: =+G17+H17 -> 641633.2 | J17: ='Draw 9'!J17+'Draw 9'!K17 -> 641633.2 | L17: =+I17-J17-K17 -> 0
A18: 2 | B18: =IF(Master!$B18=0,"",Master!$B18) | D18: =IF(Master!$D18=0,"",Master!$D18) | E18: =IF(Master!$E18=0,"",Master!$E18) | F18: =IF(Master!$F18=0,"",Master!$F18) | G18: =Master!G18 -> 0 | H18: ='Draw 9'!H18 -> 0 | I18: =+G18+H18 -> 0 | J18: ='Draw 9'!J18+'Draw 9'!K18 -> 0 | L18: =+I18-J18-K18 -> 0
A19: 3 | B19: =IF(Master!$B19=0,"",Master!$B19) -> Roosien & Associaties | D19: =IF(Master!$D19=0,"",Master!$D19) -> 5055 Plainfield Ave., Grand Rapids, MI 49525 | E19: =IF(Master!$E19=0,"",Master!$E19) -> 616-361-7220 | F19: =IF(Master!$F19=0,"",Master!$F19) -> Engineering Services | G19: =Master!G19 -> 62376 | H19: ='Draw 9'!H19 -> 15150 | I19: =+G19+H19 -> 77526 | J19: ='Draw 9'!J19+'Draw 9'!K19 -> 77526 | L19: =+I19-J19-K19 -> 0
A20: 4 | B20: =IF(Master!$B20=0,"",Master!$B20) -> Soils and Structures | D20: =IF(Master!$D20=0,"",Master!$D20) -> 6480 Grand Haven Rd Muskegon MI 49441 | E20: =IF(Master!$E20=0,"",Master!$E20) -> 1-800-933-3959 | F20: =IF(Master!$F20=0,"",Master!$F20) -> Engineering Services | G20: =Master!G20 -> 15930 | H20: ='Draw 9'!H20 -> 0 | I20: =+G20+H20 -> 15930 | J20: ='Draw 9'!J20+'Draw 9'!K20 -> 2535.5 | L20: =+I20-J20-K20 -> 13394.5
A21: 5 | B21: =IF(Master!$B21=0,"",Master!$B21) | D21: =IF(Master!$D21=0,"",Master!$D21) | E21: =IF(Master!$E21=0,"",Master!$E21) | F21: =IF(Master!$F21=0,"",Master!$F21) -> Engineering Services | G21: =Master!G21 -> 21742.22 | H21: ='Draw 9'!H21 -> -15150 | I21: =+G21+H21 -> 6592.22 | J21: ='Draw 9'!J21+'Draw 9'!K21 -> 0 | L21: =+I21-J21-K21 -> 6592.22
A22: 6 | B22: =IF(Master!$B22=0,"",Master!$B22) | D22: =IF(Master!$D22=0,"",Master!$D22) | E22: =IF(Master!$E22=0,"",Master!$E22) | F22: =IF(Master!$F22=0,"",Master!$F22) | G22: =Master!G22 -> 0 | H22: ='Draw 9'!H22 -> 0 | I22: =+G22+H22 -> 0 | J22: ='Draw 9'!J22+'Draw 9'!K22 -> 0 | L22: =+I22-J22-K22 -> 0
A23: 7 | B23: =IF(Master!$B23=0,"",Master!$B23) -> Handicap Sign | D23: =IF(Master!$D23=0,"",Master!$D23) -> 1142 Wealthy St., Grand Rapids, MI 49506 | E23: =IF(Master!$E23=0,"",Master!$E23) -> 616-454-9416 | F23: =IF(Master!$F23=0,"",Master!$F23) -> Common Area Improvements | G23: =Master!G23 -> 424.4 | H23: ='Draw 9'!H23 -> 0 | I23: =+G23+H23 -> 424.4 | J23: ='Draw 9'!J23+'Draw 9'!K23 -> 424.4 | L23: =+I23-J23-K23 -> 0
A24: 8 | B24: =IF(Master!$B24=0,"",Master!$B24) -> Rosendall Well Drilling | D24: =IF(Master!$D24=0,"",Master!$D24) -> 4181 Knapp, Grand Rapids, MI 49525 | E24: =IF(Master!$E24=0,"",Master!$E24) -> 616-363-2683 | F24: =IF(Master!$F24=0,"",Master!$F24) -> Common Area Improvements | G24: =Master!G24 -> 47734 | H24: ='Draw 9'!H24 -> 0 | I24: =+G24+H24 -> 47734 | J24: ='Draw 9'!J24+'Draw 9'!K24 -> 47734 | L24: =+I24-J24-K24 -> 0
A25: 9 | B25: =IF(Master!$B25=0,"",Master!$B25) | D25: =IF(Master!$D25=0,"",Master!$D25) | E25: =IF(Master!$E25=0,"",Master!$E25) | F25: =IF(Master!$F25=0,"",Master!$F25) -> Common Area Improvements | G25: =Master!G25 -> 8214.6 | H25: ='Draw 9'!H25 -> 0 | I25: =+G25+H25 -> 8214.6 | J25: ='Draw 9'!J25+'Draw 9'!K25 -> 0 | L25: =+I25-J25-K25 -> 8214.6
A26: 10 | B26: =IF(Master!$B26=0,"",Master!$B26) | D26: =IF(Master!$D26=0,"",Master!$D26) | E26: =IF(Master!$E26=0,"",Master!$E26) | F26: =IF(Master!$F26=0,"",Master!$F26) | G26: =Master!G26 -> 0 | H26: ='Draw 9'!H26 -> 0 | I26: =+G26+H26 -> 0 | J26: ='Draw 9'!J26+'Draw 9'!K26 -> 0 | L26: =+I26-J26-K26 -> 0
A27: 11 | B27: =IF(Master!$B27=0,"",Master!$B27) | D27: =IF(Master!$D27=0,"",Master!$D27) | E27: =IF(Master!$E27=0,"",Master!$E27) | F27: =IF(Master!$F27=0,"",Master!$F27) | G27: =Master!G27 -> 0 | H27: ='Draw 9'!H27 -> 0 | I27: =+G27+H27 -> 0 | J27: ='Draw 9'!J27+'Draw 9'!K27 -> 0 | L27: =+I27-J27-K27 -> 0
A28: 12 | B28: =IF(Master!$B28=0,"",Master!$B28) | D28: =IF(Master!$D28=0,"",Master!$D28) | E28: =IF(Master!$E28=0,"",Master!$E28) | F28: =IF(Master!$F28=0,"",Master!$F28) | G28: =Master!G28 -> 0 | H28: ='Draw 9'!H28 -> 0 | I28: =+G28+H28 -> 0 | J28: ='Draw 9'!J28+'Draw 9'!K28 -> 0 | L28: =+I28-J28-K28 -> 0
... A46: 30 | B46: =IF(Master!$B46=0,"",Master!$B46) | D46: =IF(Master!$D46=0,"",Master!$D46) | E46: =IF(Master!$E46=0,"",Master!$E46) | F46: =IF(Master!$F46=0,"",Master!$F46) -> Land | G46: =Master!G46 -> 234300 | H46: ='Draw 9'!H46 -> 0 | I46: =+G46+H46 -> 234300 | J46: ='Draw 9'!J46+'Draw 9'!K46 -> 234300 | L46: =+I46-J46-K46 -> 0
F47: SUBTOTALS | G47: =SUM(G17:G46) -> 1268365.7 | H47: =SUM(H17:H46) -> 0 | I47: =SUM(I17:I46) -> 1268365.7 | J47: =SUM(J17:J46) -> 1134587.9 | K47: =SUM(K17:K46) -> 0 | L47: =SUM(L17:L46) -> 133777.78
B48: WARNING TO OWNER OR LESSEE: An owner or lessee of the property may not rely on this sworn statement to avoid the claim of a subcontractor, supplier, or laborer who has provided a Notice of Furnishing or a laborer who may provide a Notice of Furnishing under Section 109 of the Construction Lien Act, 1980 PA 497, MCL 570.1109, to the designee or to the owner or lessee if the designee is not named or has died.
B52: Name of Subcontractor, Supplier or Laborer | D52: Address of Subcontractor, Supplier or Laborer | E52: Telephone # | F52: Type of Improvement Furnished | G52: Total Contract Price | H52: Adjustment to Contract Amount ( +/ -) | I52: Adjusted Contract Price | J52: Amount Already Paid | K52: Current Request | L52: Balance to Complete
A53: 31 | B53: =IF(Master!$B53=0,"",Master!$B53) | D53: =IF(Master!$D53=0,"",Master!$D53) | E53: =IF(Master!$E53=0,"",Master!$E53) | F53: =IF(Master!$F53=0,"",Master!$F53) | G53: =Master!G53 -> 0 | H53: ='Draw 9'!H53 -> 0 | I53: =+G53+H53 -> 0 | J53: ='Draw 9'!J53+'Draw 9'!K53 -> 0 | L53: =+I53-J53-K53 -> 0
A54: 32 | B54: =IF(Master!$B54=0,"",Master!$B54) | D54: =IF(Master!$D54=0,"",Master!$D54) | E54: =IF(Master!$E54=0,"",Master!$E54) | F54: =IF(Master!$F54=0,"",Master!$F54) | G54: =Master!G54 -> 0 | H54: ='Draw 9'!H54 -> 0 | I54: =+G54+H54 -> 0 | J54: ='Draw 9'!J54+'Draw 9'!K54 -> 0 | L54: =+I54-J54-K54 -> 0
A55: 33 | B55: =IF(Master!$B55=0,"",Master!$B55) | D55: =IF(Master!$D55=0,"",Master!$D55) | E55: =IF(Master!$E55=0,"",Master!$E55) | F55: =IF(Master!$F55=0,"",Master!$F55) | G55: =Master!G55 -> 0 | H55: ='Draw 9'!H55 -> 0 | I55: =+G55+H55 -> 0 | J55: ='Draw 9'!J55+'Draw 9'!K55 -> 0 | L55: =+I55-J55-K55 -> 0
A56: 34 | B56: =IF(Master!$B56=0,"",Master!$B56) | D56: =IF(Master!$D56=0,"",Master!$D56) | E56: =IF(Master!$E56=0,"",Master!$E56) | F56: =IF(Master!$F56=0,"",Master!$F56) | G56: =Master!G56 -> 0 | H56: ='Draw 9'!H56 -> 0 | I56: =+G56+H56 -> 0 | J56: ='Draw 9'!J56+'Draw 9'!K56 -> 0 | L56: =+I56-J56-K56 -> 0
A57: 35 | B57: =IF(Master!$B57=0,"",Master!$B57) | D57: =IF(Master!$D57=0,"",Master!$D57) | E57: =IF(Master!$E57=0,"",Master!$E57) | F57: =IF(Master!$F57=0,"",Master!$F57) | G57: =Master!G57 -> 0 | H57: ='Draw 9'!H57 -> 0 | I57: =+G57+H57 -> 0 | J57: ='Draw 9'!J57+'Draw 9'!K57 -> 0 | L57: =+I57-J57-K57 -> 0
A58: 36 | B58: =IF(Master!$B58=0,"",Master!$B58) | D58: =IF(Master!$D58=0,"",Master!$D58) | E58: =IF(Master!$E58=0,"",Master!$E58) | F58: =IF(Master!$F58=0,"",Master!$F58) | G58: =Master!G58 -> 0 | H58: ='Draw 9'!H58 -> 0 | I58: =+G58+H58 -> 0 | J58: ='Draw 9'!J58+'Draw 9'!K58 -> 0 | L58: =+I58-J58-K58 -> 0
A59: 37 | B59: =IF(Master!$B59=0,"",Master!$B59) | D59: =IF(Master!$D59=0,"",Master!$D59) | E59: =IF(Master!$E59=0,"",Master!$E59) | F59: =IF(Master!$F59=0,"",Master!$F59) | G59: =Master!G59 -> 0 | H59: ='Draw 9'!H59 -> 0 | I59: =+G59+H59 -> 0 | J59: ='Draw 9'!J59+'Draw 9'!K59 -> 0 | L59: =+I59-J59-K59 -> 0
A60: 38 | B60: =IF(Master!$B60=0,"",Master!$B60) | D60: =IF(Master!$D60=0,"",Master!$D60) | E60: =IF(Master!$E60=0,"",Master!$E60) | F60: =IF(Master!$F60=0,"",Master!$F60) | G60: =Master!G60 -> 0 | H60: ='Draw 9'!H60 -> 0 | I60: =+G60+H60 -> 0 | J60: ='Draw 9'!J60+'Draw 9'!K60 -> 0 | L60: =+I60-J60-K60 -> 0
A61: 39 | B61: =IF(Master!$B61=0,"",Master!$B61) | D61: =IF(Master!$D61=0,"",Master!$D61) | E61: =IF(Master!$E61=0,"",Master!$E61) | F61: =IF(Master!$F61=0,"",Master!$F61) | G61: =Master!G61 -> 0 | H61: ='Draw 9'!H61 -> 0 | I61: =+G61+H61 -> 0 | J61: ='Draw 9'!J61+'Draw 9'!K61 -> 0 | L61: =+I61-J61-K61 -> 0
A62: 40 | B62: =IF(Master!$B62=0,"",Master!$B62) | D62: =IF(Master!$D62=0,"",Master!$D62) | E62: =IF(Master!$E62=0,"",Master!$E62) | F62: =IF(Master!$F62=0,"",Master!$F62) | G62: =Master!G62 -> 0 | H62: ='Draw 9'!H62 -> 0 | I62: =+G62+H62 -> 0 | J62: ='Draw 9'!J62+'Draw 9'!K62 -> 0 | L62: =+I62-J62-K62 -> 0
A63: 41 | B63: =IF(Master!$B63=0,"",Master!$B63) | D63: =IF(Master!$D63=0,"",Master!$D63) | E63: =IF(Master!$E63=0,"",Master!$E63) | F63: =IF(Master!$F63=0,"",Master!$F63) | G63: =Master!G63 -> 0 | H63: ='Draw 9'!H63 -> 0 | I63: =+G63+H63 -> 0 | J63: ='Draw 9'!J63+'Draw 9'!K63 -> 0 | L63: =+I63-J63-K63 -> 0
A64: 42 | B64: =IF(Master!$B64=0,"",Master!$B64) | D64: =IF(Master!$D64=0,"",Master!$D64) | E64: =IF(Master!$E64=0,"",Master!$E64) | F64: =IF(Master!$F64=0,"",Master!$F64) | G64: =Master!G64 -> 0 | H64: ='Draw 9'!H64 -> 0 | I64: =+G64+H64 -> 0 | J64: ='Draw 9'!J64+'Draw 9'!K64 -> 0 | L64: =+I64-J64-K64 -> 0
... A82: 60 | B82: =IF(Master!$B82=0,"",Master!$B82) | D82: =IF(Master!$D82=0,"",Master!$D82) | E82: =IF(Master!$E82=0,"",Master!$E82) | F82: =IF(Master!$F82=0,"",Master!$F82) | G82: =Master!G82 -> 0 | H82: ='Draw 9'!H82 -> 0 | I82: =+G82+H82 -> 0 | J82: ='Draw 9'!J82+'Draw 9'!K82 -> 0 | L82: =+I82-J82-K82 -> 0
F83: Total | G83: =SUM(G53:G82)+G47 -> 1268365.7 | H83: =SUM(H53:H82)+H47 -> 0 | I83: =SUM(I53:I82)+I47 -> 1268365.7 | J83: =SUM(J53:J82)+J47 -> 1134587.9 | K83: =SUM(K53:K82)+K47 -> 0 | L83: =SUM(L53:L82)+L47 -> 133777.78
B84: If this sworn statement is in regard to a residential structure (defined as "an individual residential condominium unit or a residential building containing not more than 2 residential units,
B85: the land on which it is or will be located, and all appurtenances, in which the owner or lessee contracting for the improvement is residing or will reside upon completion of the improvement"), on
B86: receipt of this sworn statement, the owner or lessee, or the owner's or lessee's designee must give notice of its receipt, either in writing, or by telephone, or personally, to each subcontractor,
B87: supplier, and laborer who has provided a Notice of Furnishing under Section 109 or, if a Notice of Furnishing is excused under Section 108 or 108A, to each subcontractor, supplier, and
B88: laborer named in the sworn statement. If a subcontractor, supplier, or laborer who has provided a Notice of Furnishing or who is named in the sworn statement makes a request, the
B89: owner, lessee, or designee shall provide the requester a copy of the sworn statement within 10 business days after receiving the request.
D92: ='Example of Residential SS'!D92
D93: (DEPONENT) | F93: DATE
B95: WARNING TO DEPONENT: A person gives a false sworn statement with intent to defraud is
B96: subject to criminal penalties as provided in Section 110 of the Construction Lien Act, 1980 PA 497, MCL570.1110.
C99: Subscribed and sworn to before me on | E99: (date) by
C101: Notary Public | E101: County, Michigan
C103: My Commission expires: | L103: =IF('Example of Residential SS'!L103=0,"",'Example of Residential SS'!L103)

Sheet Draw 11
A1: OWNER'S SWORN STATEMENT - Draw #11
K2: Title Company File #
B3: Owner: | C3: =+Master!C3 -> Wolven Investments LLC | F3: General Contractor Name: | G3: =+Master!G3 -> Wolven Investments LLC | K3: Phone # | L3: =+Master!L3 -> 0
B4: Address of | F4: Person Submitting: | G4: =+Master!G4 -> Jeff Klaasen | K4: Email address | L4: =+Master!L4 -> 0
B5: Improvements: | C5: =+Master!C5 -> 43 North Phase 2 | G5: (authorized person signing sworn statement) | K5: Cell phone # | L5: =+Master!L5 -> 0
B7: State of Michigan | D7: ) | G7: (2) The following is a statement of each subcontractor and supplier, and laborer for whom payment of wages or fringe benefits and withholdings is due but unpaid, with whom the (contractor) (subcontractor) has (contracted) (subcontracted) for performance under the contract with the owner or lessee of the property, and the amounts due to the persons as of the date of this statement are correctly and fully set forth opposite their names. (3) The contractor has not procured material from, or subcontracted with, any person other than those set forth and owes no money for the improvement other than the sums set forth. (4) I make this statement as the (contractor) (subcontractor) or as ____________________ of the (contractor) (subcontractor) to represent to the owner or lessee of the property and his or her agents that the property is free from claims of construction liens, or the possibility of construction liens, except as specifically set forth in this statement except for claims of construction liens by laborers that may be provided under Section 109 of the Construction Lien Act, 1980 PA 497, MCL 570.1109.
D8: ) ss.
B9: County of: | C9: =+Master!C9 -> Kent | D9: )
B11: =IF(G4=0,"",G4) -> Jeff Klaasen | D11: (deponent), being sworn, states the following:
A12: (1) | B12: =+G3 -> Wolven Investments LLC | D12: is the (contractor) (subcontractor) for an improvement to the following real
B13: property in | C13: =+C9 -> Kent | D13: County, Michigan described as follows:
B16: Name of Subcontractor, Supplier or Laborer | D16: Address of Subcontractor, Supplier or Laborer | E16: Telephone # | F16: Type of Improvement Furnished | G16: Total Contract Price | H16: Adjustment to Contract Amount ( +/ -) | I16: Adjusted Contract Price | J16: Amount Already Paid | K16: Current Request | L16: Balance to Complete
A17: 1 | B17: =IF(Master!$B17=0,"",Master!$B17) -> Jack Dykstra Excavating | D17: =IF(Master!$D17=0,"",Master!$D17) -> 3677 3 Mile Rd., Grand Rapids, MI 49534 | E17: =IF(Master!$E17=0,"",Master!$E17) -> 616-453-4827 | F17: =IF(Master!$F17=0,"",Master!$F17) -> GC Contract Amount | G17: =Master!G17 -> 623097.95 | H17: ='Draw 10'!H17 -> 18535.25 | I17: =+G17+H17 -> 641633.2 | J17: ='Draw 10'!J17+'Draw 10'!K17 -> 641633.2 | L17: =+I17-J17-K17 -> 0
A18: 2 | B18: =IF(Master!$B18=0,"",Master!$B18) | D18: =IF(Master!$D18=0,"",Master!$D18) | E18: =IF(Master!$E18=0,"",Master!$E18) | F18: =IF(Master!$F18=0,"",Master!$F18) | G18: =Master!G18 -> 0 | H18: ='Draw 10'!H18 -> 0 | I18: =+G18+H18 -> 0 | J18: ='Draw 10'!J18+'Draw 10'!K18 -> 0 | L18: =+I18-J18-K18 -> 0
A19: 3 | B19: =IF(Master!$B19=0,"",Master!$B19) -> Roosien & Associaties | D19: =IF(Master!$D19=0,"",Master!$D19) -> 5055 Plainfield Ave., Grand Rapids, MI 49525 | E19: =IF(Master!$E19=0,"",Master!$E19) -> 616-361-7220 | F19: =IF(Master!$F19=0,"",Master!$F19) -> Engineering Services | G19: =Master!G19 -> 62376 | H19: ='Draw 10'!H19 -> 15150 | I19: =+G19+H19 -> 77526 | J19: ='Draw 10'!J19+'Draw 10'!K19 -> 77526 | L19: =+I19-J19-K19 -> 0
A20: 4 | B20: =IF(Master!$B20=0,"",Master!$B20) -> Soils and Structures | D20: =IF(Master!$D20=0,"",Master!$D20) -> 6480 Grand Haven Rd Muskegon MI 49441 | E20: =IF(Master!$E20=0,"",Master!$E20) -> 1-800-933-3959 | F20: =IF(Master!$F20=0,"",Master!$F20) -> Engineering Services | G20: =Master!G20 -> 15930 | H20: ='Draw 10'!H20 -> 0 | I20: =+G20+H20 -> 15930 | J20: ='Draw 10'!J20+'Draw 10'!K20 -> 2535.5 | L20: =+I20-J20-K20 -> 13394.5
A21: 5 | B21: =IF(Master!$B21=0,"",Master!$B21) | D21: =IF(Master!$D21=0,"",Master!$D21) | E21: =IF(Master!$E21=0,"",Master!$E21) | F21: =IF(Master!$F21=0,"",Master!$F21) -> Engineering Services | G21: =Master!G21 -> 21742.22 | H21: ='Draw 10'!H21 -> -15150 | I21: =+G21+H21 -> 6592.22 | J21: ='Draw 10'!J21+'Draw 10'!K21 -> 0 | L21: =+I21-J21-K21 -> 6592.22
A22: 6 | B22: =IF(Master!$B22=0,"",Master!$B22) | D22: =IF(Master!$D22=0,"",Master!$D22) | E22: =IF(Master!$E22=0,"",Master!$E22) | F22: =IF(Master!$F22=0,"",Master!$F22) | G22: =Master!G22 -> 0 | H22: ='Draw 10'!H22 -> 0 | I22: =+G22+H22 -> 0 | J22: ='Draw 10'!J22+'Draw 10'!K22 -> 0 | L22: =+I22-J22-K22 -> 0
A23: 7 | B23: =IF(Master!$B23=0,"",Master!$B23) -> Handicap Sign | D23: =IF(Master!$D23=0,"",Master!$D23) -> 1142 Wealthy St., Grand Rapids, MI 49506 | E23: =IF(Master!$E23=0,"",Master!$E23) -> 616-454-9416 | F23: =IF(Master!$F23=0,"",Master!$F23) -> Common Area Improvements | G23: =Master!G23 -> 424.4 | H23: ='Draw 10'!H23 -> 0 | I23: =+G23+H23 -> 424.4 | J23: ='Draw 10'!J23+'Draw 10'!K23 -> 424.4 | L23: =+I23-J23-K23 -> 0
A24: 8 | B24: =IF(Master!$B24=0,"",Master!$B24) -> Rosendall Well Drilling | D24: =IF(Master!$D24=0,"",Master!$D24) -> 4181 Knapp, Grand Rapids, MI 49525 | E24: =IF(Master!$E24=0,"",Master!$E24) -> 616-363-2683 | F24: =IF(Master!$F24=0,"",Master!$F24) -> Common Area Improvements | G24: =Master!G24 -> 47734 | H24: ='Draw 10'!H24 -> 0 | I24: =+G24+H24 -> 47734 | J24: ='Draw 10'!J24+'Draw 10'!K24 -> 47734 | L24: =+I24-J24-K24 -> 0
A25: 9 | B25: =IF(Master!$B25=0,"",Master!$B25) | D25: =IF(Master!$D25=0,"",Master!$D25) | E25: =IF(Master!$E25=0,"",Master!$E25) | F25: =IF(Master!$F25=0,"",Master!$F25) -> Common Area Improvements | G25: =Master!G25 -> 8214.6 | H25: ='Draw 10'!H25 -> 0 | I25: =+G25+H25 -> 8214.6 | J25: ='Draw 10'!J25+'Draw 10'!K25 -> 0 | L25: =+I25-J25-K25 -> 8214.6
A26: 10 | B26: =IF(Master!$B26=0,"",Master!$B26) | D26: =IF(Master!$D26=0,"",Master!$D26) | E26: =IF(Master!$E26=0,"",Master!$E26) | F26: =IF(Master!$F26=0,"",Master!$F26) | G26: =Master!G26 -> 0 | H26: ='Draw 10'!H26 -> 0 | I26: =+G26+H26 -> 0 | J26: ='Draw 10'!J26+'Draw 10'!K26 -> 0 | L26: =+I26-J26-K26 -> 0
A27: 11 | B27: =IF(Master!$B27=0,"",Master!$B27) | D27: =IF(Master!$D27=0,"",Master!$D27) | E27: =IF(Master!$E27=0,"",Master!$E27) | F27: =IF(Master!$F27=0,"",Master!$F27) | G27: =Master!G27 -> 0 | H27: ='Draw 10'!H27 -> 0 | I27: =+G27+H27 -> 0 | J27: ='Draw 10'!J27+'Draw 10'!K27 -> 0 | L27: =+I27-J27-K27 -> 0
A28: 12 | B28: =IF(Master!$B28=0,"",Master!$B28) | D28: =IF(Master!$D28=0,"",Master!$D28) | E28: =IF(Master!$E28=0,"",Master!$E28) | F28: =IF(Master!$F28=0,"",Master!$F28) | G28: =Master!G28 -> 0 | H28: ='Draw 10'!H28 -> 0 | I28: =+G28+H28 -> 0 | J28: ='Draw 10'!J28+'Draw 10'!K28 -> 0 | L28: =+I28-J28-K28 -> 0
... A46: 30 | B46: =IF(Master!$B46=0,"",Master!$B46) | D46: =IF(Master!$D46=0,"",Master!$D46) | E46: =IF(Master!$E46=0,"",Master!$E46) | F46: =IF(Master!$F46=0,"",Master!$F46) -> Land | G46: =Master!G46 -> 234300 | H46: ='Draw 10'!H46 -> 0 | I46: =+G46+H46 -> 234300 | J46: ='Draw 10'!J46+'Draw 10'!K46 -> 234300 | L46: =+I46-J46-K46 -> 0
F47: SUBTOTALS | G47: =SUM(G17:G46) -> 1268365.7 | H47: =SUM(H17:H46) -> 0 | I47: =SUM(I17:I46) -> 1268365.7 | J47: =SUM(J17:J46) -> 1134587.9 | K47: =SUM(K17:K46) -> 0 | L47: =SUM(L17:L46) -> 133777.78
B48: WARNING TO OWNER OR LESSEE: An owner or lessee of the property may not rely on this sworn statement to avoid the claim of a subcontractor, supplier, or laborer who has provided a Notice of Furnishing or a laborer who may provide a Notice of Furnishing under Section 109 of the Construction Lien Act, 1980 PA 497, MCL 570.1109, to the designee or to the owner or lessee if the designee is not named or has died.
B52: =IF(Master!$B52=0,"",Master!$B52) -> Name of Subcontractor, Supplier or Laborer | D52: =IF(Master!$D52=0,"",Master!$D52) -> Address of Subcontractor, Supplier or Laborer | E52: =IF(Master!$E52=0,"",Master!$E52) -> Telephone # | F52: =IF(Master!$F52=0,"",Master!$F52) -> Type of Improvement Furnished | G52: Total Contract Price | H52: Adjustment to Contract Amount ( +/ -) | I52: Adjusted Contract Price | J52: Amount Already Paid | K52: Current Request | L52: Balance to Complete
A53: 31 | B53: =IF(Master!$B53=0,"",Master!$B53) | D53: =IF(Master!$D53=0,"",Master!$D53) | E53: =IF(Master!$E53=0,"",Master!$E53) | F53: =IF(Master!$F53=0,"",Master!$F53) | G53: =Master!G53 -> 0 | H53: ='Draw 10'!H53 -> 0 | I53: =+G53+H53 -> 0 | J53: ='Draw 10'!J53+'Draw 10'!K53 -> 0 | L53: =+I53-J53-K53 -> 0
A54: 32 | B54: =IF(Master!$B54=0,"",Master!$B54) | D54: =IF(Master!$D54=0,"",Master!$D54) | E54: =IF(Master!$E54=0,"",Master!$E54) | F54: =IF(Master!$F54=0,"",Master!$F54) | G54: =Master!G54 -> 0 | H54: ='Draw 10'!H54 -> 0 | I54: =+G54+H54 -> 0 | J54: ='Draw 10'!J54+'Draw 10'!K54 -> 0 | L54: =+I54-J54-K54 -> 0
A55: 33 | B55: =IF(Master!$B55=0,"",Master!$B55) | D55: =IF(Master!$D55=0,"",Master!$D55) | E55: =IF(Master!$E55=0,"",Master!$E55) | F55: =IF(Master!$F55=0,"",Master!$F55) | G55: =Master!G55 -> 0 | H55: ='Draw 10'!H55 -> 0 | I55: =+G55+H55 -> 0 | J55: ='Draw 10'!J55+'Draw 10'!K55 -> 0 | L55: =+I55-J55-K55 -> 0
A56: 34 | B56: =IF(Master!$B56=0,"",Master!$B56) | D56: =IF(Master!$D56=0,"",Master!$D56) | E56: =IF(Master!$E56=0,"",Master!$E56) | F56: =IF(Master!$F56=0,"",Master!$F56) | G56: =Master!G56 -> 0 | H56: ='Draw 10'!H56 -> 0 | I56: =+G56+H56 -> 0 | J56: ='Draw 10'!J56+'Draw 10'!K56 -> 0 | L56: =+I56-J56-K56 -> 0
A57: 35 | B57: =IF(Master!$B57=0,"",Master!$B57) | D57: =IF(Master!$D57=0,"",Master!$D57) | E57: =IF(Master!$E57=0,"",Master!$E57) | F57: =IF(Master!$F57=0,"",Master!$F57) | G57: =Master!G57 -> 0 | H57: ='Draw 10'!H57 -> 0 | I57: =+G57+H57 -> 0 | J57: ='Draw 10'!J57+'Draw 10'!K57 -> 0 | L57: =+I57-J57-K57 -> 0
A58: 36 | B58: =IF(Master!$B58=0,"",Master!$B58) | D58: =IF(Master!$D58=0,"",Master!$D58) | E58: =IF(Master!$E58=0,"",Master!$E58) | F58: =IF(Master!$F58=0,"",Master!$F58) | G58: =Master!G58 -> 0 | H58: ='Draw 10'!H58 -> 0 | I58: =+G58+H58 -> 0 | J58: ='Draw 10'!J58+'Draw 10'!K58 -> 0 | L58: =+I58-J58-K58 -> 0
A59: 37 | B59: =IF(Master!$B59=0,"",Master!$B59) | D59: =IF(Master!$D59=0,"",Master!$D59) | E59: =IF(Master!$E59=0,"",Master!$E59) | F59: =IF(Master!$F59=0,"",Master!$F59) | G59: =Master!G59 -> 0 | H59: ='Draw 10'!H59 -> 0 | I59: =+G59+H59 -> 0 | J59: ='Draw 10'!J59+'Draw 10'!K59 -> 0 | L59: =+I59-J59-K59 -> 0
A60: 38 | B60: =IF(Master!$B60=0,"",Master!$B60) | D60: =IF(Master!$D60=0,"",Master!$D60) | E60: =IF(Master!$E60=0,"",Master!$E60) | F60: =IF(Master!$F60=0,"",Master!$F60) | G60: =Master!G60 -> 0 | H60: ='Draw 10'!H60 -> 0 | I60: =+G60+H60 -> 0 | J60: ='Draw 10'!J60+'Draw 10'!K60 -> 0 | L60: =+I60-J60-K60 -> 0
A61: 39 | B61: =IF(Master!$B61=0,"",Master!$B61) | D61: =IF(Master!$D61=0,"",Master!$D61) | E61: =IF(Master!$E61=0,"",Master!$E61) | F61: =IF(Master!$F61=0,"",Master!$F61) | G61: =Master!G61 -> 0 | H61: ='Draw 10'!H61 -> 0 | I61: =+G61+H61 -> 0 | J61: ='Draw 10'!J61+'Draw 10'!K61 -> 0 | L61: =+I61-J61-K61 -> 0
A62: 40 | B62: =IF(Master!$B62=0,"",Master!$B62) | D62: =IF(Master!$D62=0,"",Master!$D62) | E62: =IF(Master!$E62=0,"",Master!$E62) | F62: =IF(Master!$F62=0,"",Master!$F62) | G62: =Master!G62 -> 0 | H62: ='Draw 10'!H62 -> 0 | I62: =+G62+H62 -> 0 | J62: ='Draw 10'!J62+'Draw 10'!K62 -> 0 | L62: =+I62-J62-K62 -> 0
A63: 41 | B63: =IF(Master!$B63=0,"",Master!$B63) | D63: =IF(Master!$D63=0,"",Master!$D63) | E63: =IF(Master!$E63=0,"",Master!$E63) | F63: =IF(Master!$F63=0,"",Master!$F63) | G63: =Master!G63 -> 0 | H63: ='Draw 10'!H63 -> 0 | I63: =+G63+H63 -> 0 | J63: ='Draw 10'!J63+'Draw 10'!K63 -> 0 | L63: =+I63-J63-K63 -> 0
A64: 42 | B64: =IF(Master!$B64=0,"",Master!$B64) | D64: =IF(Master!$D64=0,"",Master!$D64) | E64: =IF(Master!$E64=0,"",Master!$E64) | F64: =IF(Master!$F64=0,"",Master!$F64) | G64: =Master!G64 -> 0 | H64: ='Draw 10'!H64 -> 0 | I64: =+G64+H64 -> 0 | J64: ='Draw 10'!J64+'Draw 10'!K64 -> 0 | L64: =+I64-J64-K64 -> 0
... A82: 60 | B82: =IF(Master!$B82=0,"",Master!$B82) | D82: =IF(Master!$D82=0,"",Master!$D82) | E82: =IF(Master!$E82=0,"",Master!$E82) | F82: =IF(Master!$F82=0,"",Master!$F82) | G82: =Master!G82 -> 0 | H82: ='Draw 10'!H82 -> 0 | I82: =+G82+H82 -> 0 | J82: ='Draw 10'!J82+'Draw 10'!K82 -> 0 | L82: =+I82-J82-K82 -> 0
F83: Total | G83: =SUM(G53:G82)+G47 -> 1268365.7 | H83: =SUM(H53:H82)+H47 -> 0 | I83: =SUM(I53:I82)+I47 -> 1268365.7 | J83: =SUM(J53:J82)+J47 -> 1134587.9 | K83: =SUM(K53:K82)+K47 -> 0 | L83: =SUM(L53:L82)+L47 -> 133777.78
B84: If this sworn statement is in regard to a residential structure (defined as "an individual residential condominium unit or a residential building containing not more than 2 residential units,
B85: the land on which it is or will be located, and all appurtenances, in which the owner or lessee contracting for the improvement is residing or will reside upon completion of the improvement"), on
B86: receipt of this sworn statement, the owner or lessee, or the owner's or lessee's designee must give notice of its receipt, either in writing, or by telephone, or personally, to each subcontractor,
B87: supplier, and laborer who has provided a Notice of Furnishing under Section 109 or, if a Notice of Furnishing is excused under Section 108 or 108A, to each subcontractor, supplier, and
B88: laborer named in the sworn statement. If a subcontractor, supplier, or laborer who has provided a Notice of Furnishing or who is named in the sworn statement makes a request, the
B89: owner, lessee, or designee shall provide the requester a copy of the sworn statement within 10 business days after receiving the request.
D92: ='Example of Residential SS'!D92
D93: (DEPONENT) | F93: DATE
B95: WARNING TO DEPONENT: A person gives a false sworn statement with intent to defraud is
B96: subject to criminal penalties as provided in Section 110 of the Construction Lien Act, 1980 PA 497, MCL570.1110.
C99: Subscribed and sworn to before me on | E99: (date) by
C101: Notary Public | E101: County, Michigan
C103: My Commission expires: | L103: =IF('Example of Residential SS'!L103=0,"",'Example of Residential SS'!L103)

Sheet Draw 12
A1: OWNER'S SWORN STATEMENT - Draw #12
K2: Title Company File #
B3: Owner: | C3: =+Master!C3 -> Wolven Investments LLC | F3: General Contractor Name: | G3: =+Master!G3 -> Wolven Investments LLC | K3: Phone # | L3: =+Master!L3 -> 0
B4: Address of | F4: Person Submitting: | G4: =+Master!G4 -> Jeff Klaasen | K4: Email address | L4: =+Master!L4 -> 0
B5: Improvements: | C5: =+Master!C5 -> 43 North Phase 2 | G5: (authorized person signing sworn statement) | K5: Cell phone # | L5: =+Master!L5 -> 0
B7: State of Michigan | D7: ) | G7: (2) The following is a statement of each subcontractor and supplier, and laborer for whom payment of wages or fringe benefits and withholdings is due but unpaid, with whom the (contractor) (subcontractor) has (contracted) (subcontracted) for performance under the contract with the owner or lessee of the property, and the amounts due to the persons as of the date of this statement are correctly and fully set forth opposite their names. (3) The contractor has not procured material from, or subcontracted with, any person other than those set forth and owes no money for the improvement other than the sums set forth. (4) I make this statement as the (contractor) (subcontractor) or as ____________________ of the (contractor) (subcontractor) to represent to the owner or lessee of the property and his or her agents that the property is free from claims of construction liens, or the possibility of construction liens, except as specifically set forth in this statement except for claims of construction liens by laborers that may be provided under Section 109 of the Construction Lien Act, 1980 PA 497, MCL 570.1109.
D8: ) ss.
B9: County of: | C9: =+Master!C9 -> Kent | D9: )
B11: =IF(G4=0,"",G4) -> Jeff Klaasen | D11: (deponent), being sworn, states the following:
A12: (1) | B12: =+G3 -> Wolven Investments LLC | D12: is the (contractor) (subcontractor) for an improvement to the following real
B13: property in | C13: =+C9 -> Kent | D13: County, Michigan described as follows:
B16: Name of Subcontractor, Supplier or Laborer | D16: Address of Subcontractor, Supplier or Laborer | E16: Telephone # | F16: Type of Improvement Furnished | G16: Total Contract Price | H16: Adjustment to Contract Amount ( +/ -) | I16: Adjusted Contract Price | J16: Amount Already Paid | K16: Current Request | L16: Balance to Complete
A17: 1 | B17: =IF(Master!$B17=0,"",Master!$B17) -> Jack Dykstra Excavating | D17: =IF(Master!$D17=0,"",Master!$D17) -> 3677 3 Mile Rd., Grand Rapids, MI 49534 | E17: =IF(Master!$E17=0,"",Master!$E17) -> 616-453-4827 | F17: =IF(Master!$F17=0,"",Master!$F17) -> GC Contract Amount | G17: =Master!G17 -> 623097.95 | H17: ='Draw 11'!H17 -> 18535.25 | I17: =+G17+H17 -> 641633.2 | J17: ='Draw 11'!J17+'Draw 11'!K17 -> 641633.2 | L17: =+I17-J17-K17 -> 0
A18: 2 | B18: =IF(Master!$B18=0,"",Master!$B18) | D18: =IF(Master!$D18=0,"",Master!$D18) | E18: =IF(Master!$E18=0,"",Master!$E18) | F18: =IF(Master!$F18=0,"",Master!$F18) | G18: =Master!G18 -> 0 | H18: ='Draw 11'!H18 -> 0 | I18: =+G18+H18 -> 0 | J18: ='Draw 11'!J18+'Draw 11'!K18 -> 0 | L18: =+I18-J18-K18 -> 0
A19: 3 | B19: =IF(Master!$B19=0,"",Master!$B19) -> Roosien & Associaties | D19: =IF(Master!$D19=0,"",Master!$D19) -> 5055 Plainfield Ave., Grand Rapids, MI 49525 | E19: =IF(Master!$E19=0,"",Master!$E19) -> 616-361-7220 | F19: =IF(Master!$F19=0,"",Master!$F19) -> Engineering Services | G19: =Master!G19 -> 62376 | H19: ='Draw 11'!H19 -> 15150 | I19: =+G19+H19 -> 77526 | J19: ='Draw 11'!J19+'Draw 11'!K19 -> 77526 | L19: =+I19-J19-K19 -> 0
A20: 4 | B20: =IF(Master!$B20=0,"",Master!$B20) -> Soils and Structures | D20: =IF(Master!$D20=0,"",Master!$D20) -> 6480 Grand Haven Rd Muskegon MI 49441 | E20: =IF(Master!$E20=0,"",Master!$E20) -> 1-800-933-3959 | F20: =IF(Master!$F20=0,"",Master!$F20) -> Engineering Services | G20: =Master!G20 -> 15930 | H20: ='Draw 11'!H20 -> 0 | I20: =+G20+H20 -> 15930 | J20: ='Draw 11'!J20+'Draw 11'!K20 -> 2535.5 | L20: =+I20-J20-K20 -> 13394.5
A21: 5 | B21: =IF(Master!$B21=0,"",Master!$B21) | D21: =IF(Master!$D21=0,"",Master!$D21) | E21: =IF(Master!$E21=0,"",Master!$E21) | F21: =IF(Master!$F21=0,"",Master!$F21) -> Engineering Services | G21: =Master!G21 -> 21742.22 | H21: ='Draw 11'!H21 -> -15150 | I21: =+G21+H21 -> 6592.22 | J21: ='Draw 11'!J21+'Draw 11'!K21 -> 0 | L21: =+I21-J21-K21 -> 6592.22
A22: 6 | B22: =IF(Master!$B22=0,"",Master!$B22) | D22: =IF(Master!$D22=0,"",Master!$D22) | E22: =IF(Master!$E22=0,"",Master!$E22) | F22: =IF(Master!$F22=0,"",Master!$F22) | G22: =Master!G22 -> 0 | H22: ='Draw 11'!H22 -> 0 | I22: =+G22+H22 -> 0 | J22: ='Draw 11'!J22+'Draw 11'!K22 -> 0 | L22: =+I22-J22-K22 -> 0
A23: 7 | B23: =IF(Master!$B23=0,"",Master!$B23) -> Handicap Sign | D23: =IF(Master!$D23=0,"",Master!$D23) -> 1142 Wealthy St., Grand Rapids, MI 49506 | E23: =IF(Master!$E23=0,"",Master!$E23) -> 616-454-9416 | F23: =IF(Master!$F23=0,"",Master!$F23) -> Common Area Improvements | G23: =Master!G23 -> 424.4 | H23: ='Draw 11'!H23 -> 0 | I23: =+G23+H23 -> 424.4 | J23: ='Draw 11'!J23+'Draw 11'!K23 -> 424.4 | L23: =+I23-J23-K23 -> 0
